Workbook

Sheet Huong_dan
A1: Mục | B1: Hướng dẫn
A2: Mục đích | B2: Checklist bản gốc sinh từ đặc tả API; tất cả endpoint chưa triển khai. Ngày đặc tả 29/10/2026.
A3: Bắt đầu | B3: Lưu một bản sao workbook để theo dõi thực tế. File master sẽ được ghi lại khi chạy npm run api:build.
A4: Cập nhật | B4: Trong API_Checklist: chọn owner/ưu tiên/trạng thái; đánh dấu 8 bước Q:X; ghi ngày bắt đầu/hạn/ngày xong/PR/bằng chứng test.
A5: Tiến độ | B5: Công thức đếm Xong / 8. Không áp dụng vẫn chưa tính xong: ghi lý do và chỉ đặt Xong khi reviewer xác nhận tiêu chí đã được xử lý.
A6: Hoàn thành | B6: Chỉ chọn Hoàn thành khi DTO, auth/scope, nghiệp vụ/giao dịch, unit/integration test, tài liệu và review đã có bằng chứng. Dropdown trạng thái là nhập tay; dashboard đếm trạng thái, tiến độ kỹ thuật ở cột Y.
A7: Ưu tiên | B7: P0: nền tảng và tính đúng giao dịch; P1: tính năng cơ sở tiếp theo; P2: mở rộng/chính sách chưa chốt. Đây là thứ tự đề xuất, có thể thay.
A8: Tổng quan | B8: Dashboard dùng COUNTIF/COUNTIFS/AVERAGE tham chiếu API_Checklist. Excel tính lại khi mở; workbook chứa công thức, lọc, cố định hàng/cột, dropdown và liên kết trang.
A9: Các sheet | B9: Luong_Nghiep_vu truy vết đủ 47 luồng; Rang_buoc giữ rule nguồn; DTO_Fields giữ đầu vào; Du_lieu lấy từ SQL thật, gồm ALTER; Quyet_dinh liệt kê phần cần chốt.
A10: Phạm vi | B10: Không có backend/cổng thanh toán đã triển khai. Stored procedure có sẵn vẫn cần API/controller/auth/mapping/lỗi/tests; route import/realtime có phụ thuộc riêng.
A11: Tệp liên quan | B11: api-guide.html ở thư mục gốc; docs/api-catalog.json là dữ liệu chung. Mở trang bằng file trực tiếp không cần server; file Excel được tải từ nút trên trang.
A12: Nguồn | B12: business-guide.js; docs/business-rules.md; app.js; house-rights.js; database/schema.sql. Hash nguồn có trong api-catalog.json.
A13: Đồng bộ | B13: node scripts/build-api-guide.cjs (cần Node 22+ và Python 3); npm run api:check kiểm tra dữ liệu/sự tồn tại và cấu trúc Excel. Không chạy migration lên CSDL.

Sheet Tong_quan
A1: Chỉ số / nhóm | B1: Giá trị | C1: Diễn giải / đã xong
A2: Ngày đặc tả | B2: 2026-10-29 | C2: Bản đề xuất; chưa có backend
A3: Tổng API | B3: 176 | C3: Một hàng = một method + path
A4: Tổng luồng | B4: 47 | C4: Gồm các luồng không phải HTTP
A5: Tổng bảng SQL | B5: 43 | C5: Tạo từ schema hiện tại
A6: Hoàn thành | B6: =COUNTIF(API_Checklist!P2:P177,"Hoàn thành") -> 0 | C6: Trạng thái nhập tay
A7: Đang làm | B7: =COUNTIF(API_Checklist!P2:P177,"Đang làm") -> 0
A8: Bị chặn | B8: =COUNTIF(API_Checklist!P2:P177,"Bị chặn") -> 0
A9: Chưa làm | B9: =COUNTIF(API_Checklist!P2:P177,"Chưa làm") -> 176
A10: Chờ review | B10: =COUNTIF(API_Checklist!P2:P177,"Chờ review") -> 0
A11: Tiến độ kỹ thuật TB | B11: =AVERAGE(API_Checklist!Y2:Y177) -> 0 | C11: Đếm 8 bước / endpoint
A12: Hoàn thành nhưng thiếu bước | B12: =COUNTIFS(API_Checklist!P2:P177,"Hoàn thành",API_Checklist!Y2:Y177,"<1") -> 0 | C12: Cần review lại trước nghiệm thu
A13: Theo nhóm | B13: Số API | C13: Đã hoàn thành
A14: Tài khoản & xác minh | B14: =COUNTIF(API_Checklist!B2:B177,A14) -> 28 | C14: =COUNTIFS(API_Checklist!B2:B177,A14,API_Checklist!P2:P177,"Hoàn thành") -> 0
A15: Nhà, quyền cho thuê & phòng | B15: =COUNTIF(API_Checklist!B2:B177,A15) -> 22 | C15: =COUNTIFS(API_Checklist!B2:B177,A15,API_Checklist!P2:P177,"Hoàn thành") -> 0
A16: Tin đăng & tìm phòng | B16: =COUNTIF(API_Checklist!B2:B177,A16) -> 12 | C16: =COUNTIFS(API_Checklist!B2:B177,A16,API_Checklist!P2:P177,"Hoàn thành") -> 0
A17: Hồ sơ & kết nối ở ghép | B17: =COUNTIF(API_Checklist!B2:B177,A17) -> 14 | C17: =COUNTIFS(API_Checklist!B2:B177,A17,API_Checklist!P2:P177,"Hoàn thành") -> 0
A18: Tin nhắn & thông báo | B18: =COUNTIF(API_Checklist!B2:B177,A18) -> 15 | C18: =COUNTIFS(API_Checklist!B2:B177,A18,API_Checklist!P2:P177,"Hoàn thành") -> 0
A19: Hẹn xem & quyết định thuê | B19: =COUNTIF(API_Checklist!B2:B177,A19) -> 10 | C19: =COUNTIFS(API_Checklist!B2:B177,A19,API_Checklist!P2:P177,"Hoàn thành") -> 0
A20: Hợp đồng & vào ở | B20: =COUNTIF(API_Checklist!B2:B177,A20) -> 13 | C20: =COUNTIFS(API_Checklist!B2:B177,A20,API_Checklist!P2:P177,"Hoàn thành") -> 0
A21: Người ở & đại diện | B21: =COUNTIF(API_Checklist!B2:B177,A21) -> 15 | C21: =COUNTIFS(API_Checklist!B2:B177,A21,API_Checklist!P2:P177,"Hoàn thành") -> 0
A22: Gia hạn, đổi phòng, kết thúc | B22: =COUNTIF(API_Checklist!B2:B177,A22) -> 8 | C22: =COUNTIFS(API_Checklist!B2:B177,A22,API_Checklist!P2:P177,"Hoàn thành") -> 0
A23: Dịch vụ & hóa đơn | B23: =COUNTIF(API_Checklist!B2:B177,A23) -> 16 | C23: =COUNTIFS(API_Checklist!B2:B177,A23,API_Checklist!P2:P177,"Hoàn thành") -> 0
A24: Đánh giá & quản trị | B24: =COUNTIF(API_Checklist!B2:B177,A24) -> 18 | C24: =COUNTIFS(API_Checklist!B2:B177,A24,API_Checklist!P2:P177,"Hoàn thành") -> 0
A25: Dữ liệu & tích hợp | B25: =COUNTIF(API_Checklist!B2:B177,A25) -> 5 | C25: =COUNTIFS(API_Checklist!B2:B177,A25,API_Checklist!P2:P177,"Hoàn thành") -> 0

Sheet API_Checklist
A1: Mã API | B1: Nhóm | C1: Luồng liên quan | D1: Method | E1: Endpoint | F1: Chức năng | G1: Quyền truy cập | H1: Ưu tiên | I1: Phụ thuộc / quyết định | J1: SQL / adapter | K1: Request / ràng buộc | L1: Response data | M1: Logic nghiệp vụ | N1: Lỗi cần kiểm tra | O1: Người phụ trách | P1: Trạng thái | Q1: Thiết kế | R1: DTO / Validate | S1: Auth / Scope | T1: Logic / SQL | U1: Unit test | V1: Integration test | W1: Tài liệu | X1: Review | Y1: Tiến độ | Z1: Ngày bắt đầu | AA1: Hạn hoàn thành | AB1: Ngày xong | AC1: PR / commit | AD1: Tiêu chí nghiệm thu | AE1: Bằng chứng test / ghi chú | AF1: Liên kết trang
A2: API-001 | B2: Tài khoản & xác minh | C2: account-access | D2: POST | E2: /api/v1/auth/register | F2: Đăng ký tài khoản người thuê | G2: PUBLIC | H2: P0 | I2: D09: idempotency store nếu chưa có khóa tự nhiên | J2: SERVICE: cần triển khai giao dịch backend | K2: fullName: string (bắt buộc) — 1–150 ký tự. email: string (tùy chọn) — Email chuẩn hóa, ≤150, duy nhất. phoneNumber: string (tùy chọn) — Chuẩn hóa số điện thoại, ≤20, duy nhất. password: string (bắt buộc) — Chính sách mật khẩu backend; không log/lưu nguyên văn. | L2: User {id,fullName,roles,status}; không trả passwordHash | M2: Ít nhất một email/phone; transaction tạo users + tenants + personal_profiles. Không nhận ADMIN/LANDLORD từ body. | N2: 400 BAD_REQUEST 404 RESOURCE_NOT_FOUND 409 STATE_CONFLICT 409 IDEMPOTENCY_KEY_REUSED 422 VALIDATION_ERROR 409 CONTACT_ALREADY_USED 422 CONTACT_REQUIRED | P2: Chưa làm | Q2: Chưa | R2: Chưa | S2: Chưa | T2: Chưa | U2: Chưa | V2: Chưa | W2: Chưa | X2: Chưa | Y2: =COUNTIF(Q2:X2,"Xong")/8 -> 0 | AD2: Happy path: Đăng ký tài khoản người thuê; kiểm tra User {id,fullName,roles,status}; không trả passwordHash. Đầu vào sai/ID ẩn: không lộ dữ liệu riêng tư. Ràng buộc: Email và số điện thoại có khóa duy nhất; phải có ít nhất một thông tin liên hệ. Vai trò chính thuộc TENANT / LANDLORD / ADMIN. Gửi lặp cùng khóa trả kết quả cũ; cùng khóa khác payload trả 409; hai request tranh cùng tài nguyên không vượt hạn mức. Kiểm tra lỗi DB/provider không để lại cập nhật dở hoặc trả thành công giả. | AF2: Mở đặc tả
A3: API-002 | B3: Tài khoản & xác minh | C3: account-access | D3: POST | E3: /api/v1/auth/login | F3: Đăng nhập và mở phiên | G3: PUBLIC | H3: P0 | I3: D09: idempotency store nếu chưa có khóa tự nhiên | J3: SERVICE: cần triển khai giao dịch backend | K3: identifier: string (bắt buộc) — Email hoặc điện thoại đã chuẩn hóa. password: string (bắt buộc) — So sánh hash an toàn. | L3: Session {accessToken,expiresAt,user}; refresh cookie HttpOnly | M3: Chặn LOCKED/DISABLED; rate limit; tạo auth_sessions, lưu hash refresh token. Access token gắn sessionKey. Không dùng bộ chuyển vai trò demo làm xác thực. | N3: 400 BAD_REQUEST 404 RESOURCE_NOT_FOUND 409 STATE_CONFLICT 409 IDEMPOTENCY_KEY_REUSED 422 VALIDATION_ERROR 409 CONTACT_ALREADY_USED 422 CONTACT_REQUIRED | P3: Chưa làm | Q3: Chưa | R3: Chưa | S3: Chưa | T3: Chưa | U3: Chưa | V3: Chưa | W3: Chưa | X3: Chưa | Y3: =COUNTIF(Q3:X3,"Xong")/8 -> 0 | AD3: Happy path: Đăng nhập và mở phiên; kiểm tra Session {accessToken,expiresAt,user}; refresh cookie HttpOnly. Đầu vào sai/ID ẩn: không lộ dữ liệu riêng tư. Ràng buộc: Email và số điện thoại có khóa duy nhất; phải có ít nhất một thông tin liên hệ. Vai trò chính thuộc TENANT / LANDLORD / ADMIN. Gửi lặp cùng khóa trả kết quả cũ; cùng khóa khác payload trả 409; hai request tranh cùng tài nguyên không vượt hạn mức. Kiểm tra lỗi DB/provider không để lại cập nhật dở hoặc trả thành công giả. | AF3: Mở đặc tả
A4: API-003 | B4: Tài khoản & xác minh | C4: account-access | D4: GET | E4: /api/v1/me | F4: Đọc tài khoản và các vai trò thực | G4: USER: tài khoản ACTIVE; chỉ dữ liệu của mình | H4: P0 | I4: Middleware auth/session/role + object scope | J4: READ: truy vấn có scope quyền | K4: Không có JSON body | L4: User {id,fullName,email,phoneNumber,roles,status,profile} | M4: Roles lấy từ tenants/landlords/admins. role trong users là vai trò hiển thị; mỗi request kiểm tra lại quyền đối tượng. | N4: 400 BAD_REQUEST 401 UNAUTHENTICATED 403 FORBIDDEN 404 RESOURCE_NOT_FOUND | P4: Chưa làm | Q4: Chưa | R4: Chưa | S4: Chưa | T4: Chưa | U4: Chưa | V4: Chưa | W4: Chưa | X4: Chưa | Y4: =COUNTIF(Q4:X4,"Xong")/8 -> 0 | AD4: Happy path: Đọc tài khoản và các vai trò thực; kiểm tra User {id,fullName,email,phoneNumber,roles,status,profile}. Thiếu phiên/phiên revoked/actor LOCKED và actor khác chủ hoặc khác participant phải bị chặn. Ràng buộc: Email và số điện thoại có khóa duy nhất; phải có ít nhất một thông tin liên hệ. Vai trò chính thuộc TENANT / LANDLORD / ADMIN. Phân trang/lọc đúng scope; dữ liệu riêng tư bị loại trên server, không chỉ ẩn UI. Kiểm tra lỗi DB/provider không để lại cập nhật dở hoặc trả thành công giả. | AF4: Mở đặc tả
A5: API-004 | B5: Tài khoản & xác minh | C5: profile | D5: PATCH | E5: /api/v1/me/profile | F5: Cập nhật hồ sơ cá nhân | G5: USER: tài khoản ACTIVE; chỉ dữ liệu của mình | H5: P0 | I5: Middleware auth/session/role + object scope D09: idempotency store nếu chưa có khóa tự nhiên | J5: SERVICE: cần triển khai giao dịch backend | K5: fullName: string (tùy chọn) — 1–150 ký tự sau trim. address: string (tùy chọn) — Tối đa 500 ký tự. gender: string (tùy chọn) — Tối đa 30 ký tự. occupation: string (tùy chọn) — Tối đa 150 ký tự. university: string (tùy chọn) — Tối đa 200 ký tự. bio: string (tùy chọn) — Giới hạn API cần cấu hình; SQL TEXT. avatarFileId: id (tùy chọn) — Tệp AVATAR ACTIVE thuộc người dùng. | L5: PersonalProfile sau cập nhật | M5: Chỉ cập nhật whitelist; không sửa role/status/contact xác thực bằng form profile. Tệp avatar phải thuộc mình. Ghi users.full_name và personal_profiles trong một giao dịch. | N5: 400 BAD_REQUEST 401 UNAUTHENTICATED 403 FORBIDDEN 404 RESOURCE_NOT_FOUND 409 STATE_CONFLICT 409 IDEMPOTENCY_KEY_REUSED 422 VALIDATION_ERROR 422 PROFILE_INVALID | P5: Chưa làm | Q5: Chưa | R5: Chưa | S5: Chưa | T5: Chưa | U5: Chưa | V5: Chưa | W5: Chưa | X5: Chưa | Y5: =COUNTIF(Q5:X5,"Xong")/8 -> 0 | AD5: Happy path: Cập nhật hồ sơ cá nhân; kiểm tra PersonalProfile sau cập nhật. Thiếu phiên/phiên revoked/actor LOCKED và actor khác chủ hoặc khác participant phải bị chặn. Ràng buộc: personal_profiles có một hồ sơ cho mỗi user; thông tin cá nhân không mặc định là dữ liệu công khai. Gửi lặp cùng khóa trả kết quả cũ; cùng khóa khác payload trả 409; hai request tranh cùng tài nguyên không vượt hạn mức. Kiểm tra lỗi DB/provider không để lại cập nhật dở hoặc trả thành công giả. | AF5: Mở đặc tả
A6: API-005 | B6: Tài khoản & xác minh | C6: profile | D6: PATCH | E6: /api/v1/me/notification-settings | F6: Cấu hình kênh thông báo | G6: USER: tài khoản ACTIVE; chỉ dữ liệu của mình | H6: P0 | I6: Middleware auth/session/role + object scope D09: idempotency store nếu chưa có khóa tự nhiên D04 | J6: SERVICE: cần triển khai giao dịch backend | K6: inAppEnabled: boolean (tùy chọn) — Ít nhất một field. emailEnabled: boolean (tùy chọn) — Chỉ bật kênh backend hỗ trợ. pushEnabled: boolean (tùy chọn) — Push delivery cần provider/device registry bổ sung. | L6: Settings {inAppEnabled,emailEnabled,pushEnabled} | M6: Cập nhật flags users. Việc bật flag không đồng nghĩa có dịch vụ email/push hiện tại. | N6: 400 BAD_REQUEST 401 UNAUTHENTICATED 403 FORBIDDEN 404 RESOURCE_NOT_FOUND 409 STATE_CONFLICT 409 IDEMPOTENCY_KEY_REUSED 422 VALIDATION_ERROR 422 PROFILE_INVALID | P6: Chưa làm | Q6: Chưa | R6: Chưa | S6: Chưa | T6: Chưa | U6: Chưa | V6: Chưa | W6: Chưa | X6: Chưa | Y6: =COUNTIF(Q6:X6,"Xong")/8 -> 0 | AD6: Happy path: Cấu hình kênh thông báo; kiểm tra Settings {inAppEnabled,emailEnabled,pushEnabled}. Thiếu phiên/phiên revoked/actor LOCKED và actor khác chủ hoặc khác participant phải bị chặn. Ràng buộc: personal_profiles có một hồ sơ cho mỗi user; thông tin cá nhân không mặc định là dữ liệu công khai. Gửi lặp cùng khóa trả kết quả cũ; cùng khóa khác payload trả 409; hai request tranh cùng tài nguyên không vượt hạn mức. Kiểm tra lỗi DB/provider không để lại cập nhật dở hoặc trả thành công giả. | AF6: Mở đặc tả
A7: API-006 | B7: Tài khoản & xác minh | C7: identity | D7: POST | E7: /api/v1/me/identity-verifications | F7: Nộp xác minh danh tính người thuê | G7: TENANT: chỉ chính người thuê và tài nguyên được phép | H7: P0 | I7: Middleware auth/session/role + object scope D09: idempotency store nếu chưa có khóa tự nhiên D05 | J7: SERVICE: cần triển khai giao dịch backend | K7: identityNumber: string (bắt buộc) — 1–30 ký tự, xử lý như dữ liệu riêng tư. identityFileId: id (bắt buộc) — Tệp IDENTITY PRIVATE ACTIVE thuộc người nộp. | L7: IdentityVerification {id,status:PENDING,createdAt} | M7: Chỉ một PENDING/người; lưu số giấy tờ, tệp và hạn lưu theo chính sách. Không công khai giấy tờ. | N7: 400 BAD_REQUEST 401 UNAUTHENTICATED 403 FORBIDDEN 404 RESOURCE_NOT_FOUND 409 STATE_CONFLICT 409 IDEMPOTENCY_KEY_REUSED 422 VALIDATION_ERROR 409 PENDING_VERIFICATION_EXISTS 422 FILE_INVALID | P7: Chưa làm | Q7: Chưa | R7: Chưa | S7: Chưa | T7: Chưa | U7: Chưa | V7: Chưa | W7: Chưa | X7: Chưa | Y7: =COUNTIF(Q7:X7,"Xong")/8 -> 0 | AD7: Happy path: Nộp xác minh danh tính người thuê; kiểm tra IdentityVerification {id,status:PENDING,createdAt}. Thiếu phiên/phiên revoked/actor LOCKED và actor khác chủ hoặc khác participant phải bị chặn. Ràng buộc: Mỗi người chỉ có một hồ sơ xác minh cùng loại đang PENDING; quyết định duyệt/từ chối lưu người và thời điểm. Gửi lặp cùng khóa trả kết quả cũ; cùng khóa khác payload trả 409; hai request tranh cùng tài nguyên không vượt hạn mức. Kiểm tra lỗi DB/provider không để lại cập nhật dở hoặc trả thành công giả. | AF7: Mở đặc tả
A8: API-007 | B8: Tài khoản & xác minh | C8: identity | D8: GET | E8: /api/v1/me/identity-verifications | F8: Lịch sử xác minh của mình | G8: TENANT: chỉ chính người thuê và tài nguyên được phép | H8: P0 | I8: Middleware auth/session/role + object scope | J8: READ: truy vấn có scope quyền | K8: Không có JSON body | L8: IdentityVerification[]; che số giấy tờ, không trả URL kho | M8: Chỉ tenant_id = actor; giấy tờ mở bằng API file có quyền. | N8: 400 BAD_REQUEST 401 UNAUTHENTICATED 403 FORBIDDEN 404 RESOURCE_NOT_FOUND 422 VALIDATION_ERROR | P8: Chưa làm | Q8: Chưa | R8: Chưa | S8: Chưa | T8: Chưa | U8: Chưa | V8: Chưa | W8: Chưa | X8: Chưa | Y8: =COUNTIF(Q8:X8,"Xong")/8 -> 0 | AD8: Happy path: Lịch sử xác minh của mình; kiểm tra IdentityVerification[]; che số giấy tờ, không trả URL kho. Thiếu phiên/phiên revoked/actor LOCKED và actor khác chủ hoặc khác participant phải bị chặn. Ràng buộc: Mỗi người chỉ có một hồ sơ xác minh cùng loại đang PENDING; quyết định duyệt/từ chối lưu người và thời điểm. Phân trang/lọc đúng scope; dữ liệu riêng tư bị loại trên server, không chỉ ẩn UI. Kiểm tra lỗi DB/provider không để lại cập nhật dở hoặc trả thành công giả. | AF8: Mở đặc tả
A9: API-008 | B9: Tài khoản & xác minh | C9: identity | D9: POST | E9: /api/v1/me/identity-verifications/{verificationId}/withdraw | F9: Rút hồ sơ danh tính đang chờ | G9: TENANT: chỉ chính người thuê và tài nguyên được phép | H9: P0 | I9: Middleware auth/session/role + object scope D09: idempotency store nếu chưa có khóa tự nhiên | J9: SERVICE: cần triển khai giao dịch backend | K9: Không có JSON body | L9: IdentityVerification {id,status:WITHDRAWN} | M9: Khóa hồ sơ thuộc mình; chỉ PENDING → WITHDRAWN; giữ lịch sử. | N9: 400 BAD_REQUEST 401 UNAUTHENTICATED 403 FORBIDDEN 404 RESOURCE_NOT_FOUND 409 STATE_CONFLICT 409 IDEMPOTENCY_KEY_REUSED 422 VALIDATION_ERROR 409 PENDING_VERIFICATION_EXISTS 422 FILE_INVALID | P9: Chưa làm | Q9: Chưa | R9: Chưa | S9: Chưa | T9: Chưa | U9: Chưa | V9: Chưa | W9: Chưa | X9: Chưa | Y9: =COUNTIF(Q9:X9,"Xong")/8 -> 0 | AD9: Happy path: Rút hồ sơ danh tính đang chờ; kiểm tra IdentityVerification {id,status:WITHDRAWN}. Thiếu phiên/phiên revoked/actor LOCKED và actor khác chủ hoặc khác participant phải bị chặn. Ràng buộc: Mỗi người chỉ có một hồ sơ xác minh cùng loại đang PENDING; quyết định duyệt/từ chối lưu người và thời điểm. Gửi lặp cùng khóa trả kết quả cũ; cùng khóa khác payload trả 409; hai request tranh cùng tài nguyên không vượt hạn mức. Kiểm tra lỗi DB/provider không để lại cập nhật dở hoặc trả thành công giả. | AF9: Mở đặc tả
A10: API-009 | B10: Tài khoản & xác minh | C10: identity | D10: POST | E10: /api/v1/me/landlord-verifications | F10: Xin cấp vai trò chủ trọ | G10: USER: tài khoản ACTIVE; chỉ dữ liệu của mình | H10: P0 | I10: Middleware auth/session/role + object scope D09: idempotency store nếu chưa có khóa tự nhiên | J10: SERVICE: cần triển khai giao dịch backend | K10: identityNumber: string (bắt buộc) — 1–30 ký tự, xử lý như dữ liệu riêng tư. identityFileId: id (bắt buộc) — Tệp IDENTITY PRIVATE ACTIVE thuộc người nộp. | L10: LandlordVerification {id,status:PENDING} | M10: applicant_user_id lấy từ phiên. Chỉ một PENDING; tệp IDENTITY PRIVATE thuộc mình. Duyệt tài khoản không tự xác minh nhà. | N10: 400 BAD_REQUEST 401 UNAUTHENTICATED 403 FORBIDDEN 404 RESOURCE_NOT_FOUND 409 STATE_CONFLICT 409 IDEMPOTENCY_KEY_REUSED 422 VALIDATION_ERROR 409 PENDING_VERIFICATION_EXISTS 422 FILE_INVALID | P10: Chưa làm | Q10: Chưa | R10: Chưa | S10: Chưa | T10: Chưa | U10: Chưa | V10: Chưa | W10: Chưa | X10: Chưa | Y10: =COUNTIF(Q10:X10,"Xong")/8 -> 0 | AD10: Happy path: Xin cấp vai trò chủ trọ; kiểm tra LandlordVerification {id,status:PENDING}. Thiếu phiên/phiên revoked/actor LOCKED và actor khác chủ hoặc khác participant phải bị chặn. Ràng buộc: Mỗi người chỉ có một hồ sơ xác minh cùng loại đang PENDING; quyết định duyệt/từ chối lưu người và thời điểm. Gửi lặp cùng khóa trả kết quả cũ; cùng khóa khác payload trả 409; hai request tranh cùng tài nguyên không vượt hạn mức. Kiểm tra lỗi DB/provider không để lại cập nhật dở hoặc trả thành công giả. | AF10: Mở đặc tả
A11: API-010 | B11: Tài khoản & xác minh | C11: identity | D11: GET | E11: /api/v1/me/landlord-verifications | F11: Lịch sử hồ sơ xin làm chủ trọ | G11: USER: tài khoản ACTIVE; chỉ dữ liệu của mình | H11: P0 | I11: Middleware auth/session/role + object scope | J11: READ: truy vấn có scope quyền | K11: Không có JSON body | L11: LandlordVerification[] | M11: Chỉ hồ sơ applicant_user_id của mình. | N11: 400 BAD_REQUEST 401 UNAUTHENTICATED 403 FORBIDDEN 404 RESOURCE_NOT_FOUND 422 VALIDATION_ERROR | P11: Chưa làm | Q11: Chưa | R11: Chưa | S11: Chưa | T11: Chưa | U11: Chưa | V11: Chưa | W11: Chưa | X11: Chưa | Y11: =COUNTIF(Q11:X11,"Xong")/8 -> 0 | AD11: Happy path: Lịch sử hồ sơ xin làm chủ trọ; kiểm tra LandlordVerification[]. Thiếu phiên/phiên revoked/actor LOCKED và actor khác chủ hoặc khác participant phải bị chặn. Ràng buộc: Mỗi người chỉ có một hồ sơ xác minh cùng loại đang PENDING; quyết định duyệt/từ chối lưu người và thời điểm. Phân trang/lọc đúng scope; dữ liệu riêng tư bị loại trên server, không chỉ ẩn UI. Kiểm tra lỗi DB/provider không để lại cập nhật dở hoặc trả thành công giả. | AF11: Mở đặc tả
A12: API-011 | B12: Tài khoản & xác minh | C12: identity | D12: POST | E12: /api/v1/me/landlord-verifications/{verificationId}/withdraw | F12: Rút hồ sơ chủ trọ đang chờ | G12: USER: tài khoản ACTIVE; chỉ dữ liệu của mình | H12: P0 | I12: Middleware auth/session/role + object scope D09: idempotency store nếu chưa có khóa tự nhiên | J12: SERVICE: cần triển khai giao dịch backend | K12: Không có JSON body | L12: LandlordVerification {id,status:WITHDRAWN} | M12: Chỉ applicant và hồ sơ PENDING; không thu hồi vai trò đã có. | N12: 400 BAD_REQUEST 401 UNAUTHENTICATED 403 FORBIDDEN 404 RESOURCE_NOT_FOUND 409 STATE_CONFLICT 409 IDEMPOTENCY_KEY_REUSED 422 VALIDATION_ERROR 409 PENDING_VERIFICATION_EXISTS 422 FILE_INVALID | P12: Chưa làm | Q12: Chưa | R12: Chưa | S12: Chưa | T12: Chưa | U12: Chưa | V12: Chưa | W12: Chưa | X12: Chưa | Y12: =COUNTIF(Q12:X12,"Xong")/8 -> 0 | AD12: Happy path: Rút hồ sơ chủ trọ đang chờ; kiểm tra LandlordVerification {id,status:WITHDRAWN}. Thiếu phiên/phiên revoked/actor LOCKED và actor khác chủ hoặc khác participant phải bị chặn. Ràng buộc: Mỗi người chỉ có một hồ sơ xác minh cùng loại đang PENDING; quyết định duyệt/từ chối lưu người và thời điểm. Gửi lặp cùng khóa trả kết quả cũ; cùng khóa khác payload trả 409; hai request tranh cùng tài nguyên không vượt hạn mức. Kiểm tra lỗi DB/provider không để lại cập nhật dở hoặc trả thành công giả. | AF12: Mở đặc tả
A13: API-012 | B13: Tài khoản & xác minh | C13: identity | D13: GET | E13: /api/v1/admin/identity-verifications | F13: Danh sách hồ sơ identity | G13: ADMIN: tài khoản ACTIVE có dòng admins | H13: P0 | I13: Middleware auth/session/role + object scope | J13: READ: truy vấn có scope quyền | K13: Không có JSON body | L13: Verification[]; status,applicant,submittedAt | M13: Lọc status/ngày; không nhúng bytes giấy tờ vào danh sách. | N13: 400 BAD_REQUEST 401 UNAUTHENTICATED 403 FORBIDDEN 404 RESOURCE_NOT_FOUND 422 VALIDATION_ERROR | P13: Chưa làm | Q13: Chưa | R13: Chưa | S13: Chưa | T13: Chưa | U13: Chưa | V13: Chưa | W13: Chưa | X13: Chưa | Y13: =COUNTIF(Q13:X13,"Xong")/8 -> 0 | AD13: Happy path: Danh sách hồ sơ identity; kiểm tra Verification[]; status,applicant,submittedAt. Thiếu phiên/phiên revoked/actor LOCKED và actor khác chủ hoặc khác participant phải bị chặn. Ràng buộc: Mỗi người chỉ có một hồ sơ xác minh cùng loại đang PENDING; quyết định duyệt/từ chối lưu người và thời điểm. Phân trang/lọc đúng scope; dữ liệu riêng tư bị loại trên server, không chỉ ẩn UI. Kiểm tra lỗi DB/provider không để lại cập nhật dở hoặc trả thành công giả. | AF13: Mở đặc tả
... A46: API-045 | B46: Nhà, quyền cho thuê & phòng | C46: rooms | D46: PUT | E46: /api/v1/rooms/{roomId}/capacity | F46: Đổi sức chứa có khóa phòng | G46: LANDLORD: sở hữu nhà/phòng/hợp đồng | H46: P0 | I46: Middleware auth/session/role + object scope D09: idempotency store nếu chưa có khóa tự nhiên | J46: sp_set_room_capacity | K46: capacity: integer (bắt buộc) — >0 và ≥ ACTIVE + PLANNED mở + hold còn hạn. | L46: Room {id,capacity,currentLoad} | M46: API kiểm tra actor ACTIVE rồi gọi procedure, không chỉ đếm phía client. | N46: 400 BAD_REQUEST 401 UNAUTHENTICATED 403 FORBIDDEN 404 RESOURCE_NOT_FOUND 409 STATE_CONFLICT 409 IDEMPOTENCY_KEY_REUSED 422 VALIDATION_ERROR 409 ROOM_NUMBER_EXISTS 422 ROOM_CAPACITY_EXCEEDED 409 ROOM_STILL_OCCUPIED | P46: Chưa làm | Q46: Chưa | R46: Chưa | S46: Chưa | T46: Chưa | U46: Chưa | V46: Chưa | W46: Chưa | X46: Chưa | Y46: =COUNTIF(Q46:X46,"Xong")/8 -> 0 | AD46: Happy path: Đổi sức chứa có khóa phòng; kiểm tra Room {id,capacity,currentLoad}. Thiếu phiên/phiên revoked/actor LOCKED và actor khác chủ hoặc khác participant phải bị chặn. Ràng buộc: Mã phòng duy nhất trong cùng nhà; sức chứa nguyên dương, giá/cọc không âm, diện tích dương. Gửi lặp cùng khóa trả kết quả cũ; cùng khóa khác payload trả 409; hai request tranh cùng tài nguyên không vượt hạn mức. Lỗi giữa giao dịch phải rollback; xác minh không bọc CALL trong transaction của ứng dụng. | AF46: Mở đặc tả
A47: API-046 | B47: Nhà, quyền cho thuê & phòng | C47: room-detail | D47: GET | E47: /api/v1/rooms/{roomId} | F47: Chi tiết phòng theo quyền người xem | G47: PUBLIC | H47: P0 | J47: READ: truy vấn có scope quyền | K47: Không có JSON body | L47: Room {id,area,rentAmount,depositAmount,capacity,status,activeCount,services}; không có danh tính cư dân | M47: Người ngoài chỉ đọc phòng có tin công khai đủ quyền. Chủ/admin xem theo phạm vi được xác thực. Tách số lượng công khai khỏi danh sách người ở. | N47: 400 BAD_REQUEST 404 RESOURCE_NOT_FOUND | P47: Chưa làm | Q47: Chưa | R47: Chưa | S47: Chưa | T47: Chưa | U47: Chưa | V47: Chưa | W47: Chưa | X47: Chưa | Y47: =COUNTIF(Q47:X47,"Xong")/8 -> 0 | AD47: Happy path: Chi tiết phòng theo quyền người xem; kiểm tra Room {id,area,rentAmount,depositAmount,capacity,status,activeCount,services}; không có danh tính cư dân. Đầu vào sai/ID ẩn: không lộ dữ liệu riêng tư. Ràng buộc: Kiểm tra kiểu dữ liệu và quan hệ FK. Phân trang/lọc đúng scope; dữ liệu riêng tư bị loại trên server, không chỉ ẩn UI. Kiểm tra lỗi DB/provider không để lại cập nhật dở hoặc trả thành công giả. | AF47: Mở đặc tả
A48: API-047 | B48: Nhà, quyền cho thuê & phòng | C48: room-detail | D48: GET | E48: /api/v1/rooms/{roomId}/posts | F48: Bài đăng của một phòng | G48: PUBLIC | H48: P0 | J48: READ: truy vấn có scope quyền | K48: Không có JSON body | L48: Post[]; chủ/admin thêm pendingReviewCount và quota=3 | M48: Public chỉ từ v_public_house_posts; chủ sở hữu/admin có thể xem mọi trạng thái của phòng có quyền. Không trả nháp cho người thuê. | N48: 400 BAD_REQUEST 404 RESOURCE_NOT_FOUND 422 VALIDATION_ERROR | P48: Chưa làm | Q48: Chưa | R48: Chưa | S48: Chưa | T48: Chưa | U48: Chưa | V48: Chưa | W48: Chưa | X48: Chưa | Y48: =COUNTIF(Q48:X48,"Xong")/8 -> 0 | AD48: Happy path: Bài đăng của một phòng; kiểm tra Post[]; chủ/admin thêm pendingReviewCount và quota=3. Đầu vào sai/ID ẩn: không lộ dữ liệu riêng tư. Ràng buộc: Kiểm tra kiểu dữ liệu và quan hệ FK. Phân trang/lọc đúng scope; dữ liệu riêng tư bị loại trên server, không chỉ ẩn UI. Kiểm tra lỗi DB/provider không để lại cập nhật dở hoặc trả thành công giả. | AF48: Mở đặc tả
A49: API-048 | B49: Nhà, quyền cho thuê & phòng | C49: room-detail | D49: GET | E49: /api/v1/rooms/{roomId}/residents | F49: Người đang ở trong phòng | G49: LANDLORD: sở hữu nhà/phòng/hợp đồng hoặc ADMIN | H49: P0 | I49: Middleware auth/session/role + object scope | J49: READ: truy vấn có scope quyền | K49: Không có JSON body | L49: Resident[] {id,fullName,isRepresentative,moveInDate,reconciliationRequired} | M49: Chỉ ACTIVE, kể cả contract đã đóng sai; không trộn PLANNED/LEFT/CANCELLED; trả 403 cho người ngoài. | N49: 400 BAD_REQUEST 401 UNAUTHENTICATED 403 FORBIDDEN 404 RESOURCE_NOT_FOUND 422 VALIDATION_ERROR | P49: Chưa làm | Q49: Chưa | R49: Chưa | S49: Chưa | T49: Chưa | U49: Chưa | V49: Chưa | W49: Chưa | X49: Chưa | Y49: =COUNTIF(Q49:X49,"Xong")/8 -> 0 | AD49: Happy path: Người đang ở trong phòng; kiểm tra Resident[] {id,fullName,isRepresentative,moveInDate,reconciliationRequired}. Thiếu phiên/phiên revoked/actor LOCKED và actor khác chủ hoặc khác participant phải bị chặn. Ràng buộc: Kiểm tra kiểu dữ liệu và quan hệ FK. Phân trang/lọc đúng scope; dữ liệu riêng tư bị loại trên server, không chỉ ẩn UI. Kiểm tra lỗi DB/provider không để lại cập nhật dở hoặc trả thành công giả. | AF49: Mở đặc tả
A50: API-049 | B50: Nhà, quyền cho thuê & phòng | C50: room-detail | D50: GET | E50: /api/v1/rooms/{roomId}/services | F50: Dịch vụ hiệu lực của phòng | G50: PUBLIC | H50: P0 | J50: READ: active_room_services | K50: Không có JSON body | L50: EffectiveService[] {name,unit,method,unitPrice} | M50: Kiểm tra quyền xem phòng; active cả house_services và room_services; COALESCE override, 0 là giá hợp lệ. | N50: 400 BAD_REQUEST 404 RESOURCE_NOT_FOUND 422 VALIDATION_ERROR | P50: Chưa làm | Q50: Chưa | R50: Chưa | S50: Chưa | T50: Chưa | U50: Chưa | V50: Chưa | W50: Chưa | X50: Chưa | Y50: =COUNTIF(Q50:X50,"Xong")/8 -> 0 | AD50: Happy path: Dịch vụ hiệu lực của phòng; kiểm tra EffectiveService[] {name,unit,method,unitPrice}. Đầu vào sai/ID ẩn: không lộ dữ liệu riêng tư. Ràng buộc: Kiểm tra kiểu dữ liệu và quan hệ FK. Phân trang/lọc đúng scope; dữ liệu riêng tư bị loại trên server, không chỉ ẩn UI. Kiểm tra lỗi DB/provider không để lại cập nhật dở hoặc trả thành công giả. | AF50: Mở đặc tả
A51: API-050 | B51: Tin đăng & tìm phòng | C51: submit-post | D51: GET | E51: /api/v1/landlord/posts | F51: Danh sách tin chủ trọ quản lý | G51: LANDLORD: sở hữu nhà/phòng/hợp đồng | H51: P1 | I51: Middleware auth/session/role + object scope | J51: READ: truy vấn có scope quyền | K51: Không có JSON body | L51: Post[] {id,roomId,status,contentVersion,pendingReviewCount} | M51: Lọc đúng các phòng thuộc mình; trả đủ mọi trạng thái. | N51: 400 BAD_REQUEST 401 UNAUTHENTICATED 403 FORBIDDEN 404 RESOURCE_NOT_FOUND 422 VALIDATION_ERROR | P51: Chưa làm | Q51: Chưa | R51: Chưa | S51: Chưa | T51: Chưa | U51: Chưa | V51: Chưa | W51: Chưa | X51: Chưa | Y51: =COUNTIF(Q51:X51,"Xong")/8 -> 0 | AD51: Happy path: Danh sách tin chủ trọ quản lý; kiểm tra Post[] {id,roomId,status,contentVersion,pendingReviewCount}. Thiếu phiên/phiên revoked/actor LOCKED và actor khác chủ hoặc khác participant phải bị chặn. Ràng buộc: Một phòng tối đa 3 PENDING_REVIEW qua slot 1–3, UNIQUE (room_id,pending_review_slot) và CHECK. Tổng bài và số bài APPROVED không giới hạn. Phân trang/lọc đúng scope; dữ liệu riêng tư bị loại trên server, không chỉ ẩn UI. Kiểm tra lỗi DB/provider không để lại cập nhật dở hoặc trả thành công giả. | AF51: Mở đặc tả
A52: API-051 | B52: Tin đăng & tìm phòng | C52: submit-post | D52: POST | E52: /api/v1/posts | F52: Tạo bài mới và gửi duyệt | G52: LANDLORD: sở hữu nhà/phòng/hợp đồng | H52: P0 | I52: Middleware auth/session/role + object scope D09: idempotency store nếu chưa có khóa tự nhiên D07 | J52: sp_submit_post | K52: roomId: id (bắt buộc) — Phòng thuộc chủ trọ. Khi sửa giữ nguyên roomId. title: string (bắt buộc) — 1–200 ký tự sau trim. content: string (bắt buộc) — Không trống; posts.content là TEXT (≤65.535 bytes UTF-8), dù tham số procedure LONGTEXT. API kiểm tra byte length trước ghi. imageFileIds: id[] (bắt buộc) — Ít nhất 1 tệp POST_IMAGE ACTIVE của chủ trọ; thứ tự mảng là thứ tự ảnh. amenities: string[] (tùy chọn) — Chuẩn hóa, loại trùng; mỗi amenity ≤100 ký tự theo SQL; giới hạn số mục API cần cấu hình. | L52: Post {id,status:PENDING_REVIEW,contentVersion,pendingReviewCount} | M52: Gọi sp_submit_post(p_post=NULL) cấp slot 1–3, nhà chưa xác minh vẫn nộp chờ được. sp_submit_post không ghi ảnh/amenities: cần mở rộng thủ tục trước khi coi toàn bộ body là nguyên tử. Không tạo post nửa chừng rồi báo thành công. | N52: 400 BAD_REQUEST 401 UNAUTHENTICATED 403 FORBIDDEN 404 RESOURCE_NOT_FOUND 409 STATE_CONFLICT 409 IDEMPOTENCY_KEY_REUSED 422 VALIDATION_ERROR 409 POST_REVIEW_QUOTA_REACHED 409 POST_VERSION_CHANGED 422 POST_IMAGE_INVALID | P52: Chưa làm | Q52: Chưa | R52: Chưa | S52: Chưa | T52: Chưa | U52: Chưa | V52: Chưa | W52: Chưa | X52: Chưa | Y52: =COUNTIF(Q52:X52,"Xong")/8 -> 0 | AD52: Happy path: Tạo bài mới và gửi duyệt; kiểm tra Post {id,status:PENDING_REVIEW,contentVersion,pendingReviewCount}. Thiếu phiên/phiên revoked/actor LOCKED và actor khác chủ hoặc khác participant phải bị chặn. Ràng buộc: Một phòng tối đa 3 PENDING_REVIEW qua slot 1–3, UNIQUE (room_id,pending_review_slot) và CHECK. Tổng bài và số bài APPROVED không giới hạn. Gửi lặp cùng khóa trả kết quả cũ; cùng khóa khác payload trả 409; hai request tranh cùng tài nguyên không vượt hạn mức. Lỗi giữa giao dịch phải rollback; xác minh không bọc CALL trong transaction của ứng dụng. | AF52: Mở đặc tả
A53: API-052 | B53: Tin đăng & tìm phòng | C53: submit-post | D53: PATCH | E53: /api/v1/posts/{postId} | F53: Sửa đúng bài và gửi duyệt lại | G53: LANDLORD: sở hữu nhà/phòng/hợp đồng | H53: P1 | I53: Middleware auth/session/role + object scope D09: idempotency store nếu chưa có khóa tự nhiên D07 D15: kiểm tra version trong khóa | J53: sp_submit_post | K53: roomId: id (tùy chọn) — Phòng thuộc chủ trọ. Khi sửa giữ nguyên roomId. title: string (tùy chọn) — 1–200 ký tự sau trim. content: string (tùy chọn) — Không trống; posts.content là TEXT (≤65.535 bytes UTF-8), dù tham số procedure LONGTEXT. API kiểm tra byte length trước ghi. imageFileIds: id[] (tùy chọn) — Ít nhất 1 tệp POST_IMAGE ACTIVE của chủ trọ; thứ tự mảng là thứ tự ảnh. amenities: string[] (tùy chọn) — Chuẩn hóa, loại trùng; mỗi amenity ≤100 ký tự theo SQL; giới hạn số mục API cần cấu hình. | L53: Post {id,status:PENDING_REVIEW,contentVersion} | M53: Giữ roomId. If-Match → p_expected_version. Sửa bài PENDING giữ slot, bài khác cần slot trống. Ảnh/amenities cần mở rộng procedure cùng transaction; không tác động bài khác. | N53: 400 BAD_REQUEST 401 UNAUTHENTICATED 403 FORBIDDEN 404 RESOURCE_NOT_FOUND 409 STATE_CONFLICT 409 IDEMPOTENCY_KEY_REUSED 422 VALIDATION_ERROR 409 POST_REVIEW_QUOTA_REACHED 409 POST_VERSION_CHANGED 422 POST_IMAGE_INVALID | P53: Chưa làm | Q53: Chưa | R53: Chưa | S53: Chưa | T53: Chưa | U53: Chưa | V53: Chưa | W53: Chưa | X53: Chưa | Y53: =COUNTIF(Q53:X53,"Xong")/8 -> 0 | AD53: Happy path: Sửa đúng bài và gửi duyệt lại; kiểm tra Post {id,status:PENDING_REVIEW,contentVersion}. Thiếu phiên/phiên revoked/actor LOCKED và actor khác chủ hoặc khác participant phải bị chặn. Ràng buộc: Một phòng tối đa 3 PENDING_REVIEW qua slot 1–3, UNIQUE (room_id,pending_review_slot) và CHECK. Tổng bài và số bài APPROVED không giới hạn. Gửi lặp cùng khóa trả kết quả cũ; cùng khóa khác payload trả 409; hai request tranh cùng tài nguyên không vượt hạn mức. Lỗi giữa giao dịch phải rollback; xác minh không bọc CALL trong transaction của ứng dụng. | AF53: Mở đặc tả
A54: API-053 | B54: Tin đăng & tìm phòng | C54: moderate-post | D54: GET | E54: /api/v1/admin/posts | F54: Hàng đợi kiểm duyệt tin | G54: ADMIN: tài khoản ACTIVE có dòng admins | H54: P1 | I54: Middleware auth/session/role + object scope | J54: READ: truy vấn có scope quyền | K54: Không có JSON body | L54: Post[] kèm trạng thái quyền nhà | M54: Lọc trạng thái; đọc tin và ảnh riêng phục vụ kiểm duyệt, không dùng route public. | N54: 400 BAD_REQUEST 401 UNAUTHENTICATED 403 FORBIDDEN 404 RESOURCE_NOT_FOUND 422 VALIDATION_ERROR | P54: Chưa làm | Q54: Chưa | R54: Chưa | S54: Chưa | T54: Chưa | U54: Chưa | V54: Chưa | W54: Chưa | X54: Chưa | Y54: =COUNTIF(Q54:X54,"Xong")/8 -> 0 | AD54: Happy path: Hàng đợi kiểm duyệt tin; kiểm tra Post[] kèm trạng thái quyền nhà. Thiếu phiên/phiên revoked/actor LOCKED và actor khác chủ hoặc khác participant phải bị chặn. Ràng buộc: moderation_actions lưu đối tượng, người xử lý, lý do và bản chụp trước/sau khi có. Phân trang/lọc đúng scope; dữ liệu riêng tư bị loại trên server, không chỉ ẩn UI. Kiểm tra lỗi DB/provider không để lại cập nhật dở hoặc trả thành công giả. | AF54: Mở đặc tả
A55: API-054 | B55: Tin đăng & tìm phòng | C55: moderate-post | D55: POST | E55: /api/v1/admin/posts/{postId}/decision | F55: Duyệt hoặc từ chối đúng bài | G55: ADMIN: tài khoản ACTIVE có dòng admins | H55: P1 | I55: Middleware auth/session/role + object scope D09: idempotency store nếu chưa có khóa tự nhiên D15: kiểm tra version trong khóa | J55: SERVICE: cần triển khai giao dịch backend | K55: decision: enum (bắt buộc) — APPROVE hoặc REJECT. reason: string (tùy chọn) — Bắt buộc khi REJECT; tối đa 1.000 ký tự. | L55: Post và contentVersion | M55: Khóa room + post, kiểm tra If-Match/content_version, PENDING_REVIEW; APPROVE cần quyền nhà hiệu lực; REJECT cần reason. Giải phóng slot; ghi audit + thông báo. | N55: 400 BAD_REQUEST 401 UNAUTHENTICATED 403 FORBIDDEN 404 RESOURCE_NOT_FOUND 409 STATE_CONFLICT 409 IDEMPOTENCY_KEY_REUSED 422 VALIDATION_ERROR 409 MODERATION_STATE_CHANGED 422 HOUSE_RIGHT_NOT_EFFECTIVE | P55: Chưa làm | Q55: Chưa | R55: Chưa | S55: Chưa | T55: Chưa | U55: Chưa | V55: Chưa | W55: Chưa | X55: Chưa | Y55: =COUNTIF(Q55:X55,"Xong")/8 -> 0 | AD55: Happy path: Duyệt hoặc từ chối đúng bài; kiểm tra Post và contentVersion. Thiếu phiên/phiên revoked/actor LOCKED và actor khác chủ hoặc khác participant phải bị chặn. Ràng buộc: moderation_actions lưu đối tượng, người xử lý, lý do và bản chụp trước/sau khi có. Gửi lặp cùng khóa trả kết quả cũ; cùng khóa khác payload trả 409; hai request tranh cùng tài nguyên không vượt hạn mức. Kiểm tra lỗi DB/provider không để lại cập nhật dở hoặc trả thành công giả. | AF55: Mở đặc tả
A56: API-055 | B56: Tin đăng & tìm phòng | C56: moderate-post | D56: POST | E56: /api/v1/posts/{postId}/hide | F56: Ẩn tin đang công khai | G56: LANDLORD: sở hữu nhà/phòng/hợp đồng hoặc ADMIN | H56: P1 | I56: Middleware auth/session/role + object scope D09: idempotency store nếu chưa có khóa tự nhiên | J56: SERVICE: cần triển khai giao dịch backend | K56: reason: string (bắt buộc) — Không chỉ khoảng trắng; tối đa 1.000 ký tự. | L56: Post {id,status:HIDDEN} | M56: Chỉ APPROVED; kiểm tra chủ phòng/admin, không đổi bài khác. Giữ ID đã lưu/chia sẻ; ghi audit. | N56: 400 BAD_REQUEST 401 UNAUTHENTICATED 403 FORBIDDEN 404 RESOURCE_NOT_FOUND 409 STATE_CONFLICT 409 IDEMPOTENCY_KEY_REUSED 422 VALIDATION_ERROR 409 MODERATION_STATE_CHANGED 422 HOUSE_RIGHT_NOT_EFFECTIVE | P56: Chưa làm | Q56: Chưa | R56: Chưa | S56: Chưa | T56: Chưa | U56: Chưa | V56: Chưa | W56: Chưa | X56: Chưa | Y56: =COUNTIF(Q56:X56,"Xong")/8 -> 0 | AD56: Happy path: Ẩn tin đang công khai; kiểm tra Post {id,status:HIDDEN}. Thiếu phiên/phiên revoked/actor LOCKED và actor khác chủ hoặc khác participant phải bị chặn. Ràng buộc: moderation_actions lưu đối tượng, người xử lý, lý do và bản chụp trước/sau khi có. Gửi lặp cùng khóa trả kết quả cũ; cùng khóa khác payload trả 409; hai request tranh cùng tài nguyên không vượt hạn mức. Kiểm tra lỗi DB/provider không để lại cập nhật dở hoặc trả thành công giả. | AF56: Mở đặc tả
A57: API-056 | B57: Tin đăng & tìm phòng | C57: moderate-post | D57: POST | E57: /api/v1/admin/posts/{postId}/restore | F57: Hiện lại tin đã ẩn | G57: ADMIN: tài khoản ACTIVE có dòng admins | H57: P1 | I57: Middleware auth/session/role + object scope D09: idempotency store nếu chưa có khóa tự nhiên | J57: SERVICE: cần triển khai giao dịch backend | K57: reason: string (bắt buộc) — Không chỉ khoảng trắng; tối đa 1.000 ký tự. | L57: Post {id,status:APPROVED} | M57: Chỉ HIDDEN; kiểm tra quyền nhà, giữ nội dung, ghi người/lý do/thời điểm; nếu chủ sửa bài thì phải đi lại hàng chờ. | N57: 400 BAD_REQUEST 401 UNAUTHENTICATED 403 FORBIDDEN 404 RESOURCE_NOT_FOUND 409 STATE_CONFLICT 409 IDEMPOTENCY_KEY_REUSED 422 VALIDATION_ERROR 409 MODERATION_STATE_CHANGED 422 HOUSE_RIGHT_NOT_EFFECTIVE | P57: Chưa làm | Q57: Chưa | R57: Chưa | S57: Chưa | T57: Chưa | U57: Chưa | V57: Chưa | W57: Chưa | X57: Chưa | Y57: =COUNTIF(Q57:X57,"Xong")/8 -> 0 | AD57: Happy path: Hiện lại tin đã ẩn; kiểm tra Post {id,status:APPROVED}. Thiếu phiên/phiên revoked/actor LOCKED và actor khác chủ hoặc khác participant phải bị chặn. Ràng buộc: moderation_actions lưu đối tượng, người xử lý, lý do và bản chụp trước/sau khi có. Gửi lặp cùng khóa trả kết quả cũ; cùng khóa khác payload trả 409; hai request tranh cùng tài nguyên không vượt hạn mức. Kiểm tra lỗi DB/provider không để lại cập nhật dở hoặc trả thành công giả. | AF57: Mở đặc tả
A58: API-057 | B58: Tin đăng & tìm phòng | C58: discover | D58: GET | E58: /api/v1/posts | F58: Khám phá và lọc tin công khai | G58: PUBLIC | H58: P0 | J58: READ: v_public_house_posts | K58: Không có JSON body | L58: Post[] {id,roomId,title,images,room,landlordSummary} | M58: Dùng v_public_house_posts; khám phá loại OCCUPIED, vẫn gắn nhãn RESERVED/MAINTENANCE. q,provinceCode,minArea,maxRent,amenities,lat,lng,radiusKm; tọa độ phải cùng cặp. Khoảng cách do backend tính, không dùng demo distance. | N58: 400 BAD_REQUEST 404 RESOURCE_NOT_FOUND 422 VALIDATION_ERROR | P58: Chưa làm | Q58: Chưa | R58: Chưa | S58: Chưa | T58: Chưa | U58: Chưa | V58: Chưa | W58: Chưa | X58: Chưa | Y58: =COUNTIF(Q58:X58,"Xong")/8 -> 0 | AD58: Happy path: Khám phá và lọc tin công khai; kiểm tra Post[] {id,roomId,title,images,room,landlordSummary}. Đầu vào sai/ID ẩn: không lộ dữ liệu riêng tư. Ràng buộc: favorite_posts chống trùng cặp người thuê + bài đăng; FK giữ tham chiếu đúng bài. Phân trang/lọc đúng scope; dữ liệu riêng tư bị loại trên server, không chỉ ẩn UI. Kiểm tra lỗi DB/provider không để lại cập nhật dở hoặc trả thành công giả. | AF58: Mở đặc tả
A59: API-058 | B59: Tin đăng & tìm phòng | C59: discover | D59: GET | E59: /api/v1/posts/{postId} | F59: Chi tiết đúng tin công khai | G59: PUBLIC | H59: P1 | J59: READ: v_public_house_posts | K59: Không có JSON body | L59: Post {id,roomId,title,content,images,amenities,room,landlordSummary} | M59: Tin không còn quyền/ẩn/từ chối trả 404; không tự thay bài khác cùng roomId. Giá/tình trạng/sức chứa lấy rooms hiện tại. | N59: 400 BAD_REQUEST 404 RESOURCE_NOT_FOUND | P59: Chưa làm | Q59: Chưa | R59: Chưa | S59: Chưa | T59: Chưa | U59: Chưa | V59: Chưa | W59: Chưa | X59: Chưa | Y59: =COUNTIF(Q59:X59,"Xong")/8 -> 0 | AD59: Happy path: Chi tiết đúng tin công khai; kiểm tra Post {id,roomId,title,content,images,amenities,room,landlordSummary}. Đầu vào sai/ID ẩn: không lộ dữ liệu riêng tư. Ràng buộc: favorite_posts chống trùng cặp người thuê + bài đăng; FK giữ tham chiếu đúng bài. Phân trang/lọc đúng scope; dữ liệu riêng tư bị loại trên server, không chỉ ẩn UI. Kiểm tra lỗi DB/provider không để lại cập nhật dở hoặc trả thành công giả. | AF59: Mở đặc tả
A60: API-059 | B60: Tin đăng & tìm phòng | C60: discover | D60: GET | E60: /api/v1/me/favorites | F60: Danh sách bài đã lưu | G60: TENANT: chỉ chính người thuê và tài nguyên được phép | H60: P1 | I60: Middleware auth/session/role + object scope | J60: READ: truy vấn có scope quyền | K60: Không có JSON body | L60: Favorite[] {postId,savedAt,availability,post|null} | M60: Chỉ favorites actor. Nếu bài mất quyền thì trả placeholder không lộ ảnh/tiêu đề cũ. | N60: 400 BAD_REQUEST 401 UNAUTHENTICATED 403 FORBIDDEN 404 RESOURCE_NOT_FOUND 422 VALIDATION_ERROR | P60: Chưa làm | Q60: Chưa | R60: Chưa | S60: Chưa | T60: Chưa | U60: Chưa | V60: Chưa | W60: Chưa | X60: Chưa | Y60: =COUNTIF(Q60:X60,"Xong")/8 -> 0 | AD60: Happy path: Danh sách bài đã lưu; kiểm tra Favorite[] {postId,savedAt,availability,post|null}. Thiếu phiên/phiên revoked/actor LOCKED và actor khác chủ hoặc khác participant phải bị chặn. Ràng buộc: favorite_posts chống trùng cặp người thuê + bài đăng; FK giữ tham chiếu đúng bài. Phân trang/lọc đúng scope; dữ liệu riêng tư bị loại trên server, không chỉ ẩn UI. Kiểm tra lỗi DB/provider không để lại cập nhật dở hoặc trả thành công giả. | AF60: Mở đặc tả
A61: API-060 | B61: Tin đăng & tìm phòng | C61: discover | D61: PUT | E61: /api/v1/me/favorites/{postId} | F61: Lưu bài theo ID | G61: TENANT: chỉ chính người thuê và tài nguyên được phép | H61: P1 | I61: Middleware auth/session/role + object scope D09: idempotency store nếu chưa có khóa tự nhiên | J61: SERVICE: cần triển khai giao dịch backend | K61: Không có JSON body | L61: {postId,saved:true} | M61: Bài còn công khai khi lưu; uq tenant+post chống trùng; gọi lặp cùng kết quả. | N61: 400 BAD_REQUEST 401 UNAUTHENTICATED 403 FORBIDDEN 404 RESOURCE_NOT_FOUND 409 STATE_CONFLICT 409 IDEMPOTENCY_KEY_REUSED 422 VALIDATION_ERROR 404 POST_UNAVAILABLE | P61: Chưa làm | Q61: Chưa | R61: Chưa | S61: Chưa | T61: Chưa | U61: Chưa | V61: Chưa | W61: Chưa | X61: Chưa | Y61: =COUNTIF(Q61:X61,"Xong")/8 -> 0 | AD61: Happy path: Lưu bài theo ID; kiểm tra {postId,saved:true}. Thiếu phiên/phiên revoked/actor LOCKED và actor khác chủ hoặc khác participant phải bị chặn. Ràng buộc: favorite_posts chống trùng cặp người thuê + bài đăng; FK giữ tham chiếu đúng bài. Gửi lặp cùng khóa trả kết quả cũ; cùng khóa khác payload trả 409; hai request tranh cùng tài nguyên không vượt hạn mức. Kiểm tra lỗi DB/provider không để lại cập nhật dở hoặc trả thành công giả. | AF61: Mở đặc tả
A62: API-061 | B62: Tin đăng & tìm phòng | C62: discover | D62: DELETE | E62: /api/v1/me/favorites/{postId} | F62: Bỏ lưu bài | G62: TENANT: chỉ chính người thuê và tài nguyên được phép | H62: P1 | I62: Middleware auth/session/role + object scope D09: idempotency store nếu chưa có khóa tự nhiên | J62: SERVICE: cần triển khai giao dịch backend | K62: Không có JSON body | L62: {postId,saved:false} | M62: Chỉ favorite actor; bỏ lưu được cả khi bài đã ẩn; gọi lặp vẫn thành công. | N62: 400 BAD_REQUEST 401 UNAUTHENTICATED 403 FORBIDDEN 404 RESOURCE_NOT_FOUND 409 STATE_CONFLICT 409 IDEMPOTENCY_KEY_REUSED 422 VALIDATION_ERROR 404 POST_UNAVAILABLE | P62: Chưa làm | Q62: Chưa | R62: Chưa | S62: Chưa | T62: Chưa | U62: Chưa | V62: Chưa | W62: Chưa | X62: Chưa | Y62: =COUNTIF(Q62:X62,"Xong")/8 -> 0 | AD62: Happy path: Bỏ lưu bài; kiểm tra {postId,saved:false}. Thiếu phiên/phiên revoked/actor LOCKED và actor khác chủ hoặc khác participant phải bị chặn. Ràng buộc: favorite_posts chống trùng cặp người thuê + bài đăng; FK giữ tham chiếu đúng bài. Gửi lặp cùng khóa trả kết quả cũ; cùng khóa khác payload trả 409; hai request tranh cùng tài nguyên không vượt hạn mức. Kiểm tra lỗi DB/provider không để lại cập nhật dở hoặc trả thành công giả. | AF62: Mở đặc tả
A63: API-062 | B63: Hồ sơ & kết nối ở ghép | C63: roommate-profile | D63: GET | E63: /api/v1/me/roommate-profile | F63: Đọc hồ sơ ở ghép của mình | G63: TENANT: chỉ chính người thuê và tài nguyên được phép | H63: P1 | I63: Middleware auth/session/role + object scope | J63: READ: truy vấn có scope quyền | K63: Không có JSON body | L63: RoommateProfile hoặc 404 PROFILE_NOT_CREATED | M63: Trả profileVersion/housingStatus/currentRoomTenantId; phát hiện hồ sơ IN_SYSTEM cũ khi cư trú đã đổi. | N63: 400 BAD_REQUEST 401 UNAUTHENTICATED 403 FORBIDDEN 404 RESOURCE_NOT_FOUND | P63: Chưa làm | Q63: Chưa | R63: Chưa | S63: Chưa | T63: Chưa | U63: Chưa | V63: Chưa | W63: Chưa | X63: Chưa | Y63: =COUNTIF(Q63:X63,"Xong")/8 -> 0 | AD63: Happy path: Đọc hồ sơ ở ghép của mình; kiểm tra RoommateProfile hoặc 404 PROFILE_NOT_CREATED. Thiếu phiên/phiên revoked/actor LOCKED và actor khác chủ hoặc khác participant phải bị chặn. Ràng buộc: Một roommate_profiles cho mỗi tenant; ngân sách không âm và max ≥ min nếu có cả hai. Phân trang/lọc đúng scope; dữ liệu riêng tư bị loại trên server, không chỉ ẩn UI. Kiểm tra lỗi DB/provider không để lại cập nhật dở hoặc trả thành công giả. | AF63: Mở đặc tả
A64: API-063 | B64: Hồ sơ & kết nối ở ghép | C64: roommate-profile | D64: PUT | E64: /api/v1/me/roommate-profile | F64: Tạo hoặc thay thế hồ sơ ở ghép | G64: TENANT: chỉ chính người thuê và tài nguyên được phép | H64: P1 | I64: Middleware auth/session/role + object scope D09: idempotency store nếu chưa có khóa tự nhiên D15: kiểm tra version trong khóa | J64: SERVICE: cần triển khai giao dịch backend | K64: housingStatus: enum (bắt buộc) — NO_ACCOMMODATION / EXTERNAL; IN_SYSTEM do server xác định từ ACTIVE. externalContext: string (tùy chọn) — Chỉ EXTERNAL, tối đa 1.000 ký tự. availableFrom: date (bắt buộc) — Ngày hợp lệ. budgetMin: money (tùy chọn) — ≥0. budgetMax: money (tùy chọn) — ≥ budgetMin. preferredLocation: string (bắt buộc) — 1–500 ký tự. preferredGender: string (tùy chọn) — ≤30 ký tự. requirementsSnapshot: object (tùy chọn) — Nhu cầu tự khai; schema cần chốt. active: boolean (bắt buộc) — Bật cho phép tìm kiếm. | L64: RoommateProfile {id,profileVersion,...} | M64: Một hồ sơ/tenant; tra ACTIVE bằng khóa, tự ghi IN_SYSTEM + đúng member nếu có; không tin currentRoomTenantId client. If-Match cho cập nhật, If-None-Match:* khi tạo. Lưu không gửi lời mời. | N64: 400 BAD_REQUEST 401 UNAUTHENTICATED 403 FORBIDDEN 404 RESOURCE_NOT_FOUND 409 STATE_CONFLICT 409 IDEMPOTENCY_KEY_REUSED 422 VALIDATION_ERROR 409 PROFILE_VERSION_CHANGED 422 HOUSING_CONTEXT_INVALID | P64: Chưa làm | Q64: Chưa | R64: Chưa | S64: Chưa | T64: Chưa | U64: Chưa | V64: Chưa | W64: Chưa | X64: Chưa | Y64: =COUNTIF(Q64:X64,"Xong")/8 -> 0 | AD64: Happy path: Tạo hoặc thay thế hồ sơ ở ghép; kiểm tra RoommateProfile {id,profileVersion,...}. Thiếu phiên/phiên revoked/actor LOCKED và actor khác chủ hoặc khác participant phải bị chặn. Ràng buộc: Một roommate_profiles cho mỗi tenant; ngân sách không âm và max ≥ min nếu có cả hai. Gửi lặp cùng khóa trả kết quả cũ; cùng khóa khác payload trả 409; hai request tranh cùng tài nguyên không vượt hạn mức. Kiểm tra lỗi DB/provider không để lại cập nhật dở hoặc trả thành công giả. | AF64: Mở đặc tả
A65: API-064 | B65: Hồ sơ & kết nối ở ghép | C65: roommate-profile | D65: GET | E65: /api/v1/roommate-profiles/{profileId} | F65: Xem hồ sơ ứng viên theo quyền | G65: TENANT: chỉ chính người thuê và tài nguyên được phép | H65: P1 | I65: Middleware auth/session/role + object scope | J65: READ: truy vấn có scope quyền | K65: Không có JSON body | L65: PublicRoommateProfile; không có CCCD/địa chỉ cư trú cụ thể | M65: Hồ sơ active được tìm; người nhận lời mời vẫn được xem nội dung đủ quyết định theo quyền lời mời. Không trả định danh căn cước. | N65: 400 BAD_REQUEST 401 UNAUTHENTICATED 403 FORBIDDEN 404 RESOURCE_NOT_FOUND | P65: Chưa làm | Q65: Chưa | R65: Chưa | S65: Chưa | T65: Chưa | U65: Chưa | V65: Chưa | W65: Chưa | X65: Chưa | Y65: =COUNTIF(Q65:X65,"Xong")/8 -> 0 | AD65: Happy path: Xem hồ sơ ứng viên theo quyền; kiểm tra PublicRoommateProfile; không có CCCD/địa chỉ cư trú cụ thể. Thiếu phiên/phiên revoked/actor LOCKED và actor khác chủ hoặc khác participant phải bị chặn. Ràng buộc: Một roommate_profiles cho mỗi tenant; ngân sách không âm và max ≥ min nếu có cả hai. Phân trang/lọc đúng scope; dữ liệu riêng tư bị loại trên server, không chỉ ẩn UI. Kiểm tra lỗi DB/provider không để lại cập nhật dở hoặc trả thành công giả. | AF65: Mở đặc tả
A66: API-065 | B66: Hồ sơ & kết nối ở ghép | C66: matching-criteria | D66: GET | E66: /api/v1/lifestyle-criteria | F66: Danh mục tiêu chí đang áp dụng | G66: TENANT: chỉ chính người thuê và tài nguyên được phép | H66: P1 | I66: Middleware auth/session/role + object scope | J66: READ: truy vấn có scope quyền | K66: Không có JSON body | L66: LifestyleCriterion[] {id,code,name,category,valueType,allowedValues} | M66: Chỉ active; cấu trúc JSON theo valueType được validate bởi service. | N66: 400 BAD_REQUEST 401 UNAUTHENTICATED 403 FORBIDDEN 404 RESOURCE_NOT_FOUND 422 VALIDATION_ERROR | P66: Chưa làm | Q66: Chưa | R66: Chưa | S66: Chưa | T66: Chưa | U66: Chưa | V66: Chưa | W66: Chưa | X66: Chưa | Y66: =COUNTIF(Q66:X66,"Xong")/8 -> 0 | AD66: Happy path: Danh mục tiêu chí đang áp dụng; kiểm tra LifestyleCriterion[] {id,code,name,category,valueType,allowedValues}. Thiếu phiên/phiên revoked/actor LOCKED và actor khác chủ hoặc khác participant phải bị chặn. Ràng buộc: lifestyle_criteria.code duy nhất; value_type thuộc BOOLEAN / NUMBER / CATEGORY / TIME / RANGE. Phân trang/lọc đúng scope; dữ liệu riêng tư bị loại trên server, không chỉ ẩn UI. Kiểm tra lỗi DB/provider không để lại cập nhật dở hoặc trả thành công giả. | AF66: Mở đặc tả
A67: API-066 | B67: Hồ sơ & kết nối ở ghép | C67: matching-criteria | D67: GET | E67: /api/v1/me/roommate-profile/lifestyles | F67: Đọc đặc điểm và mong muốn đã lưu | G67: TENANT: chỉ chính người thuê và tài nguyên được phép | H67: P1 | I67: Middleware auth/session/role + object scope | J67: READ: truy vấn có scope quyền | K67: Không có JSON body | L67: ProfileLifestyle[] | M67: Chỉ profile actor; trả selfValue/preferredValue/isMandatory/importance. | N67: 400 BAD_REQUEST 401 UNAUTHENTICATED 403 FORBIDDEN 404 RESOURCE_NOT_FOUND 422 VALIDATION_ERROR | P67: Chưa làm | Q67: Chưa | R67: Chưa | S67: Chưa | T67: Chưa | U67: Chưa | V67: Chưa | W67: Chưa | X67: Chưa | Y67: =COUNTIF(Q67:X67,"Xong")/8 -> 0 | AD67: Happy path: Đọc đặc điểm và mong muốn đã lưu; kiểm tra ProfileLifestyle[]. Thiếu phiên/phiên revoked/actor LOCKED và actor khác chủ hoặc khác participant phải bị chặn. Ràng buộc: lifestyle_criteria.code duy nhất; value_type thuộc BOOLEAN / NUMBER / CATEGORY / TIME / RANGE. Phân trang/lọc đúng scope; dữ liệu riêng tư bị loại trên server, không chỉ ẩn UI. Kiểm tra lỗi DB/provider không để lại cập nhật dở hoặc trả thành công giả. | AF67: Mở đặc tả
A68: API-067 | B68: Hồ sơ & kết nối ở ghép | C68: matching-criteria | D68: PUT | E68: /api/v1/me/roommate-profile/lifestyles | F68: Thay bộ tiêu chí của hồ sơ | G68: TENANT: chỉ chính người thuê và tài nguyên được phép | H68: P1 | I68: Middleware auth/session/role + object scope D09: idempotency store nếu chưa có khóa tự nhiên | J68: SERVICE: cần triển khai giao dịch backend | K68: criteria: object[] (bắt buộc) — Mỗi criterionId duy nhất; có selfValue hoặc preferredValue; mandatory cần preferredValue; importance 0–5. | L68: ProfileLifestyle[] và profileVersion | M68: Khóa profile; kiểm tra criterion active, kiểu JSON BOOLEAN/NUMBER/CATEGORY/TIME/RANGE và allowed_values; thay bộ giá trị atomically, tăng profile_version. | N68: 400 BAD_REQUEST 401 UNAUTHENTICATED 403 FORBIDDEN 404 RESOURCE_NOT_FOUND 409 STATE_CONFLICT 409 IDEMPOTENCY_KEY_REUSED 422 VALIDATION_ERROR 422 INVALID_CRITERION_VALUE 409 CRITERION_IN_USE | P68: Chưa làm | Q68: Chưa | R68: Chưa | S68: Chưa | T68: Chưa | U68: Chưa | V68: Chưa | W68: Chưa | X68: Chưa | Y68: =COUNTIF(Q68:X68,"Xong")/8 -> 0 | AD68: Happy path: Thay bộ tiêu chí của hồ sơ; kiểm tra ProfileLifestyle[] và profileVersion. Thiếu phiên/phiên revoked/actor LOCKED và actor khác chủ hoặc khác participant phải bị chặn. Ràng buộc: lifestyle_criteria.code duy nhất; value_type thuộc BOOLEAN / NUMBER / CATEGORY / TIME / RANGE. Gửi lặp cùng khóa trả kết quả cũ; cùng khóa khác payload trả 409; hai request tranh cùng tài nguyên không vượt hạn mức. Kiểm tra lỗi DB/provider không để lại cập nhật dở hoặc trả thành công giả. | AF68: Mở đặc tả
A69: API-068 | B69: Hồ sơ & kết nối ở ghép | C69: matching-criteria | D69: GET | E69: /api/v1/roommate-matches | F69: Danh sách người phù hợp | G69: TENANT: chỉ chính người thuê và tài nguyên được phép | H69: P1 | I69: Middleware auth/session/role + object scope D02 | J69: READ: truy vấn có scope quyền | K69: Không có JSON body | L69: Match[] {profile,score|null,algorithmVersion,explanations} | M69: Loại bản thân, hồ sơ inactive; lọc khu vực/ngân sách/tiêu chí bắt buộc. Thuật toán điểm/trọng số chưa tồn tại: chốt D02 trước khi trả score. | N69: 400 BAD_REQUEST 401 UNAUTHENTICATED 403 FORBIDDEN 404 RESOURCE_NOT_FOUND 422 VALIDATION_ERROR | P69: Chưa làm | Q69: Chưa | R69: Chưa | S69: Chưa | T69: Chưa | U69: Chưa | V69: Chưa | W69: Chưa | X69: Chưa | Y69: =COUNTIF(Q69:X69,"Xong")/8 -> 0 | AD69: Happy path: Danh sách người phù hợp; kiểm tra Match[] {profile,score|null,algorithmVersion,explanations}. Thiếu phiên/phiên revoked/actor LOCKED và actor khác chủ hoặc khác participant phải bị chặn. Ràng buộc: lifestyle_criteria.code duy nhất; value_type thuộc BOOLEAN / NUMBER / CATEGORY / TIME / RANGE. Phân trang/lọc đúng scope; dữ liệu riêng tư bị loại trên server, không chỉ ẩn UI. Kiểm tra lỗi DB/provider không để lại cập nhật dở hoặc trả thành công giả. | AF69: Mở đặc tả
A70: API-069 | B70: Hồ sơ & kết nối ở ghép | C70: matching-criteria | D70: POST | E70: /api/v1/admin/lifestyle-criteria | F70: Tạo tiêu chí ghép linh động | G70: ADMIN: tài khoản ACTIVE có dòng admins | H70: P1 | I70: Middleware auth/session/role + object scope D09: idempotency store nếu chưa có khóa tự nhiên | J70: SERVICE: cần triển khai giao dịch backend | K70: code: string (bắt buộc) — Duy nhất; ≤80 ký tự. name: string (bắt buộc) — ≤100 ký tự. category: string (bắt buộc) — ≤100 ký tự. valueType: enum (bắt buộc) — BOOLEAN/NUMBER/CATEGORY/TIME/RANGE. allowedValues: object (tùy chọn) — JSON phải tương thích kiểu. active: boolean (bắt buộc) — Bật/ngừng. | L70: LifestyleCriterion | M70: Không thêm cột hồ sơ cho từng tiêu chí; ghi audit vận hành riêng nếu cần vì moderation_actions không có target tiêu chí. | N70: 400 BAD_REQUEST 401 UNAUTHENTICATED 403 FORBIDDEN 404 RESOURCE_NOT_FOUND 409 STATE_CONFLICT 409 IDEMPOTENCY_KEY_REUSED 422 VALIDATION_ERROR 422 INVALID_CRITERION_VALUE 409 CRITERION_IN_USE | P70: Chưa làm | Q70: Chưa | R70: Chưa | S70: Chưa | T70: Chưa | U70: Chưa | V70: Chưa | W70: Chưa | X70: Chưa | Y70: =COUNTIF(Q70:X70,"Xong")/8 -> 0 | AD70: Happy path: Tạo tiêu chí ghép linh động; kiểm tra LifestyleCriterion. Thiếu phiên/phiên revoked/actor LOCKED và actor khác chủ hoặc khác participant phải bị chặn. Ràng buộc: lifestyle_criteria.code duy nhất; value_type thuộc BOOLEAN / NUMBER / CATEGORY / TIME / RANGE. Gửi lặp cùng khóa trả kết quả cũ; cùng khóa khác payload trả 409; hai request tranh cùng tài nguyên không vượt hạn mức. Kiểm tra lỗi DB/provider không để lại cập nhật dở hoặc trả thành công giả. | AF70: Mở đặc tả
A71: API-070 | B71: Hồ sơ & kết nối ở ghép | C71: matching-criteria | D71: PATCH | E71: /api/v1/admin/lifestyle-criteria/{criterionId} | F71: Sửa/ngừng tiêu chí | G71: ADMIN: tài khoản ACTIVE có dòng admins | H71: P1 | I71: Middleware auth/session/role + object scope D09: idempotency store nếu chưa có khóa tự nhiên D02 | J71: SERVICE: cần triển khai giao dịch backend | K71: code: string (tùy chọn) — Duy nhất; ≤80 ký tự. name: string (tùy chọn) — ≤100 ký tự. category: string (tùy chọn) — ≤100 ký tự. valueType: enum (tùy chọn) — BOOLEAN/NUMBER/CATEGORY/TIME/RANGE. allowedValues: object (tùy chọn) — JSON phải tương thích kiểu. active: boolean (tùy chọn) — Bật/ngừng. | L71: LifestyleCriterion | M71: Không đổi code/kiểu khiến giá trị lịch sử mất nghĩa; đổi kiểu đang dùng cần phiên bản/migration được thiết kế. | N71: 400 BAD_REQUEST 401 UNAUTHENTICATED 403 FORBIDDEN 404 RESOURCE_NOT_FOUND 409 STATE_CONFLICT 409 IDEMPOTENCY_KEY_REUSED 422 VALIDATION_ERROR 422 INVALID_CRITERION_VALUE 409 CRITERION_IN_USE | P71: Chưa làm | Q71: Chưa | R71: Chưa | S71: Chưa | T71: Chưa | U71: Chưa | V71: Chưa | W71: Chưa | X71: Chưa | Y71: =COUNTIF(Q71:X71,"Xong")/8 -> 0 | AD71: Happy path: Sửa/ngừng tiêu chí; kiểm tra LifestyleCriterion. Thiếu phiên/phiên revoked/actor LOCKED và actor khác chủ hoặc khác participant phải bị chặn. Ràng buộc: lifestyle_criteria.code duy nhất; value_type thuộc BOOLEAN / NUMBER / CATEGORY / TIME / RANGE. Gửi lặp cùng khóa trả kết quả cũ; cùng khóa khác payload trả 409; hai request tranh cùng tài nguyên không vượt hạn mức. Kiểm tra lỗi DB/provider không để lại cập nhật dở hoặc trả thành công giả. | AF71: Mở đặc tả
... A153: API-152 | B153: Dịch vụ & hóa đơn | C153: pay-invoice | D153: POST | E153: /api/v1/invoices/{invoiceId}/replacements | F153: Lập bản nháp thay hóa đơn đã hủy | G153: LANDLORD: sở hữu nhà/phòng/hợp đồng | H153: P1 | I153: Middleware auth/session/role + object scope D09: idempotency store nếu chưa có khóa tự nhiên | J153: SERVICE: cần triển khai giao dịch backend | K153: dueDate: date (bắt buộc) — Không trước ngày phát hành theo chính sách đề xuất. items: InvoiceInputItem[] (bắt buộc) — Có tiền thuê và các dòng dịch vụ/khoản khác; tổng không âm. | L153: Invoice {id,status:DRAFT,replacesInvoiceId} | M153: Hóa đơn nguồn CANCELLED, cùng contract/period; unique active kỳ; links FK, giữ dữ liệu cũ. Đây là service mới chưa có UI đầy đủ. | N153: 400 BAD_REQUEST 401 UNAUTHENTICATED 403 FORBIDDEN 404 RESOURCE_NOT_FOUND 409 STATE_CONFLICT 409 IDEMPOTENCY_KEY_REUSED 422 VALIDATION_ERROR 409 INVOICE_STATE_CHANGED 409 INVOICE_PERIOD_EXISTS 422 INVOICE_TOTAL_INVALID | P153: Chưa làm | Q153: Chưa | R153: Chưa | S153: Chưa | T153: Chưa | U153: Chưa | V153: Chưa | W153: Chưa | X153: Chưa | Y153: =COUNTIF(Q153:X153,"Xong")/8 -> 0 | AD153: Happy path: Lập bản nháp thay hóa đơn đã hủy; kiểm tra Invoice {id,status:DRAFT,replacesInvoiceId}. Thiếu phiên/phiên revoked/actor LOCKED và actor khác chủ hoặc khác participant phải bị chặn. Ràng buộc: PAID cần paid_by_id và paid_at; CANCELLED cần người/thời điểm/lý do. Hóa đơn thay thế phải cùng hợp đồng/kỳ theo FK. Gửi lặp cùng khóa trả kết quả cũ; cùng khóa khác payload trả 409; hai request tranh cùng tài nguyên không vượt hạn mức. Kiểm tra lỗi DB/provider không để lại cập nhật dở hoặc trả thành công giả. | AF153: Mở đặc tả
A154: API-153 | B154: Đánh giá & quản trị | C154: review | D154: GET | E154: /api/v1/rooms/{roomId}/reviews | F154: Đánh giá phòng được công khai | G154: PUBLIC | H154: P1 | J154: READ: truy vấn có scope quyền | K154: Không có JSON body | L154: Review[] {rating,content,reviewerDisplayName}; không có giấy tờ | M154: Chỉ PUBLISHED và room có quyền xem; không lộ contract/CCCD của reviewer. | N154: 400 BAD_REQUEST 404 RESOURCE_NOT_FOUND 422 VALIDATION_ERROR | P154: Chưa làm | Q154: Chưa | R154: Chưa | S154: Chưa | T154: Chưa | U154: Chưa | V154: Chưa | W154: Chưa | X154: Chưa | Y154: =COUNTIF(Q154:X154,"Xong")/8 -> 0 | AD154: Happy path: Đánh giá phòng được công khai; kiểm tra Review[] {rating,content,reviewerDisplayName}; không có giấy tờ. Đầu vào sai/ID ẩn: không lộ dữ liệu riêng tư. Ràng buộc: Rating từ 1 đến 5; UNIQUE (reviewer_id,room_id,contract_id). FK ghép tới room_tenants giữ đúng người-phòng-hợp đồng làm bằng chứng. Phân trang/lọc đúng scope; dữ liệu riêng tư bị loại trên server, không chỉ ẩn UI. Kiểm tra lỗi DB/provider không để lại cập nhật dở hoặc trả thành công giả. | AF154: Mở đặc tả
A155: API-154 | B155: Đánh giá & quản trị | C155: review | D155: POST | E155: /api/v1/reviews | F155: Đánh giá bằng lượt cư trú thực tế | G155: TENANT: chỉ chính người thuê và tài nguyên được phép | H155: P1 | I155: Middleware auth/session/role + object scope D09: idempotency store nếu chưa có khóa tự nhiên D13 | J155: SERVICE: cần triển khai giao dịch backend | K155: roomTenantId: id (bắt buộc) — Lượt ở của actor đúng room/contract. rating: integer (bắt buộc) — 1–5. content: string (tùy chọn) — SQL TEXT; giới hạn API được cấu hình. | L155: Review {id,status:PUBLISHED} | M155: Lấy room/contract từ member; unique reviewer+room+contract. Chính sách đề xuất: contract TERMINATED và có ACTIVE/LEFT thật; cần chốt thời điểm/hạn sửa D13. Không chỉ dựa contractId demo. | N155: 400 BAD_REQUEST 401 UNAUTHENTICATED 403 FORBIDDEN 404 RESOURCE_NOT_FOUND 409 STATE_CONFLICT 409 IDEMPOTENCY_KEY_REUSED 422 VALIDATION_ERROR 409 ALREADY_REVIEWED 422 TENANCY_EVIDENCE_REQUIRED 422 REVIEW_NOT_YET_ALLOWED | P155: Chưa làm | Q155: Chưa | R155: Chưa | S155: Chưa | T155: Chưa | U155: Chưa | V155: Chưa | W155: Chưa | X155: Chưa | Y155: =COUNTIF(Q155:X155,"Xong")/8 -> 0 | AD155: Happy path: Đánh giá bằng lượt cư trú thực tế; kiểm tra Review {id,status:PUBLISHED}. Thiếu phiên/phiên revoked/actor LOCKED và actor khác chủ hoặc khác participant phải bị chặn. Ràng buộc: Rating từ 1 đến 5; UNIQUE (reviewer_id,room_id,contract_id). FK ghép tới room_tenants giữ đúng người-phòng-hợp đồng làm bằng chứng. Gửi lặp cùng khóa trả kết quả cũ; cùng khóa khác payload trả 409; hai request tranh cùng tài nguyên không vượt hạn mức. Kiểm tra lỗi DB/provider không để lại cập nhật dở hoặc trả thành công giả. | AF155: Mở đặc tả
A156: API-155 | B156: Đánh giá & quản trị | C156: review | D156: POST | E156: /api/v1/admin/reviews/{reviewId}/moderation | F156: Ẩn/khôi phục/xóa mềm đánh giá | G156: ADMIN: tài khoản ACTIVE có dòng admins | H156: P1 | I156: Middleware auth/session/role + object scope D09: idempotency store nếu chưa có khóa tự nhiên D14 | J156: SERVICE: cần triển khai giao dịch backend | K156: status: enum (bắt buộc) — HIDDEN / PUBLISHED / DELETED. reason: string (bắt buộc) — Lý do không trống, ≤1.000 ký tự. | L156: Review {id,status} | M156: Bảo toàn bằng chứng cư trú. Ghi hidden_by/reason/at; moderation_actions hiện không có target_review_id nên cần thiết kế mở rộng audit, không giả có cột. | N156: 400 BAD_REQUEST 401 UNAUTHENTICATED 403 FORBIDDEN 404 RESOURCE_NOT_FOUND 409 STATE_CONFLICT 409 IDEMPOTENCY_KEY_REUSED 422 VALIDATION_ERROR 409 ALREADY_REVIEWED 422 TENANCY_EVIDENCE_REQUIRED 422 REVIEW_NOT_YET_ALLOWED | P156: Chưa làm | Q156: Chưa | R156: Chưa | S156: Chưa | T156: Chưa | U156: Chưa | V156: Chưa | W156: Chưa | X156: Chưa | Y156: =COUNTIF(Q156:X156,"Xong")/8 -> 0 | AD156: Happy path: Ẩn/khôi phục/xóa mềm đánh giá; kiểm tra Review {id,status}. Thiếu phiên/phiên revoked/actor LOCKED và actor khác chủ hoặc khác participant phải bị chặn. Ràng buộc: Rating từ 1 đến 5; UNIQUE (reviewer_id,room_id,contract_id). FK ghép tới room_tenants giữ đúng người-phòng-hợp đồng làm bằng chứng. Gửi lặp cùng khóa trả kết quả cũ; cùng khóa khác payload trả 409; hai request tranh cùng tài nguyên không vượt hạn mức. Kiểm tra lỗi DB/provider không để lại cập nhật dở hoặc trả thành công giả. | AF156: Mở đặc tả
A157: API-156 | B157: Đánh giá & quản trị | C157: report | D157: POST | E157: /api/v1/reports | F157: Gửi báo cáo hoặc tranh chấp | G157: TENANT: chỉ chính người thuê và tài nguyên được phép | H157: P1 | I157: Middleware auth/session/role + object scope D09: idempotency store nếu chưa có khóa tự nhiên | J157: SERVICE: cần triển khai giao dịch backend | K157: type: enum (bắt buộc) — VIOLATION / DISPUTE. targetType: enum (bắt buộc) — POST / USER / CONTRACT / ROOMMATE_REQUEST. targetId: id (bắt buộc) — Đối tượng actor có quyền truy cập. reason: string (bắt buộc) — Nội dung không trống. evidenceFileIds: id[] (tùy chọn) — REPORT_EVIDENCE PRIVATE ACTIVE của actor. | L157: Report {id,status:PENDING} | M157: Ánh xạ đúng một trong 4 FK, không nhận 4 target tùy ý; liên kết evidence cùng transaction. Không tự ẩn bài/khóa user. | N157: 400 BAD_REQUEST 401 UNAUTHENTICATED 403 FORBIDDEN 404 RESOURCE_NOT_FOUND 409 STATE_CONFLICT 409 IDEMPOTENCY_KEY_REUSED 422 VALIDATION_ERROR 422 REPORT_TARGET_INVALID 409 REPORT_ALREADY_CLOSED | P157: Chưa làm | Q157: Chưa | R157: Chưa | S157: Chưa | T157: Chưa | U157: Chưa | V157: Chưa | W157: Chưa | X157: Chưa | Y157: =COUNTIF(Q157:X157,"Xong")/8 -> 0 | AD157: Happy path: Gửi báo cáo hoặc tranh chấp; kiểm tra Report {id,status:PENDING}. Thiếu phiên/phiên revoked/actor LOCKED và actor khác chủ hoặc khác participant phải bị chặn. Ràng buộc: Một report nhắm đúng một trong reported_user_id / reported_post_id / contract_id / roommate_request_id. Gửi lặp cùng khóa trả kết quả cũ; cùng khóa khác payload trả 409; hai request tranh cùng tài nguyên không vượt hạn mức. Kiểm tra lỗi DB/provider không để lại cập nhật dở hoặc trả thành công giả. | AF157: Mở đặc tả
A158: API-157 | B158: Đánh giá & quản trị | C158: report | D158: GET | E158: /api/v1/me/reports | F158: Báo cáo mình đã gửi và kết luận | G158: TENANT: chỉ chính người thuê và tài nguyên được phép | H158: P1 | I158: Middleware auth/session/role + object scope | J158: READ: truy vấn có scope quyền | K158: Không có JSON body | L158: Report[] không lộ dữ liệu riêng tư người bị báo cáo | M158: Chỉ reporter_id=actor, không trả thông tin điều tra nội bộ không được phép. | N158: 400 BAD_REQUEST 401 UNAUTHENTICATED 403 FORBIDDEN 404 RESOURCE_NOT_FOUND 422 VALIDATION_ERROR | P158: Chưa làm | Q158: Chưa | R158: Chưa | S158: Chưa | T158: Chưa | U158: Chưa | V158: Chưa | W158: Chưa | X158: Chưa | Y158: =COUNTIF(Q158:X158,"Xong")/8 -> 0 | AD158: Happy path: Báo cáo mình đã gửi và kết luận; kiểm tra Report[] không lộ dữ liệu riêng tư người bị báo cáo. Thiếu phiên/phiên revoked/actor LOCKED và actor khác chủ hoặc khác participant phải bị chặn. Ràng buộc: Một report nhắm đúng một trong reported_user_id / reported_post_id / contract_id / roommate_request_id. Phân trang/lọc đúng scope; dữ liệu riêng tư bị loại trên server, không chỉ ẩn UI. Kiểm tra lỗi DB/provider không để lại cập nhật dở hoặc trả thành công giả. | AF158: Mở đặc tả
A159: API-158 | B159: Đánh giá & quản trị | C159: report | D159: GET | E159: /api/v1/admin/reports | F159: Hàng đợi báo cáo | G159: ADMIN: tài khoản ACTIVE có dòng admins | H159: P1 | I159: Middleware auth/session/role + object scope | J159: READ: truy vấn có scope quyền | K159: Không có JSON body | L159: Report[] và target summary | M159: Lọc type/status; giữ target gốc dù bài mất quyền công khai. | N159: 400 BAD_REQUEST 401 UNAUTHENTICATED 403 FORBIDDEN 404 RESOURCE_NOT_FOUND 422 VALIDATION_ERROR | P159: Chưa làm | Q159: Chưa | R159: Chưa | S159: Chưa | T159: Chưa | U159: Chưa | V159: Chưa | W159: Chưa | X159: Chưa | Y159: =COUNTIF(Q159:X159,"Xong")/8 -> 0 | AD159: Happy path: Hàng đợi báo cáo; kiểm tra Report[] và target summary. Thiếu phiên/phiên revoked/actor LOCKED và actor khác chủ hoặc khác participant phải bị chặn. Ràng buộc: Một report nhắm đúng một trong reported_user_id / reported_post_id / contract_id / roommate_request_id. Phân trang/lọc đúng scope; dữ liệu riêng tư bị loại trên server, không chỉ ẩn UI. Kiểm tra lỗi DB/provider không để lại cập nhật dở hoặc trả thành công giả. | AF159: Mở đặc tả
A160: API-159 | B160: Đánh giá & quản trị | C160: report | D160: GET | E160: /api/v1/admin/reports/{reportId} | F160: Chi tiết báo cáo và bằng chứng | G160: ADMIN: tài khoản ACTIVE có dòng admins | H160: P1 | I160: Middleware auth/session/role + object scope | J160: READ: truy vấn có scope quyền | K160: Không có JSON body | L160: Report,evidenceFileIds,targetSnapshotIfAvailable | M160: Xét quyền mở tệp riêng; không tạo URL công khai. | N160: 400 BAD_REQUEST 401 UNAUTHENTICATED 403 FORBIDDEN 404 RESOURCE_NOT_FOUND | P160: Chưa làm | Q160: Chưa | R160: Chưa | S160: Chưa | T160: Chưa | U160: Chưa | V160: Chưa | W160: Chưa | X160: Chưa | Y160: =COUNTIF(Q160:X160,"Xong")/8 -> 0 | AD160: Happy path: Chi tiết báo cáo và bằng chứng; kiểm tra Report,evidenceFileIds,targetSnapshotIfAvailable. Thiếu phiên/phiên revoked/actor LOCKED và actor khác chủ hoặc khác participant phải bị chặn. Ràng buộc: Một report nhắm đúng một trong reported_user_id / reported_post_id / contract_id / roommate_request_id. Phân trang/lọc đúng scope; dữ liệu riêng tư bị loại trên server, không chỉ ẩn UI. Kiểm tra lỗi DB/provider không để lại cập nhật dở hoặc trả thành công giả. | AF160: Mở đặc tả
A161: API-160 | B161: Đánh giá & quản trị | C161: report | D161: POST | E161: /api/v1/admin/reports/{reportId}/decision | F161: Điều tra hoặc kết luận báo cáo | G161: ADMIN: tài khoản ACTIVE có dòng admins | H161: P1 | I161: Middleware auth/session/role + object scope D09: idempotency store nếu chưa có khóa tự nhiên | J161: SERVICE: cần triển khai giao dịch backend | K161: status: enum (bắt buộc) — INVESTIGATING / RESOLVED / DISMISSED. resolution: string (tùy chọn) — RESOLVED/DISMISSED bắt buộc nội dung kết luận. | L161: Report sau xử lý | M161: Khóa trạng thái nguồn, không mở lại bản đóng bằng form cũ; đóng có handled_by/time/resolution; audit. Ẩn/khóa dùng endpoint quyết định riêng. | N161: 400 BAD_REQUEST 401 UNAUTHENTICATED 403 FORBIDDEN 404 RESOURCE_NOT_FOUND 409 STATE_CONFLICT 409 IDEMPOTENCY_KEY_REUSED 422 VALIDATION_ERROR 422 REPORT_TARGET_INVALID 409 REPORT_ALREADY_CLOSED | P161: Chưa làm | Q161: Chưa | R161: Chưa | S161: Chưa | T161: Chưa | U161: Chưa | V161: Chưa | W161: Chưa | X161: Chưa | Y161: =COUNTIF(Q161:X161,"Xong")/8 -> 0 | AD161: Happy path: Điều tra hoặc kết luận báo cáo; kiểm tra Report sau xử lý. Thiếu phiên/phiên revoked/actor LOCKED và actor khác chủ hoặc khác participant phải bị chặn. Ràng buộc: Một report nhắm đúng một trong reported_user_id / reported_post_id / contract_id / roommate_request_id. Gửi lặp cùng khóa trả kết quả cũ; cùng khóa khác payload trả 409; hai request tranh cùng tài nguyên không vượt hạn mức. Kiểm tra lỗi DB/provider không để lại cập nhật dở hoặc trả thành công giả. | AF161: Mở đặc tả
A162: API-161 | B162: Đánh giá & quản trị | C162: lock-account | D162: GET | E162: /api/v1/admin/users | F162: Quản lý tài khoản và vai trò | G162: ADMIN: tài khoản ACTIVE có dòng admins | H162: P1 | I162: Middleware auth/session/role + object scope | J162: READ: truy vấn có scope quyền | K162: Không có JSON body | L162: User[] với thông tin tối thiểu | M162: Lọc role/status/q; không trả password/refresh/OTP hash. | N162: 400 BAD_REQUEST 401 UNAUTHENTICATED 403 FORBIDDEN 404 RESOURCE_NOT_FOUND 422 VALIDATION_ERROR | P162: Chưa làm | Q162: Chưa | R162: Chưa | S162: Chưa | T162: Chưa | U162: Chưa | V162: Chưa | W162: Chưa | X162: Chưa | Y162: =COUNTIF(Q162:X162,"Xong")/8 -> 0 | AD162: Happy path: Quản lý tài khoản và vai trò; kiểm tra User[] với thông tin tối thiểu. Thiếu phiên/phiên revoked/actor LOCKED và actor khác chủ hoặc khác participant phải bị chặn. Ràng buộc: users lưu locked_at, locked_by_id, lock_reason và trạng thái hợp lệ. Phân trang/lọc đúng scope; dữ liệu riêng tư bị loại trên server, không chỉ ẩn UI. Kiểm tra lỗi DB/provider không để lại cập nhật dở hoặc trả thành công giả. | AF162: Mở đặc tả
A163: API-162 | B163: Đánh giá & quản trị | C163: lock-account | D163: GET | E163: /api/v1/admin/users/{userId} | F163: Chi tiết trạng thái tài khoản | G163: ADMIN: tài khoản ACTIVE có dòng admins | H163: P1 | I163: Middleware auth/session/role + object scope | J163: READ: truy vấn có scope quyền | K163: Không có JSON body | L163: User,roles,verificationSummary | M163: Chỉ metadata cần quản trị; giấy tờ mở riêng theo quyền. | N163: 400 BAD_REQUEST 401 UNAUTHENTICATED 403 FORBIDDEN 404 RESOURCE_NOT_FOUND | P163: Chưa làm | Q163: Chưa | R163: Chưa | S163: Chưa | T163: Chưa | U163: Chưa | V163: Chưa | W163: Chưa | X163: Chưa | Y163: =COUNTIF(Q163:X163,"Xong")/8 -> 0 | AD163: Happy path: Chi tiết trạng thái tài khoản; kiểm tra User,roles,verificationSummary. Thiếu phiên/phiên revoked/actor LOCKED và actor khác chủ hoặc khác participant phải bị chặn. Ràng buộc: users lưu locked_at, locked_by_id, lock_reason và trạng thái hợp lệ. Phân trang/lọc đúng scope; dữ liệu riêng tư bị loại trên server, không chỉ ẩn UI. Kiểm tra lỗi DB/provider không để lại cập nhật dở hoặc trả thành công giả. | AF163: Mở đặc tả
A164: API-163 | B164: Đánh giá & quản trị | C164: lock-account | D164: POST | E164: /api/v1/admin/users/{userId}/lock | F164: Khóa tài khoản có lý do | G164: ADMIN: tài khoản ACTIVE có dòng admins | H164: P1 | I164: Middleware auth/session/role + object scope D09: idempotency store nếu chưa có khóa tự nhiên | J164: SERVICE: cần triển khai giao dịch backend | K164: reason: string (bắt buộc) — Không chỉ khoảng trắng; tối đa 1.000 ký tự. | L164: User {id,status:LOCKED,lockedAt} | M164: Khóa user, ghi reason/admin/time, revoke sessions và audit trong transaction. Không tự cho cư dân LEFT hoặc xóa nghĩa vụ/hợp đồng; view quyền nhà hết hiệu lực nếu landlord bị khóa. | N164: 400 BAD_REQUEST 401 UNAUTHENTICATED 403 FORBIDDEN 404 RESOURCE_NOT_FOUND 409 STATE_CONFLICT 409 IDEMPOTENCY_KEY_REUSED 422 VALIDATION_ERROR 409 ACCOUNT_STATE_CHANGED | P164: Chưa làm | Q164: Chưa | R164: Chưa | S164: Chưa | T164: Chưa | U164: Chưa | V164: Chưa | W164: Chưa | X164: Chưa | Y164: =COUNTIF(Q164:X164,"Xong")/8 -> 0 | AD164: Happy path: Khóa tài khoản có lý do; kiểm tra User {id,status:LOCKED,lockedAt}. Thiếu phiên/phiên revoked/actor LOCKED và actor khác chủ hoặc khác participant phải bị chặn. Ràng buộc: users lưu locked_at, locked_by_id, lock_reason và trạng thái hợp lệ. Gửi lặp cùng khóa trả kết quả cũ; cùng khóa khác payload trả 409; hai request tranh cùng tài nguyên không vượt hạn mức. Kiểm tra lỗi DB/provider không để lại cập nhật dở hoặc trả thành công giả. | AF164: Mở đặc tả
A165: API-164 | B165: Đánh giá & quản trị | C165: lock-account | D165: POST | E165: /api/v1/admin/users/{userId}/unlock | F165: Mở khóa tài khoản | G165: ADMIN: tài khoản ACTIVE có dòng admins | H165: P1 | I165: Middleware auth/session/role + object scope D09: idempotency store nếu chưa có khóa tự nhiên | J165: SERVICE: cần triển khai giao dịch backend | K165: reason: string (bắt buộc) — Không chỉ khoảng trắng; tối đa 1.000 ký tự. | L165: User {id,status:ACTIVE} | M165: Chỉ LOCKED; ghi audit, xóa metadata lock theo schema. Không tự khôi phục phiên đã thu hồi hoặc cấp thêm vai trò. | N165: 400 BAD_REQUEST 401 UNAUTHENTICATED 403 FORBIDDEN 404 RESOURCE_NOT_FOUND 409 STATE_CONFLICT 409 IDEMPOTENCY_KEY_REUSED 422 VALIDATION_ERROR 409 ACCOUNT_STATE_CHANGED | P165: Chưa làm | Q165: Chưa | R165: Chưa | S165: Chưa | T165: Chưa | U165: Chưa | V165: Chưa | W165: Chưa | X165: Chưa | Y165: =COUNTIF(Q165:X165,"Xong")/8 -> 0 | AD165: Happy path: Mở khóa tài khoản; kiểm tra User {id,status:ACTIVE}. Thiếu phiên/phiên revoked/actor LOCKED và actor khác chủ hoặc khác participant phải bị chặn. Ràng buộc: users lưu locked_at, locked_by_id, lock_reason và trạng thái hợp lệ. Gửi lặp cùng khóa trả kết quả cũ; cùng khóa khác payload trả 409; hai request tranh cùng tài nguyên không vượt hạn mức. Kiểm tra lỗi DB/provider không để lại cập nhật dở hoặc trả thành công giả. | AF165: Mở đặc tả
A166: API-165 | B166: Đánh giá & quản trị | C166: templates | D166: GET | E166: /api/v1/contract-templates | F166: Mẫu hợp đồng theo phiên bản | G166: LANDLORD: sở hữu nhà/phòng/hợp đồng hoặc ADMIN | H166: P1 | I166: Middleware auth/session/role + object scope | J166: READ: truy vấn có scope quyền | K166: Không có JSON body | L166: ContractTemplate[] | M166: Chủ chỉ active, admin xem tất cả; từng row là một version. | N166: 400 BAD_REQUEST 401 UNAUTHENTICATED 403 FORBIDDEN 404 RESOURCE_NOT_FOUND 422 VALIDATION_ERROR | P166: Chưa làm | Q166: Chưa | R166: Chưa | S166: Chưa | T166: Chưa | U166: Chưa | V166: Chưa | W166: Chưa | X166: Chưa | Y166: =COUNTIF(Q166:X166,"Xong")/8 -> 0 | AD166: Happy path: Mẫu hợp đồng theo phiên bản; kiểm tra ContractTemplate[]. Thiếu phiên/phiên revoked/actor LOCKED và actor khác chủ hoặc khác participant phải bị chặn. Ràng buộc: Mẫu có tên/phiên bản duy nhất, phiên bản > 0 và nội dung, các hợp đồng tham chiếu mẫu/phiên bản qua contract_revisions. Phân trang/lọc đúng scope; dữ liệu riêng tư bị loại trên server, không chỉ ẩn UI. Kiểm tra lỗi DB/provider không để lại cập nhật dở hoặc trả thành công giả. | AF166: Mở đặc tả
... A177: API-176 | B177: Đánh giá & quản trị | C177: audit | D177: GET | E177: /api/v1/admin/dashboard | F177: Tổng quan hàng đợi quản trị | G177: ADMIN: tài khoản ACTIVE có dòng admins | H177: P1 | I177: Middleware auth/session/role + object scope | J177: READ: truy vấn có scope quyền | K177: Không có JSON body | L177: {pendingIdentityCount,pendingLandlordCount,pendingHouseProofCount,pendingPostCount,pendingReportCount,userCount} | M177: Đếm các loại hồ sơ riêng, không cộng nhầm xác minh tài khoản và quyền nhà. Phân loại PENDING/INVESTIGATING cho báo cáo; chỉ tổng số liệu, không trả giấy tờ. | N177: 400 BAD_REQUEST 401 UNAUTHENTICATED 403 FORBIDDEN 404 RESOURCE_NOT_FOUND | P177: Chưa làm | Q177: Chưa | R177: Chưa | S177: Chưa | T177: Chưa | U177: Chưa | V177: Chưa | W177: Chưa | X177: Chưa | Y177: =COUNTIF(Q177:X177,"Xong")/8 -> 0 | AD177: Happy path: Tổng quan hàng đợi quản trị; kiểm tra {pendingIdentityCount,pendingLandlordCount,pendingHouseProofCount,pendingPostCount,pendingReportCount,userCount}. Thiếu phiên/phiên revoked/actor LOCKED và actor khác chủ hoặc khác participant phải bị chặn. Ràng buộc: moderation_actions nhắm đúng một loại đối tượng; các FK giữ liên kết với đối tượng hợp lệ. Phân trang/lọc đúng scope; dữ liệu riêng tư bị loại trên server, không chỉ ẩn UI. Kiểm tra lỗi DB/provider không để lại cập nhật dở hoặc trả thành công giả. | AF177: Mở đặc tả

Sheet Luong_Nghiep_vu
A1: ID luồng | B1: Nhóm | C1: Tên luồng | D1: Vai trò | E1: Điểm vào wireframe | F1: API liên quan | G1: Job / vận hành | H1: Trạng thái | I1: Giới hạn | J1: Bảng dữ liệu
A2: account-access | B2: Tài khoản & xác minh | C2: Tài khoản, đăng nhập và vai trò | D2: tenant, landlord, admin | E2: Thanh trên → chọn Người thuê / Chủ trọ / Quản trị | F2: API-001 API-002 API-003 | H2: ACTIVE: hoạt động LOCKED: bị khóa DISABLED: vô hiệu hóa | I2: Wireframe chưa có đăng ký/đăng nhập thật. Nút chọn vai trò dùng cho trình diễn, không phải cơ chế bảo mật. | J2: users, tenants, landlords, admins
A3: profile | B3: Tài khoản & xác minh | C3: Cập nhật hồ sơ cá nhân | D3: tenant, landlord, admin | E3: Tài khoản → thông tin cá nhân → Lưu | F3: API-004 API-005 | H3: Thông tin hiện tại → cập nhật thông tin | I3: Không dùng hồ sơ cá nhân để xác nhận đã thuê phòng hoặc có quyền cho thuê nhà. | J3: users, personal_profiles, files
A4: identity | B4: Tài khoản & xác minh | C4: Xác minh danh tính và hồ sơ tài khoản | D4: tenant, landlord, admin | E4: Người thuê: Tài khoản → Xác minh · Quản trị: Xác minh hồ sơ | F4: API-006 API-007 API-008 API-009 API-010 API-011 API-012 API-013 API-014 API-015 API-016 API-017 | H4: PENDING: chờ duyệt → APPROVED: chấp thuận PENDING → REJECTED: từ chối WITHDRAWN: đã rút (CSDL) | I4: Form xác minh người thuê hiện lưu tên tệp, chưa tải giấy tờ lên máy chủ. Khác với minh chứng nhà đang lưu Blob trong IndexedDB. Duyệt tài khoản không tự xác minh tất cả các nhà của chủ trọ. | J4: tenant_identity_verifications, landlord_verifications, files, moderation_actions
A5: sessions | B5: Tài khoản & xác minh | C5: OTP, quên mật khẩu, phiên và liên kết tài khoản cư trú | D5: tenant, landlord, admin, system | E5: Thiết kế CSDL · Tài khoản → Phiên đăng nhập (màn hình mô phỏng) | F5: API-018 API-019 API-020 API-021 API-022 API-023 API-024 API-025 API-026 API-027 API-028 | G5: JOB05 | H5: Mã còn hạn → consumed / revoked / hết hạn Phiên còn hạn → revoked / hết hạn | I5: Chưa có OTP/đổi mật khẩu/liên kết tài khoản thật. Nút thu hồi phiên trong demo chỉ báo thành công. | J5: auth_sessions, verification_tokens, room_tenants
A6: create-house | B6: Nhà, quyền cho thuê & phòng | C6: Thêm và sửa nhà trọ | D6: landlord | E6: Chủ trọ → Nhà & phòng → Thêm nhà trọ / Sửa thông tin nhà | F6: API-029 API-030 API-031 API-032 | H6: Chưa có nhà → nhà nháp / chưa xác minh Sửa thông tin → tăng phiên bản | I6: Lưu nhà chưa cho phép công khai tin hoặc lập hợp đồng mới. Không có chức năng chuyển quyền sở hữu nhà trên giao diện. | J6: rental_houses
A7: house-proof | B7: Nhà, quyền cho thuê & phòng | C7: Nộp và xét duyệt quyền cho thuê từng nhà | D7: landlord, admin | E7: Nhà & phòng → Xác minh quyền cho thuê · Quản trị → Xác minh hồ sơ → Quyền cho thuê từng nhà | F7: API-033 API-034 API-035 API-036 API-037 API-038 API-039 | H7: PENDING → APPROVED / REJECTED / WITHDRAWN APPROVED → SUPERSEDED / REVOKED / EXPIRED | I7: Tệp wireframe nằm trong IndexedDB cùng trình duyệt. Hai nhà mẫu có hồ sơ giả lập được gắn nhãn, không phải xác minh giấy tờ thực. Phê duyệt hiện áp dụng cả nhà; quản trị phải kiểm tra phạm vi bao phủ các phòng. Chưa có quyền cho thuê giới hạn một số phòng. | J7: rental_house_verifications, house_verification_documents, files, notifications, moderation_actions
A8: house-rights-expiry | B8: Nhà, quyền cho thuê & phòng | C8: Hết quyền, thu hồi hoặc đổi định danh nhà | D8: landlord, admin, system | E8: Nhà & phòng → Sửa nhà / Lịch sử xác minh · Quản trị → Hồ sơ nhà → Thu hồi | F8: API-040 API-041 | G8: JOB03 | H8: Đã xác minh → cần xác minh lại / hết hạn / bị thu hồi Phê duyệt mới → phê duyệt cũ SUPERSEDED | I8: Migration không tự duyệt nhà cũ. API phải sử dụng view công khai cùng thời điểm triển khai migration. | J8: rental_houses, rental_house_verifications, posts, contracts
A9: rooms | B9: Nhà, quyền cho thuê & phòng | C9: Thêm phòng, sức chứa và tình trạng phòng | D9: landlord, system | E9: Chủ trọ → Nhà & phòng → chọn nhà → Thêm phòng / Sửa | F9: API-042 API-043 API-044 API-045 API-175 | H9: AVAILABLE: trống RESERVED: giữ bởi hợp đồng mở OCCUPIED: có người ACTIVE MAINTENANCE: bảo trì | I9: Tình trạng phòng không thay thế chứng cứ người đang ở. Dữ liệu mâu thuẫn cần đối soát, không tự bỏ cư dân. | J9: rooms, room_tenants, contracts, occupant_join_requests
A10: room-detail | B10: Nhà, quyền cho thuê & phòng | C10: Chi tiết phòng: Bài đăng, Người ở, Dịch vụ | D10: tenant, landlord, admin | E10: Nhà & phòng → Xem chi tiết · Chi tiết tin → thông tin phòng | F10: API-046 API-047 API-048 API-049 | H10: Bài đăng ↔ Người ở ↔ Dịch vụ; ghi nhớ tab | I10: Người ngoài chỉ mở được phòng có tin công khai còn đủ quyền cho thuê. | J10: rooms, posts, room_tenants, room_services, house_services
A11: submit-post | B11: Tin đăng & tìm phòng | C11: Tạo, sửa và gửi duyệt tin đăng | D11: landlord | E11: Chủ trọ → Tin đăng → Tạo tin · hoặc Chi tiết phòng → Tạo bài cho phòng này | F11: API-050 API-051 API-052 | H11: DRAFT / APPROVED / REJECTED / HIDDEN → PENDING_REVIEW PENDING_REVIEW → sửa vẫn PENDING_REVIEW | I11: UI chưa có quản lý nhiều ảnh. Nhà chưa xác minh vẫn gửi bài chờ được, nhưng chưa công khai được. | J11: posts, post_images, post_amenities
A12: moderate-post | B12: Tin đăng & tìm phòng | C12: Duyệt, từ chối, ẩn và hiện lại tin | D12: landlord, admin | E12: Quản trị → Kiểm duyệt tin · Chủ trọ → Tin đăng → Ẩn tin | F12: API-053 API-054 API-055 API-056 | H12: PENDING_REVIEW → APPROVED / REJECTED APPROVED → HIDDEN → APPROVED | I12: Tin đã duyệt không có nghĩa phòng còn trống: trạng thái phòng và quyền nhà còn được kiểm tra riêng. | J12: posts, moderation_actions, rental_house_verifications
A13: discover | B13: Tin đăng & tìm phòng | C13: Tìm phòng, xem tin và lưu trái tim | D13: tenant | E13: Người thuê → Khám phá / Đã lưu | F13: API-057 API-058 API-059 API-060 API-061 | H13: Chưa lưu ↔ đã lưu: trái tim đỏ | I13: Khoảng cách trong demo là dữ liệu mẫu, chưa có tính khoảng cách GPS hoặc bản đồ thật. RESERVED/MAINTENANCE vẫn có thể hiện với nhãn tình trạng. | J13: posts, rooms, rental_houses, favorite_posts, post_amenities
A14: roommate-profile | B14: Hồ sơ & kết nối ở ghép | C14: Tạo hồ sơ ở ghép và xác định tình trạng chỗ ở | D14: tenant | E14: Người thuê → Ở ghép → Tạo hồ sơ ở ghép / Sửa hồ sơ | F14: API-062 API-063 API-064 | H14: Chưa tạo → active: hồ sơ đã tạo NO_ACCOMMODATION / EXTERNAL / IN_SYSTEM | I14: Lưu hồ sơ không tự gửi lời mời, tạo hợp đồng, giữ chỗ hoặc ghi đồng thuận thuê. | J14: roommate_profiles, room_tenants
A15: matching-criteria | B15: Hồ sơ & kết nối ở ghép | C15: Tiêu chí ghép linh động và danh sách người phù hợp | D15: tenant, admin, system | E15: Ở ghép → Người phù hợp · Thiết kế quản lý tiêu chí trong CSDL | F15: API-065 API-066 API-067 API-068 API-069 API-070 | H15: Tiêu chí active / ngừng dùng Giá trị tự khai + giá trị mong muốn + mức quan trọng | I15: Chưa có thuật toán ghép cặp thật hoặc quản trị tiêu chí trên UI. Thói quen trên form demo hiện là mô tả văn bản. | J15: lifestyle_criteria, profile_lifestyles, roommate_profiles
A16: roommate-invite | B16: Hồ sơ & kết nối ở ghép | C16: Ba tab ở ghép và phản hồi lời mời kết nối | D16: tenant | E16: Ở ghép → Người phù hợp / Lời mời dành cho bạn / Đã mời | F16: API-071 API-072 API-073 API-074 API-075 | H16: PENDING → ACCEPTED / REJECTED CANCELLED và ended_at: có trong CSDL | I16: UI chưa có trọn luồng hủy/kết thúc kết nối. Lời mời cũ vẫn có thể phản hồi khi chưa tạo hồ sơ mới. | J16: roommate_requests, conversations, conversation_participants
A17: room-chat | B17: Tin nhắn & thông báo | C17: Nhắn chủ trọ theo ngữ cảnh tin/phòng | D17: tenant, landlord | E17: Chi tiết tin → Nhắn tin · hoặc Tin nhắn → chọn hội thoại | F17: API-076 API-077 API-078 API-079 API-080 API-081 API-082 API-083 | H17: ROOM_INQUIRY: hỏi thuê phòng Tin TEXT / IMAGE / SYSTEM / POST_SHARE (CSDL) | I17: Tin và lịch không phải hai bản sao trạng thái. Chưa có máy chủ chat xuyên thiết bị hoặc tải ảnh chat thực. | J17: conversations, conversation_participants, chat_messages, room_viewing_requests
A18: roommate-chat | B18: Tin nhắn & thông báo | C18: Chat riêng giữa hai bạn ghép | D18: tenant | E18: Ở ghép → Chấp nhận / Nhắn tin · Tin nhắn → Bạn ghép | F18: API-084 | H18: ACCEPTED, chưa ended_at → được mở/gửi chat | I18: Muốn thuê chung phải thực hiện luồng hợp đồng hoặc yêu cầu thêm người riêng. | J18: roommate_requests, conversations, conversation_participants, chat_messages
A19: share-post | B19: Tin nhắn & thông báo | C19: Chia sẻ đúng tin phòng cho bạn ghép | D19: tenant | E19: Chi tiết tin → Chia sẻ cho bạn ghép · Chat bạn ghép → Chia sẻ phòng | F19: API-085 | H19: Bài còn công khai → thẻ mở được Bài ẩn / mất quyền / không tồn tại → thẻ không còn hiển thị | I19: Chia sẻ là giới thiệu tin, không phải đồng ý thuê hoặc quyền ưu tiên thuê. | J19: chat_messages, posts, roommate_requests
A20: notifications | B20: Tin nhắn & thông báo | C20: Chuông, bộ đếm và popup thông báo mới | D20: tenant, landlord, admin, system | E20: Chuông trên thanh trên · Popup khi có thông báo mới | F20: API-086 API-087 API-088 API-089 API-090 | G20: JOB06 | H20: Chưa đọc → đã đọc; đóng popup không đồng nghĩa đã đọc | I20: Hiện truyền giữa hai tab cùng nguồn trình duyệt qua storage event; chưa có email, SMS, push hoặc máy chủ realtime. | J20: notifications, users, chat_messages
A21: propose-viewing | B21: Hẹn xem & quyết định thuê | C21: Người thuê đề nghị lịch xem, chủ trọ xét duyệt | D21: tenant, landlord | E21: Người thuê → Chi tiết tin / Tin nhắn → Đề nghị lịch xem | F21: API-083 API-091 API-092 API-093 API-094 | G21: JOB01 | H21: PENDING → ACCEPTED / REJECTED / WITHDRAWN / EXPIRED ACCEPTED → lịch SCHEDULED có liên kết | I21: Đổi giờ bằng rút/gửi đề nghị mới hoặc hủy lịch đã chốt. Lịch hủy không xóa lịch sử ACCEPTED của đề nghị. | J21: room_viewing_proposals, room_viewing_requests, notifications
A22: schedule-viewing | B22: Hẹn xem & quyết định thuê | C22: Chủ trọ tự tạo lịch sau khi đã trao đổi | D22: landlord, tenant | E22: Chủ trọ → Tin nhắn / Lịch xem → Tạo lịch xem | F22: API-083 API-095 API-096 API-097 | H22: Tạo lịch trực tiếp → SCHEDULED | I22: Có nhiều lịch khác giờ cho một phòng; xem trước không tạo quyền ưu tiên thuê. | J22: conversations, chat_messages, room_viewing_requests
A23: viewing-outcome | B23: Hẹn xem & quyết định thuê | C23: Xác nhận đã xem, không đến, hủy và ý định thuê | D23: tenant, landlord | E23: Lịch xem / thẻ lịch trong Tin nhắn | F23: API-098 API-099 API-100 | H23: SCHEDULED → COMPLETED / NO_SHOW / CANCELLED WAITING → AGREED / DECLINED; AGREED → WITHDRAWN | I23: Không đảo ngược quyết định bằng nút/form cũ; cần theo đúng chuyển trạng thái cho phép. | J23: room_viewing_requests, contracts
A24: create-contract | B24: Hợp đồng & vào ở | C24: Lập hợp đồng thuê mới từ lịch đã xem | D24: landlord, tenant | E24: Chủ trọ → Lịch xem COMPLETED, AGREED → Lập hợp đồng | F24: API-101 API-102 API-103 | H24: Hợp đồng PENDING_CONFIRMATION; phòng RESERVED; thành viên PLANNED | I24: Người phụ có thể chưa có tài khoản, vẫn có dòng cư trú riêng. Mở form hoặc bấm AGREED chưa giữ phòng. | J24: contracts, contract_revisions, room_tenants, contract_representative_history
A25: reserve-cleanup | B25: Hợp đồng & vào ở | C25: Tự xử lý lịch/đề nghị khi hợp đồng giữ phòng | D25: landlord, tenant, system | E25: Tự chạy khi chủ trọ gửi hợp đồng mới | F25: API-103 API-104 | H25: Lịch tương lai SCHEDULED → CANCELLED Đề nghị còn hạn PENDING → REJECTED; quá giờ → EXPIRED | I25: Lịch đã diễn ra/đang diễn ra không bị biến thành hủy tự động. | J25: contracts, room_viewing_requests, room_viewing_proposals, notifications
A26: contract-revision | B26: Hợp đồng & vào ở | C26: Xác nhận nội dung hoặc yêu cầu sửa hợp đồng | D26: tenant, landlord | E26: Hợp đồng → Xem chi tiết → Xác nhận / Yêu cầu sửa | F26: API-105 API-106 API-107 API-108 API-109 | H26: PENDING_CONFIRMATION → CONFIRMED Yêu cầu sửa → phiên bản cũ CANCELLED + bản DRAFT → PENDING_CONFIRMATION | I26: Wireframe mô phỏng xác nhận; chưa có chữ ký điện tử, tài liệu ký số hoặc dịch vụ ký từ xa. | J26: contracts, contract_revisions
A27: move-in | B27: Hợp đồng & vào ở | C27: Xác nhận người thuê thực tế vào ở | D27: landlord, tenant | E27: Chủ trọ → Hợp đồng → Xác nhận vào ở / xác nhận từng thành viên | F27: API-110 | H27: PLANNED → ACTIVE CONFIRMED → ACTIVE (Còn hiệu lực) | I27: Không cho tài khoản đang ở nơi khác vào thêm lượt ACTIVE; phải giải quyết lượt ở trước. | J27: room_tenants, contracts, rooms
A28: cancel-contract | B28: Hợp đồng & vào ở | C28: Hủy trước vào ở, hủy người dự kiến và nhập giấy | D28: landlord, tenant, system | E28: Hợp đồng chưa vào ở → Hủy · Người ở → Hủy dự kiến | F28: API-111 API-112 API-113 | H28: Hợp đồng chưa ACTIVE → CANCELLED PLANNED → CANCELLED | I28: Demo có dữ liệu nhập giấy mẫu, chưa có form nhập hợp đồng giấy đầy đủ. | J28: contracts, room_tenants, files, contract_revisions
A29: residents | B29: Người ở & đại diện | C29: Danh sách người ở, lịch sử và xuất CSV | D29: landlord | E29: Chủ trọ → Người ở · Hợp đồng → thành viên / lịch sử | F29: API-114 API-115 API-116 | H29: PLANNED / ACTIVE / LEFT / CANCELLED | I29: Không tự sửa dữ liệu lịch sử mâu thuẫn bằng suy đoán ngày rời phòng. | J29: room_tenants, contracts, contract_representative_history
A30: join-consent | B30: Người ở & đại diện | C30: Đề nghị thêm người và hai đồng ý thuê chung | D30: tenant, landlord | E30: Nghiệp vụ thuê chung → yêu cầu thêm người → Chủ trọ / Người ở | F30: API-117 API-118 API-119 API-120 | H30: PENDING_CONSENT → PENDING_LANDLORD PENDING_LANDLORD → APPROVED / REJECTED / CANCELLED | I30: Demo có yêu cầu/đồng ý mẫu và xử lý duyệt, chưa có đầy đủ form hai bên tạo/xác nhận yêu cầu mới. | J30: occupant_join_requests, roommate_requests, contracts
A31: join-hold | B31: Người ở & đại diện | C31: Duyệt thêm người, giữ 48 giờ và hoàn tất vào ở | D31: landlord, tenant, system | E31: Chủ trọ → Người ở → Yêu cầu thêm người | F31: API-121 API-122 API-123 API-124 | G31: JOB02 | H31: PENDING_LANDLORD → APPROVED → COMPLETED APPROVED → CANCELLED / EXPIRED; chờ → REJECTED | I31: Giữ chỗ cho người ở ghép khác với giữ cả phòng bằng hợp đồng mới. | J31: occupant_join_requests, room_tenants, rooms
A32: departure | B32: Người ở & đại diện | C32: Thành viên rời phòng và người cuối cùng rời | D32: landlord | E32: Chủ trọ → Người ở → Xác nhận rời | F32: API-125 | H32: ACTIVE → LEFT Hết thành viên mở → hợp đồng kết thúc; phòng tính lại | I32: Thành viên PLANNED chưa đến dùng hủy dự kiến, không chuyển LEFT với ngày vào giả. | J32: room_tenants, contracts, contract_representative_history, occupant_join_requests
A33: handover | B33: Người ở & đại diện | C33: Bàn giao đại diện khi người đại diện rời | D33: landlord, tenant | E33: Người ở → đại diện → Xác nhận rời → Bàn giao · Hợp đồng → Lịch sử đại diện | F33: API-126 API-127 API-128 | H33: Đại diện cũ → giai đoạn đóng; đại diện mới → giai đoạn hiện hành Hợp đồng vẫn ACTIVE, phòng vẫn OCCUPIED | I33: Demo là chủ trọ ghi nhận đồng ý, chưa phải người nhận tự đăng nhập ký phụ lục. Dữ liệu cũ không biết thời điểm nhận thì để chưa rõ, không đoán theo ngày ký. | J33: contract_representative_history, contracts, room_tenants, notifications
A34: change-request | B34: Gia hạn, đổi phòng, kết thúc | C34: Luồng chung yêu cầu điều chỉnh hợp đồng | D34: tenant, landlord | E34: Người thuê → Hợp đồng → Chi tiết → Yêu cầu · Chủ trọ → Hợp đồng → Yêu cầu gia hạn / điều chỉnh | F34: API-129 API-130 API-131 API-132 API-133 API-134 API-135 | H34: PENDING → APPROVED_WAITING_CONFIRMATION → READY_TO_APPLY → COMPLETED PENDING → REJECTED; CANCELLED / EXPIRED có trong CSDL | I34: Chưa có trình chỉnh giá/điều khoản tùy ý trong form gia hạn; thay đổi trên UI hiện chủ yếu là gia hạn, đổi phòng và chấm dứt. | J34: contract_change_requests, contracts, contract_revisions
A35: renewal | B35: Gia hạn, đổi phòng, kết thúc | C35: Gia hạn thời hạn hợp đồng | D35: tenant, landlord | E35: Hợp đồng → Chi tiết → Yêu cầu gia hạn | F35: API-130 API-135 | H35: RENEWAL theo luồng duyệt chung → COMPLETED | I35: Luồng chưa thương lượng giá/điều khoản mới đầy đủ; demo không dùng API hoặc ký số. | J35: contract_change_requests, contracts, contract_revisions
A36: transfer | B36: Gia hạn, đổi phòng, kết thúc | C36: Đổi sang phòng khác và tạo hợp đồng chuyển phòng | D36: tenant, landlord | E36: Hợp đồng → Chi tiết → Yêu cầu thay đổi → chọn phòng đích | F36: API-130 API-135 API-136 | H36: Nguồn: ACTIVE → TERMINATED, người đang ở → LEFT Đích: CONFIRMED + PLANNED; phòng RESERVED → OCCUPIED khi vào | I36: Đích không đủ chỗ hoặc mất quyền cho thuê thì chưa thay đổi hợp đồng nguồn. | J36: contracts, room_tenants, contract_change_requests, contract_representative_history
A37: end-lease | B37: Gia hạn, đổi phòng, kết thúc | C37: Yêu cầu chấm dứt và đóng hợp đồng | D37: tenant, landlord | E37: Hợp đồng → Chi tiết → Yêu cầu chấm dứt | F37: API-130 API-135 | G37: OPS03 | H37: Yêu cầu TERMINATION → COMPLETED Hợp đồng ACTIVE → TERMINATED | I37: Chưa mô phỏng quyết toán cọc hoặc tự động kết thúc vì đến hạn; EXPIRED có trong SQL nhưng cần tác vụ máy chủ phù hợp. | J37: contracts, contract_change_requests, room_tenants, contract_representative_history, invoices
A38: services | B38: Dịch vụ & hóa đơn | C38: Dịch vụ theo nhà và giá riêng theo phòng | D38: landlord | E38: Chủ trọ → Dịch vụ → chọn nhà / phòng | F38: API-137 API-138 API-139 API-140 API-141 API-142 API-143 API-144 | H38: Dịch vụ tại nhà active / ngừng; áp dụng tại phòng active / ngừng | I38: Demo giữ cấu hình danh mục/nhà trong mảng services; API phải ánh xạ thành các bảng tương ứng. | J38: rental_services, house_services, room_services, invoice_items
A39: bill | B39: Dịch vụ & hóa đơn | C39: Lập và sửa bản nháp hóa đơn | D39: landlord | E39: Chủ trọ → Hóa đơn → Lập hóa đơn → Lưu nháp | F39: API-145 API-146 API-147 API-148 | H39: Chưa có kỳ → DRAFT; sửa vẫn DRAFT | I39: Cần API kiểm tra quyền/tổng tiền toàn diện; một số đầu vào demo còn dựa vào kiểm tra form HTML. | J39: invoices, invoice_items, room_services
A40: pay-invoice | B40: Dịch vụ & hóa đơn | C40: Phát hành, thu tiền, hủy và hóa đơn quá hạn | D40: landlord, tenant, system | E40: Hóa đơn → Chi tiết → Phát hành / Thu tiền / Hủy | F40: API-149 API-150 API-151 API-152 | G40: JOB04 | H40: DRAFT → UNPAID → PAID UNPAID → CANCELLED; OVERDUE có trong CSDL | I40: Chưa có cổng thanh toán, đối soát ngân hàng, biên nhận số hoặc worker quá hạn thực. | J40: invoices, invoice_items
A41: review | B41: Đánh giá & quản trị | C41: Đánh giá phòng theo bằng chứng đã thuê | D41: tenant, admin | E41: Người thuê → Hợp đồng đã chấm dứt → Đánh giá phòng | F41: API-153 API-154 API-155 | H41: PUBLISHED / HIDDEN / DELETED (CSDL) | I41: Nút hiện khi hợp đồng TERMINATED; handler hiện kiểm tra thành viên ACTIVE/LEFT, chưa kiểm tra đầy đủ chính sách thời điểm. Chưa có luồng sửa/phản hồi/kiểm duyệt đánh giá đầy đủ. | J41: reviews, room_tenants
A42: report | B42: Đánh giá & quản trị | C42: Báo cáo vi phạm và kết luận xử lý | D42: tenant, admin | E42: Chi tiết tin → Báo cáo · Quản trị → Báo cáo → xử lý | F42: API-156 API-157 API-158 API-159 API-160 | H42: PENDING → RESOLVED (demo) INVESTIGATING / DISMISSED: có trong CSDL | I42: Wireframe hiện chủ yếu báo cáo tin; chưa có quy trình tranh chấp/đính kèm minh chứng đầy đủ. | J42: reports, files, moderation_actions
A43: lock-account | B43: Đánh giá & quản trị | C43: Khóa và mở khóa tài khoản | D43: admin | E43: Quản trị → Tài khoản → Khóa / Mở khóa | F43: API-161 API-162 API-163 API-164 | H43: ACTIVE ↔ LOCKED; DISABLED có trong SQL | I43: Đây là mô phỏng quyết định, chưa phải cơ chế ngăn truy cập bảo mật trên máy chủ. | J43: users, auth_sessions, moderation_actions
A44: templates | B44: Đánh giá & quản trị | C44: Mẫu hợp đồng và phiên bản mẫu | D44: admin, landlord | E44: Quản trị → Mẫu hợp đồng · Chủ trọ → Lập hợp đồng → chọn mẫu | F44: API-165 API-166 API-167 | H44: Mẫu active / ngừng; version tăng khi tạo phiên bản mới | I44: Mẫu không tự bảo đảm tính pháp lý và chưa có ký số; người lập vẫn kiểm tra điều khoản cụ thể. | J44: contract_templates, contract_revisions
A45: audit | B45: Đánh giá & quản trị | C45: Nhật ký kiểm duyệt và truy vết thay đổi | D45: admin, system | E45: Quản trị → Nhật ký | F45: API-168 API-169 API-176 | H45: Sự kiện quyết định → bản ghi audit được giữ | I45: Danh sách audit demo chưa mô phỏng mọi cột của SQL và mọi thay đổi dữ liệu. | J45: moderation_actions
A46: data-safety | B46: Dữ liệu & tích hợp | C46: Ràng buộc chung, giao dịch và dữ liệu lịch sử | D46: system, tenant, landlord, admin | E46: Áp dụng cho toàn hệ thống · database/schema.sql + database/source/ | F46: Không có HTTP endpoint | G46: OPS02 | H46: Kiểm tra → khóa/đọc lại → ghi cùng giao dịch → commit hoặc rollback | I46: Wireframe hiện chạy localStorage; đồng bộ tab dùng storage event. Chưa có API bảo mật hoặc giao dịch máy chủ nối với giao diện. | J46: contracts, room_tenants, contract_representative_history, invoices, notifications
A47: file-storage | B47: Dữ liệu & tích hợp | C47: Tệp, quyền riêng tư và giới hạn lưu trữ | D47: tenant, landlord, admin, system | E47: Tệp minh chứng nhà / căn cước / hợp đồng / báo cáo | F47: API-170 API-171 API-172 API-173 API-174 | H47: STAGED → ACTIVE; ARCHIVED / DELETED theo chính sách | I47: Tệp cục bộ không có ở máy/trình duyệt khác. Chuyển vai trò demo không thay thế phân quyền kho tệp thật. | J47: files, house_verification_documents
A48: migration | B48: Dữ liệu & tích hợp | C48: Tạo CSDL mới, nâng cấp và giới hạn triển khai | D48: system, admin | E48: database/schema.sql · database/migrations/ · README.md | F48: Không có HTTP endpoint | G48: OPS01 | H48: Schema mới hoặc nâng cấp một lần theo thứ tự; không chạy cả hai lên cùng CSDL mới | I48: Các kiểm thử SQL dùng MySQL tạm. Chưa áp dụng migration lên CSDL thật hoặc triển khai backend chỉ bằng mở wireframe. | J48: rental_houses, rental_house_verifications, posts, contract_representative_history

Sheet Rang_buoc
A1: ID luồng | B1: Tên luồng | C1: Lớp bảo vệ | D1: Ràng buộc từ nguồn
A2: account-access | B2: Tài khoản, đăng nhập và vai trò | C2: DB | D2: Email và số điện thoại có khóa duy nhất; phải có ít nhất một thông tin liên hệ. Vai trò chính thuộc TENANT / LANDLORD / ADMIN.
A3: account-access | B3: Tài khoản, đăng nhập và vai trò | C3: DB | D3: Các bảng tenants, landlords, admins tham chiếu users, hỗ trợ lưu quan hệ vai trò riêng; không suy quyền chỉ từ tên hiển thị.
A4: account-access | B4: Tài khoản, đăng nhập và vai trò | C4: API | D4: Actor ID phải lấy từ phiên đã xác thực, không tin ID hoặc vai trò do trình duyệt gửi lên.
A5: profile | B5: Cập nhật hồ sơ cá nhân | C5: UI | D5: Handler hiện mới lưu tên; các trường điện thoại, email, địa chỉ trên form chưa được lưu đầy đủ.
A6: profile | B6: Cập nhật hồ sơ cá nhân | C6: DB | D6: personal_profiles có một hồ sơ cho mỗi user; thông tin cá nhân không mặc định là dữ liệu công khai.
A7: profile | B7: Cập nhật hồ sơ cá nhân | C7: API | D7: Thay đổi liên hệ cần kiểm tra trùng và quy trình xác thực tương ứng.
A8: identity | B8: Xác minh danh tính và hồ sơ tài khoản | C8: DB | D8: Mỗi người chỉ có một hồ sơ xác minh cùng loại đang PENDING; quyết định duyệt/từ chối lưu người và thời điểm.
A9: identity | B9: Xác minh danh tính và hồ sơ tài khoản | C9: DB | D9: Giấy tờ danh tính dùng files với quyền PRIVATE.
A10: identity | B10: Xác minh danh tính và hồ sơ tài khoản | C10: API | D10: Phải kiểm tra nội dung tệp, đối chiếu danh tính và chính sách lưu giấy tờ trên máy chủ.
A11: sessions | B11: OTP, quên mật khẩu, phiên và liên kết tài khoản cư trú | C11: DB | D11: selector, session_key và refresh_token_hash có khóa duy nhất; expires_at phải sau created_at.
A12: sessions | B12: OTP, quên mật khẩu, phiên và liên kết tài khoản cư trú | C12: DB | D12: Số lần thử từ 0 đến max_attempts. Token OCCUPANT_LINK phải có target_room_tenant_id; token mục đích khác không có liên kết này.
... A161: migration | B161: Tạo CSDL mới, nâng cấp và giới hạn triển khai | C161: API | D161: Ánh xạ dữ liệu demo sang SQL thay vì đưa nguyên JSON JavaScript vào bảng hoặc coi tài khoản mẫu là phiên đăng nhập.

Sheet DTO_Fields
A1: API | B1: Method / path | C1: Field | D1: Type | E1: Bắt buộc | F1: Ràng buộc | G1: Ví dụ
A2: API-001 | B2: POST /auth/register | C2: fullName | D2: string | E2: Có | F2: 1–150 ký tự. | G2: "Nguyễn Thị Lan"
A3: API-001 | B3: POST /auth/register | C3: email | D3: string | E3: Không | F3: Email chuẩn hóa, ≤150, duy nhất. | G3: ""
A4: API-001 | B4: POST /auth/register | C4: phoneNumber | D4: string | E4: Không | F4: Chuẩn hóa số điện thoại, ≤20, duy nhất. | G4: "0901234567"
A5: API-001 | B5: POST /auth/register | C5: password | D5: string | E5: Có | F5: Chính sách mật khẩu backend; không log/lưu nguyên văn. | G5: "Example-only-change-me"
A6: API-002 | B6: POST /auth/login | C6: identifier | D6: string | E6: Có | F6: Email hoặc điện thoại đã chuẩn hóa. | G6: "0901234567"
A7: API-002 | B7: POST /auth/login | C7: password | D7: string | E7: Có | F7: So sánh hash an toàn. | G7: "Example-only-change-me"
A8: API-004 | B8: PATCH /me/profile | C8: fullName | D8: string | E8: Không | F8: 1–150 ký tự sau trim. | G8: "Nguyễn Thị Lan"
A9: API-004 | B9: PATCH /me/profile | C9: address | D9: string | E9: Không | F9: Tối đa 500 ký tự. | G9: ""
A10: API-004 | B10: PATCH /me/profile | C10: gender | D10: string | E10: Không | F10: Tối đa 30 ký tự. | G10: ""
A11: API-004 | B11: PATCH /me/profile | C11: occupation | D11: string | E11: Không | F11: Tối đa 150 ký tự. | G11: ""
A12: API-004 | B12: PATCH /me/profile | C12: university | D12: string | E12: Không | F12: Tối đa 200 ký tự. | G12: ""
... A252: API-170 | B252: POST /files/upload-sessions | C252: sha256 | D252: string | E252: Có | F252: 64 ký tự hex; xác minh sau upload. | G252: "aaaaaaaaaaaaaaaaaaaaaaaaaaaaaaaaaaaaaaaaaaaaaaaaaaaaaaaaaaaaaaaa"

Sheet Du_lieu
A1: Bảng | B1: Cột | C1: Định nghĩa SQL hiện tại | D1: Nguồn | E1: Luồng tham chiếu
A2: users | B2: id | C2: BIGINT NOT NULL AUTO_INCREMENT PRIMARY KEY | D2: database/schema.sql:10 | E2: account-access, profile, notifications, lock-account
A3: users | B3: email | C3: VARCHAR(150) | D3: database/schema.sql:10 | E3: account-access, profile, notifications, lock-account
A4: users | B4: phone_number | C4: VARCHAR(20) | D4: database/schema.sql:10 | E4: account-access, profile, notifications, lock-account
A5: users | B5: password_hash | C5: VARCHAR(255) NOT NULL | D5: database/schema.sql:10 | E5: account-access, profile, notifications, lock-account
A6: users | B6: full_name | C6: VARCHAR(150) NOT NULL | D6: database/schema.sql:10 | E6: account-access, profile, notifications, lock-account
A7: users | B7: role | C7: VARCHAR(40) NOT NULL DEFAULT 'TENANT' | D7: database/schema.sql:10 | E7: account-access, profile, notifications, lock-account
A8: users | B8: status | C8: VARCHAR(40) NOT NULL DEFAULT 'ACTIVE' | D8: database/schema.sql:10 | E8: account-access, profile, notifications, lock-account
A9: users | B9: phone_verified_at | C9: DATETIME(6) | D9: database/schema.sql:10 | E9: account-access, profile, notifications, lock-account
A10: users | B10: locked_at | C10: DATETIME(6) | D10: database/schema.sql:10 | E10: account-access, profile, notifications, lock-account
A11: users | B11: in_app_enabled | C11: BOOLEAN NOT NULL DEFAULT TRUE | D11: database/schema.sql:10 | E11: account-access, profile, notifications, lock-account
A12: users | B12: email_enabled | C12: BOOLEAN NOT NULL DEFAULT FALSE | D12: database/schema.sql:10 | E12: account-access, profile, notifications, lock-account
... A584: house_verification_documents | B584: created_at | C584: DATETIME(6) NOT NULL DEFAULT CURRENT_TIMESTAMP(6) | D584: database/schema.sql:2571 | E584: house-proof, file-storage

Sheet Quyet_dinh
A1: ID | B1: Vấn đề | C1: Ưu tiên | D1: Tình trạng thiết kế | E1: Nội dung cần chốt | F1: Vai trò phụ trách | G1: Theo dõi | H1: Quyết định / ngày | I1: Người chốt
A2: D01 | B2: Chính sách xác thực | C2: P0 | D2: Cần chốt | E2: TTL access/refresh/OTP, giới hạn gửi/thử, mật khẩu, provider email/SMS. SQL có expires_at/max_attempts; chưa có cấu hình vận hành. | F2: Backend + chủ sản phẩm | G2: Chưa chốt
A3: D02 | B3: Thuật toán ghép cặp | C3: P1 | D3: Cần chốt | E3: Điểm số, trọng số, tiêu chí bắt buộc, xử lý thiếu dữ liệu và phiên bản thuật toán; chưa có thuật toán thật. | F3: Chủ sản phẩm | G3: Chưa chốt
A4: D03 | B4: Đọc chat sau kết thúc kết nối | C4: P1 | D4: Cần chốt | E4: Wireframe chỉ mở/gửi khi kết nối còn hiệu lực; đề xuất giữ lịch sử đọc cho hai bên sau ended, chặn gửi. Chưa coi đề xuất là rule đã duyệt. | F4: Chủ sản phẩm | G4: Chưa chốt
A5: D04 | B5: Kênh email/push | C5: P2 | D5: Phụ thuộc hạ tầng | E5: users có flags nhưng chưa có provider, device token registry hoặc delivery ledger; chỉ bảo đảm in-app trước. | F5: Backend | G5: Chưa chốt
A6: D05 | B6: Kho tệp và hạn lưu | C6: P0 | D6: Cần chốt | E6: Proof nhà có giới hạn rõ 8×5 MB; giới hạn mục đích khác, quét nội dung, TTL link, hạn lưu CCCD/hợp đồng và xóa object cần chính sách. | F6: Chủ sản phẩm + Backend | G6: Chưa chốt
A7: D06 | B7: Liên kết cư dân với tài khoản | C7: P1 | D7: Cần chốt | E7: Xác minh đúng người nhận token OCCUPANT_LINK, kênh gửi và xử lý danh tính không khớp; không ghép theo tên tự khai. | F7: Chủ sản phẩm | G7: Chưa chốt
A8: D07 | B8: Gửi tin kèm nhiều ảnh atomically | C8: P0 | D8: Cần mở rộng SQL | E8: sp_submit_post chỉ ghi posts và tự COMMIT. Muốn gửi imageFileIds/amenities cùng transaction phải mở rộng procedure/DTO; không bọc CALL trong transaction ngoài. | F8: Backend + DBA | G8: Chưa chốt
A9: D08 | B9: Get-or-create chat hỏi phòng | C9: P1 | D9: Cần thiết kế | E9: Giữ một conversation/room/post ở lớp ghi; gộp nhiều context theo peer ở lớp đọc. Cần unique/khóa cho cặp inquiry để chống trùng đồng thời. | F9: Backend + DBA | G9: Chưa chốt
A10: D09 | B10: Idempotency và realtime bền vững | C10: P0 | D10: Cần hạ tầng bổ sung | E10: Chỉ nhà/proposal/chat có khóa riêng hiện hữu; các POST khác cần idempotency store, request hash và response cache. Replay SSE bền vững cần outbox/event store, không có bảng sẵn. | F10: Backend + DBA | G10: Chưa chốt
A11: D10 | B11: Xác nhận đúng phiên bản | C11: P0 | D11: Cần mở rộng procedure | E11: sp_confirm_contract nhận contract+tenant, không nhận expected revision; cần so revisionId dưới cùng khóa transaction trước xác nhận để tránh TOCTOU. | F11: Backend + DBA | G11: Chưa chốt
A12: D11 | B12: Nhập hợp đồng giấy | C12: P2 | D12: Cần thiết kế | E12: Source PAPER_IMPORT có trong SQL nhưng chưa có import transaction đầy đủ; yêu cầu quyền riêng, chứng cứ đã ký và JSON member/state/date. Chưa tính route này sẵn sàng coding ngay. | F12: Backend + chủ sản phẩm | G12: Chưa chốt
A13: D12 | B13: Thanh toán và trường người ghi nhận | C13: P1 | D13: Giới hạn phạm vi | E13: Chỉ thu toàn bộ do chủ ghi nhận; kiểm tra paid_by_id/payer theo schema. Thanh toán online, trả một phần, hoàn cọc và đối soát cần bảng giao dịch mới, không thuộc API cơ sở. | F13: Chủ sản phẩm | G13: Chưa chốt
... A16: D15 | B16: Phiên bản CRUD tổng quát | C16: P0 | D16: Cần thiết kế | E16: Chỉ house.row_version, post.content_version, roommate.profile_version có sẵn. Các tài nguyên khác dùng revision ID/state/updated_at compare-and-swap trong service; không giả có row_version toàn hệ thống. | F16: Backend + DBA | G16: Chưa chốt

Sheet Tac_vu_nen
A1: ID | B1: Công việc | C1: Luồng | D1: Lịch chạy đề xuất | E1: Adapter | F1: Nghiệp vụ | G1: Nghiệm thu | H1: Owner | I1: Trạng thái | J1: Bằng chứng
A2: JOB01 | B2: Hết hạn đề nghị xem | C2: propose-viewing | D2: Theo phút (đề xuất) | E2: sp_expire_viewing_proposals | F2: PENDING có starts_at≤UTC now → EXPIRED. Read/write vẫn kiểm tra thời gian ngay cả khi job trễ. | G2: Retry không tạo thêm lịch; không công khai API job. | I2: Chưa làm
A3: JOB02 | B3: Hết hạn giữ chỗ thêm người | C3: join-hold | D3: Theo phút (đề xuất) | E3: SERVICE: transaction mới | F3: APPROVED hold_expires_at≤now → EXPIRED; không chạm COMPLETED/member đã tạo. | G3: Capacity không tính hold quá hạn kể cả job chưa chạy. | I3: Chưa làm
A4: JOB03 | B4: Quyền nhà quá hạn | C4: house-rights-expiry | D4: Hàng ngày theo Việt Nam (đề xuất) | E4: SERVICE: transaction mới | F4: APPROVED valid_until < todayVN → EXPIRED, giữ hồ sơ/tệp; view hiệu lực chặn ngay. | G4: Không tự kết thúc hợp đồng cũ, không tự xóa tin. | I4: Chưa làm
A5: JOB04 | B5: Hóa đơn quá hạn | C5: pay-invoice | D5: Hàng ngày theo Việt Nam (đề xuất) | E5: SERVICE: transaction mới | F5: UNPAID có due_date<todayVN → OVERDUE; không sửa PAID/CANCELLED. | G5: Lặp không gửi trùng nhắc nợ; event_key ổn định. | I5: Chưa làm
A6: JOB05 | B6: Dọn token/phiên/tệp staged | C6: sessions | D6: Hàng ngày (đề xuất) | E6: SERVICE: retention worker | F6: Thu hồi/xóa theo chính sách D01/D05, không xóa tệp proof/hợp đồng đang được giữ. | G6: Kiểm tra tham chiếu trước khi xóa object; không log OTP. | I6: Chưa làm
A7: JOB06 | B7: Phát sự kiện sau commit | C7: notifications | D7: Liên tục (đề xuất) | E7: OUTBOX/queue cần bổ sung | F7: Delivery theo eventId/recipient, retry/backoff/dedupe; chỉ phát dữ liệu tối thiểu. | G7: Giữ nghiệp vụ đúng nếu kênh SSE mất kết nối; client fetch lại. | I7: Chưa làm
A8: OPS01 | B8: Triển khai schema/migration | C8: migration | D8: Một lần theo phiên bản | E8: database/schema.sql hoặc migrations | F8: Tạo mới HOẶC nâng cấp theo thứ tự README; dừng khi preflight lỗi; không có HTTP endpoint chạy SQL. | G8: Sao lưu + dry run trên DB tạm; không dùng --force. | I8: Chưa làm
A9: OPS02 | B9: Đối soát dữ liệu cư trú | C9: data-safety | D9: Khi có cảnh báo (đề xuất) | E9: Read-only report + xử lý có phê duyệt nghiệp vụ | F9: ACTIVE trên contract đóng vẫn tính tải; báo cáo lỗi thay vì đoán ngày rời/nhận đại diện. | G9: Không tự mở lại hợp đồng, không xóa lịch sử. | I9: Chưa làm
A10: OPS03 | B10: Hợp đồng hết ngày kết thúc | C10: end-lease | D10: Cần chốt chính sách | E10: Chưa có worker tự kết thúc | F10: Không tự đóng hợp đồng bỏ lại cư dân ACTIVE. EXPIRED có trong schema; cần quy trình bàn giao/kết thúc/đối soát rõ. | G10: Giữ nghĩa vụ hóa đơn và người ở, không suy đoán đã rời. | I10: Chưa làm

Sheet Kiem_thu
A1: ID | B1: Ca kiểm thử | C1: Luồng | D1: Kịch bản / kỳ vọng | E1: Kết quả | F1: Người kiểm thử | G1: Bằng chứng / lỗi
A2: QA01 | B2: Giới hạn tin chờ | C2: submit-post | D2: 4 submit đồng thời cùng room: tối đa 3 PENDING; sửa một tin PENDING không chiếm slot mới. | E2: Chưa chạy
A3: QA02 | B3: Tranh cùng khoảng giờ | C3: schedule-viewing | D3: 2 accept/propose khác nhau cùng khoảng giờ: chỉ một SCHEDULED; hai lịch liền kề được phép. | E3: Chưa chạy
A4: QA03 | B4: Tranh giữ phòng | C4: create-contract | D4: 2 lịch COMPLETED+AGREED cùng room tạo hợp đồng: chỉ một open contract; rollback mọi side effect bên thua. | E4: Chưa chạy
A5: QA04 | B5: Đóng lịch khi giữ phòng | C5: reserve-cleanup | D5: Hủy SCHEDULED tương lai và reject pending còn hạn trên tất cả bài cùng room; giữ lịch đang diễn ra/đã kết thúc. Hủy contract không hồi lịch. | E5: Chưa chạy
A6: QA05 | B6: Giới hạn người ở | C6: join-hold | D6: 2 approve tranh chỗ cuối: chỉ một giữ được. Hold quá 48h không tính capacity/không complete dù job chưa chạy. | E6: Chưa chạy
A7: QA06 | B7: Xác nhận revision cũ | C7: contract-revision | D7: Đại diện mở revision A, chủ gửi B trước confirm: request A phải 409, không xác nhận B ngoài ý muốn (D10). | E7: Chưa chạy
A8: QA07 | B8: Bàn giao đại diện | C8: handover | D8: Người cũ LEFT, người mới cùng hợp đồng ACTIVE, history đúng; request cũ hủy; payer/viewing/giá/ngày hợp đồng cũ giữ. | E8: Chưa chạy
A9: QA08 | B9: Rollback đổi phòng | C9: transfer | D9: Đích mất chỗ/quyền trước apply: không đóng nguồn. Thành công chuyển đủ ACTIVE+PLANNED, đích PLANNED chờ move-in. | E9: Chưa chạy
A10: QA09 | B10: Mất quyền nhà | C10: house-rights-expiry | D10: Hết hạn/thu hồi/đổi định danh/khóa landlord: public ẩn ngay, thuê mới/gia hạn/đích bị chặn, rời/kết thúc cũ vẫn hoạt động. | E10: Chưa chạy
A11: QA10 | B11: Hóa đơn bất biến | C11: pay-invoice | D11: Đổi giá dịch vụ/đại diện sau phát hành: invoice cũ không đổi. Kỳ trùng bị chặn; override=0 giữ 0; meter cuối<đầu bị chặn. | E11: Chưa chạy
A12: QA11 | B12: Phân quyền chéo tài khoản | C12: data-safety | D12: Thử ID nhà/contract/member/file/chat/invoice của người khác, bao gồm nested route không khớp parent; không lộ PII. | E12: Chưa chạy
A13: QA12 | B13: Idempotency và mất mạng | C13: data-safety | D13: Retry sau commit/trả response lỗi: cùng key/payload nhận kết quả cũ; khác payload 409; không lặp member/invoice/notification. | E13: Chưa chạy
... A17: QA16 | B17: Tài khoản nhiều vai trò/phiên | C17: account-access | D17: Role demo không cấp quyền; users.role không thay bảng role; JWT phiên revoked/LOCKED bị chặn trên mọi endpoint riêng tư. | E17: Chưa chạy
