Workbook

Sheet Huong_dan
A1: Mục | B1: Cách sử dụng
A2: Mục tiêu | B2: Phân công 3 người A/B/C theo module và mốc phụ thuộc, bao phủ 176 API. FE và AI để trống. Đây là kế hoạch, chưa có task backend nào được thực hiện.
A3: Tạo bản làm việc | B3: Save As một bản sao trước khi cập nhật. npm run plan:build sẽ thay bản master sinh từ mã nguồn; không ghi tiến độ thực vào master rồi chạy build.
A4: Cách cập nhật | B4: BE_Tasks là nguồn trạng thái chính trong workbook: P chọn trạng thái, Q:W đánh dấu 7 bước, AA:AC nhập ngày, AD:AF lưu PR/bằng chứng/lý do. Tăng chiều cao hàng khi cần đọc đủ nội dung dài.
A5: Hoàn thành | B5: Chọn Hoàn thành sau khi 7 bước Xong, các task phụ thuộc đã Hoàn thành và có bằng chứng tại AE. Cột Z cảnh báo khai báo chưa đủ. Công thức kiểm tra không thay thế review/test thật.
A6: Mốc và SP | B6: 8 mốc là thứ tự tích hợp, không phải các tuần cố định. SP là độ lớn tương đối, không phải ngày công; xem lại sau G1. Chưa gán deadline vì chưa có năng lực/lịch làm việc.
A7: Làm song song | B7: Sau G0 có thể code với fixture/mock cùng contract v1. Chờ tích hợp dùng khi module đã viết nhưng provider thật chưa sẵn sàng. Chỉ nghiệm thu đầy đủ khi phụ thuộc và test liên module đạt.
A8: Tên người thực tế | B8: Điền tên thành viên tương ứng A/B/C tại Tong_quan, cột Tên thực tế; giữ ký hiệu owner để liên kết task/API ổn định. Không đổi owner của một task lẻ rồi cùng sửa một module.
A9: API coverage | B9: API_176 tra trạng thái tự động từ BE_Tasks bằng INDEX/MATCH; mỗi endpoint có đúng một task/owner. Không nhập trạng thái độc lập tại API_176.
A10: Tiến độ tổng | B10: Tong_quan dùng COUNTIF và SUMPRODUCT(SP × tiến độ)/SUM(SP). Tỷ lệ task hoàn thành theo trạng thái là chỉ số khác; review cả cột cảnh báo. Excel tính lại công thức khi mở.
A11: File dùng chung | B11: A là người tích hợp bootstrap/dependency/CI/output SQL. B/C chỉ sửa source SQL đã phân, mỗi người có fixtures/tests riêng. Tất cả đường dẫn backend/** là đề xuất, không phải backend đã có.
A12: Đồng bộ trang | B12: Tiến độ trên trang chỉ lưu trong trình duyệt này; Excel không tự đồng bộ với trang hoặc máy khác. Team nên dùng một bản workbook chung hoặc công cụ task làm nguồn thật.
... A14: Nguồn | B14: docs/api-catalog.json + scripts/work-plan-blueprint.cjs → docs/work-plan.json, work-plan-data.js và file Excel này. Kiểm tra: npm run plan:check; npm run test:work-plan.

Sheet Tong_quan
A1: Chỉ số | B1: Giá trị | C1: Diễn giải / số task | D1: Tên thực tế / đã xong
A2: Ngày kế hoạch | B2: 2026-10-29
A3: Tổng task | B3: 52
A4: Tổng API | B4: 176
A5: Mốc tích hợp | B5: 8
A6: SP dự kiến | B6: 263 | C6: Độ lớn tương đối, không phải ngày công
A7: Hoàn thành | B7: =COUNTIF(BE_Tasks!$P$2:$P$53,"Hoàn thành") -> 0
A8: Đang làm | B8: =COUNTIF(BE_Tasks!$P$2:$P$53,"Đang làm") -> 0
A9: Chờ tích hợp | B9: =COUNTIF(BE_Tasks!$P$2:$P$53,"Chờ tích hợp") -> 0
A10: Chờ review | B10: =COUNTIF(BE_Tasks!$P$2:$P$53,"Chờ review") -> 0
A11: Bị chặn | B11: =COUNTIF(BE_Tasks!$P$2:$P$53,"Bị chặn") -> 0
A12: Chưa làm | B12: =COUNTIF(BE_Tasks!$P$2:$P$53,"Chưa làm") -> 52
A13: Tiến độ theo SP | B13: =SUMPRODUCT(BE_Tasks!G2:G53,BE_Tasks!X2:X53)/SUM(BE_Tasks!G2:G53) -> 0 | C13: 7 bước, có trọng số độ lớn
A14: Hoàn thành nhưng thiếu bằng chứng | B14: =COUNTIF(BE_Tasks!Z2:Z53,"Thiếu*") -> 0 | C14: Cần review lại trước nghiệm thu
A15: Người / vai trò | B15: SP | C15: Số task | D15: Tên thực tế
A16: A — Nền tảng, tài khoản, tương tác & hóa đơn | B16: 86 | C16: 17
A17: B — Nhà/phòng, tin đăng, lịch xem & ở ghép | B17: 91 | C17: 19
A18: C — Hợp đồng, cư trú & thay đổi thuê | B18: 86 | C18: 16
A19: Tiến độ từng người | B19: SP đã xử lý | C19: Tỷ lệ theo SP | D19: Task hoàn thành
A20: A | B20: =SUMPRODUCT((BE_Tasks!$D$2:$D$53="A")*BE_Tasks!$G$2:$G$53*BE_Tasks!$X$2:$X$53) -> 0 | C20: =SUMPRODUCT((BE_Tasks!$D$2:$D$53="A")*BE_Tasks!$G$2:$G$53*BE_Tasks!$X$2:$X$53)/SUMIF(BE_Tasks!$D$2:$D$53,"A",BE_Tasks!$G$2:$G$53) -> 0 | D20: =COUNTIFS(BE_Tasks!$D$2:$D$53,"A",BE_Tasks!$P$2:$P$53,"Hoàn thành") -> 0
A21: B | B21: =SUMPRODUCT((BE_Tasks!$D$2:$D$53="B")*BE_Tasks!$G$2:$G$53*BE_Tasks!$X$2:$X$53) -> 0 | C21: =SUMPRODUCT((BE_Tasks!$D$2:$D$53="B")*BE_Tasks!$G$2:$G$53*BE_Tasks!$X$2:$X$53)/SUMIF(BE_Tasks!$D$2:$D$53,"B",BE_Tasks!$G$2:$G$53) -> 0 | D21: =COUNTIFS(BE_Tasks!$D$2:$D$53,"B",BE_Tasks!$P$2:$P$53,"Hoàn thành") -> 0
A22: C | B22: =SUMPRODUCT((BE_Tasks!$D$2:$D$53="C")*BE_Tasks!$G$2:$G$53*BE_Tasks!$X$2:$X$53) -> 0 | C22: =SUMPRODUCT((BE_Tasks!$D$2:$D$53="C")*BE_Tasks!$G$2:$G$53*BE_Tasks!$X$2:$X$53)/SUMIF(BE_Tasks!$D$2:$D$53,"C",BE_Tasks!$G$2:$G$53) -> 0 | D22: =COUNTIFS(BE_Tasks!$D$2:$D$53,"C",BE_Tasks!$P$2:$P$53,"Hoàn thành") -> 0

Sheet BE_Tasks
A1: Task ID | B1: Mốc | C1: Thứ tự trong lane | D1: Owner | E1: Reviewer | F1: Công việc | G1: SP tương đối | H1: Số API | I1: API ID | J1: Phạm vi file được sửa | K1: Phụ thuộc trước tích hợp | L1: Cần phối hợp nghiệm thu | M1: Quyết định liên quan | N1: Đầu ra bàn giao | O1: Tiêu chí nghiệm thu | P1: Trạng thái | Q1: Thiết kế / contract | R1: Code / SQL | S1: Validate / phân quyền | T1: Test module / DB | U1: Test tích hợp | V1: Tài liệu / bàn giao | W1: Review / merge | X1: Tiến độ 7 bước | Y1: Điều kiện nghiệm thu | Z1: Cảnh báo hoàn thành | AA1: Bắt đầu | AB1: Hạn | AC1: Ngày xong | AD1: PR / commit | AE1: Bằng chứng test / quyết định | AF1: Ghi chú / lý do bị chặn | AG1: Link task
A2: BE-A01 | B2: P0 | C2: 1 | D2: A | E2: B | F2: Khởi tạo backend, nhánh và CI theo module | G2: 3 | H2: 0 | J2: backend/src/core/** backend/contracts/core.* backend/tests/fixtures/A/** backend/tests/contracts/A/** backend/tests/e2e/platform-*/** backend/bootstrap.* backend/package* backend/lockfile .github/workflows/backend-* database/schema.sql database/migrations/* scripts/build-database.cjs backend/tests/e2e/release/** | M2: D15 | N2: Tạo backend/src/modules/<domain>, tests/fixtures theo module và manifest tự đăng ký. Mỗi PR có branch be/<owner>/<task-id>-<slug>; main được bảo vệ bằng review và CI. CI dựng SQL từ nguồn vào thư mục tạm cho feature PR; A giữ output SQL tích hợp khớp nguồn khi merge. | O2: Lệnh chạy và test được ghi trong README backend; không dùng DB thật để test. B/C thêm module qua manifest riêng mà không sửa bootstrap, lockfile hay root routes. | P2: Chưa làm | Q2: Chưa | R2: Chưa | S2: Chưa | T2: Chưa | U2: Chưa | V2: Chưa | W2: Chưa | X2: =COUNTIF(Q2:W2,"Xong")/7 -> 0 | Y2: =IF(TRUE,"Đủ điều kiện","Chờ phụ thuộc") -> Đủ điều kiện | Z2: =IF(AND(P2="Hoàn thành",OR(X2<1,Y2<>"Đủ điều kiện",AND(AE2="",AD2=""))),"Thiếu bước / phụ thuộc / bằng chứng","") | AG2: Mở task
A3: BE-A02 | B3: P0 | C3: 2 | D3: A | E3: B | F3: Chốt contract v1 và cổng dùng chung | G3: 5 | H3: 0 | J3: backend/src/core/** backend/contracts/core.* backend/tests/fixtures/A/** backend/tests/contracts/A/** backend/tests/e2e/platform-*/** backend/bootstrap.* backend/package* backend/lockfile .github/workflows/backend-* | K3: BE-A01 | M3: D01, D09, D14, D15 | N3: Công bố backend/contracts/core.* với fixture request/response/error và mock adapter. Tách UnitOfWork của service với ProcedureRunner tự START/COMMIT; actor luôn lấy từ phiên. Định nghĩa eventId/recipient/eventKey, idempotency scope và whitelist audit target; B/C có contract test dùng ngay. | O3: B01/C01 cùng duyệt contract v1 trước khi merge code tích hợp. Contract test chạy với mock và adapter thật mà không sửa code consumer. | P3: Chưa làm | Q3: Chưa | R3: Chưa | S3: Chưa | T3: Chưa | U3: Chưa | V3: Chưa | W3: Chưa | X3: =COUNTIF(Q3:W3,"Xong")/7 -> 0 | Y3: =IF(AND(AND(INDEX(BE_Tasks!$P$2:$P$53,MATCH("BE-A01",BE_Tasks!$A$2:$A$53,0))="Hoàn thành",INDEX(BE_Tasks!$Z$2:$Z$53,MATCH("BE-A01",BE_Tasks!$A$2:$A$53,0))="")),"Đủ điều kiện","Chờ phụ thuộc") -> Chờ phụ thuộc | Z3: =IF(AND(P3="Hoàn thành",OR(X3<1,Y3<>"Đủ điều kiện",AND(AE3="",AD3=""))),"Thiếu bước / phụ thuộc / bằng chứng","") | AG3: Mở task
A4: BE-A03 | B4: P1 | C4: 3 | D4: A | E4: B | F4: Xác thực, phiên, profile và scope quyền | G4: 8 | H4: 9 | I4: API-001, API-002, API-003, API-004, API-005, API-018, API-019, API-020, API-021 | J4: backend/src/modules/identity/** backend/tests/identity/** backend/contracts/identity.* | K4: BE-A02 | M4: D01 | N4: Register users+tenants+profile nguyên tử; không nhận ADMIN/LANDLORD tùy ý từ client. Refresh xoay token, session revoked/LOCKED bị chặn; profile và flags theo whitelist. Cung cấp factory actor/phiên test cho B/C, tách policy role với quyền từng đối tượng. | O4: Thiếu token 401; sai scope/LOCKED không truy cập được tài nguyên module khác. Mọi contact/ID/money/date validate theo đặc tả, không log secret. | P4: Chưa làm | Q4: Chưa | R4: Chưa | S4: Chưa | T4: Chưa | U4: Chưa | V4: Chưa | W4: Chưa | X4: =COUNTIF(Q4:W4,"Xong")/7 -> 0 | Y4: =IF(AND(AND(INDEX(BE_Tasks!$P$2:$P$53,MATCH("BE-A02",BE_Tasks!$A$2:$A$53,0))="Hoàn thành",INDEX(BE_Tasks!$Z$2:$Z$53,MATCH("BE-A02",BE_Tasks!$A$2:$A$53,0))="")),"Đủ điều kiện","Chờ phụ thuộc") -> Chờ phụ thuộc | Z4: =IF(AND(P4="Hoàn thành",OR(X4<1,Y4<>"Đủ điều kiện",AND(AE4="",AD4=""))),"Thiếu bước / phụ thuộc / bằng chứng","") | AG4: Mở task
A5: BE-A04 | B5: P1 | C5: 4 | D5: A | E5: B | F5: Idempotency, event store và adapter audit nền | G5: 5 | H5: 0 | J5: backend/src/core/** backend/contracts/core.* backend/tests/fixtures/A/** backend/tests/contracts/A/** backend/tests/e2e/platform-*/** backend/bootstrap.* backend/package* backend/lockfile .github/workflows/backend-* database/schema.sql database/migrations/* scripts/build-database.cjs backend/tests/e2e/release/** | K5: BE-A02 | M5: D09, D14 | N5: Store key+actor+route+request hash+kết quả; xử lý đang chạy, TTL và retry sau commit. EventPort append cùng transaction cho service; cơ chế lấy notifications sau CALL có checkpoint/dedupe và giới hạn bảo đảm được ghi rõ. AuditPort nhận đúng một target hợp lệ; procedure đã ghi audit/notification thì adapter không ghi lặp. | O5: Cùng key/payload trả kết quả cũ; khác payload 409; retry không nhân đôi tác dụng phụ. Kiểm thử crash trước/sau commit; không tuyên bố exactly-once cho kênh vận chuyển. | P5: Chưa làm | Q5: Chưa | R5: Chưa | S5: Chưa | T5: Chưa | U5: Chưa | V5: Chưa | W5: Chưa | X5: =COUNTIF(Q5:W5,"Xong")/7 -> 0 | Y5: =IF(AND(AND(INDEX(BE_Tasks!$P$2:$P$53,MATCH("BE-A02",BE_Tasks!$A$2:$A$53,0))="Hoàn thành",INDEX(BE_Tasks!$Z$2:$Z$53,MATCH("BE-A02",BE_Tasks!$A$2:$A$53,0))="")),"Đủ điều kiện","Chờ phụ thuộc") -> Chờ phụ thuộc | Z5: =IF(AND(P5="Hoàn thành",OR(X5<1,Y5<>"Đủ điều kiện",AND(AE5="",AD5=""))),"Thiếu bước / phụ thuộc / bằng chứng","") | AG5: Mở task
A6: BE-A05 | B6: P1 | C6: 5 | D6: A | E6: B | F6: Kho tệp riêng tư và quyền mở theo ngữ cảnh | G6: 8 | H6: 5 | I6: API-170, API-171, API-172, API-173, API-174 | J6: backend/src/modules/files/** backend/tests/files/** backend/contracts/files.* | K6: BE-A03, BE-A04 | M6: D05 | N6: Adapter kho tệp cấu hình qua môi trường; MIME magic, byte length, SHA-256 và ownership được server kiểm tra. FilePort hỗ trợ context resolver do B/C đăng ký riêng; không import service B/C vào files tạo vòng phụ thuộc. Proof đã tham chiếu bất biến, URL ngắn hạn và retention có chính sách D05. | O6: Proof nhà đúng 1–8 tệp, tối đa 5 MB/tệp; MIME giả/owner khác bị chặn. Không đọc được file bằng đoán ID; tệp đang được giữ không bị xóa vật lý. | P6: Chưa làm | Q6: Chưa | R6: Chưa | S6: Chưa | T6: Chưa | U6: Chưa | V6: Chưa | W6: Chưa | X6: =COUNTIF(Q6:W6,"Xong")/7 -> 0 | Y6: =IF(AND(AND(INDEX(BE_Tasks!$P$2:$P$53,MATCH("BE-A03",BE_Tasks!$A$2:$A$53,0))="Hoàn thành",INDEX(BE_Tasks!$Z$2:$Z$53,MATCH("BE-A03",BE_Tasks!$A$2:$A$53,0))=""),AND(INDEX(BE_Tasks!$P$2:$P$53,MATCH("BE-A04",BE_Tasks!$A$2:$A$53,0))="Hoàn thành",INDEX(BE_Tasks!$Z$2:$Z$53,MATCH("BE-A04",BE_Tasks!$A$2:$A$53,0))="")),"Đủ điều kiện","Chờ phụ thuộc") -> Chờ phụ thuộc | Z6: =IF(AND(P6="Hoàn thành",OR(X6<1,Y6<>"Đủ điều kiện",AND(AE6="",AD6=""))),"Thiếu bước / phụ thuộc / bằng chứng","") | AG6: Mở task
A7: BE-A06 | B7: P2 | C7: 6 | D7: A | E7: B | F7: Xác minh danh tính và cấp vai trò chủ trọ | G7: 5 | H7: 12 | I7: API-006, API-007, API-008, API-009, API-010, API-011, API-012, API-013, API-014, API-015, API-016, API-017 | J7: backend/src/modules/identity/** backend/tests/identity/** backend/contracts/identity.* | K7: BE-A05 | M7: D05 | N7: Một PENDING/người/loại; duyệt/từ chối có actor/time/reason. APPROVE landlord tạo dòng landlords trong cùng transaction; không tự duyệt nhà. Ghi audit và thông báo qua adapter đã chốt, giữ hồ sơ lịch sử. | O7: Hai lần nộp đồng thời không có hai PENDING; file của người khác bị chặn. Chủ trọ mới được cấp vai trò chỉ công khai nhà sau B05 xác minh riêng. | P7: Chưa làm | Q7: Chưa | R7: Chưa | S7: Chưa | T7: Chưa | U7: Chưa | V7: Chưa | W7: Chưa | X7: =COUNTIF(Q7:W7,"Xong")/7 -> 0 | Y7: =IF(AND(AND(INDEX(BE_Tasks!$P$2:$P$53,MATCH("BE-A05",BE_Tasks!$A$2:$A$53,0))="Hoàn thành",INDEX(BE_Tasks!$Z$2:$Z$53,MATCH("BE-A05",BE_Tasks!$A$2:$A$53,0))="")),"Đủ điều kiện","Chờ phụ thuộc") -> Chờ phụ thuộc | Z7: =IF(AND(P7="Hoàn thành",OR(X7<1,Y7<>"Đủ điều kiện",AND(AE7="",AD7=""))),"Thiếu bước / phụ thuộc / bằng chứng","") | AG7: Mở task
A8: BE-A07 | B8: P2 | C8: 7 | D8: A | E8: B | F8: OTP, reset mật khẩu và TokenPort | G8: 5 | H8: 5 | I8: API-022, API-023, API-024, API-025, API-026 | J8: backend/src/modules/identity/** backend/tests/identity/** backend/contracts/identity.* | K8: BE-A03, BE-A04 | M8: D01, D06 | N8: Hash/HMAC mã, hạn dùng, attempt, consumed/revoked; reset không lộ tài khoản tồn tại. Reset grant chỉ đổi mật khẩu đúng user và thu hồi phiên; phone uniqueness kiểm tra lại dưới khóa. TokenPort issue/consume hỗ trợ OCCUPANT_LINK và targetRoomTenantId trong transaction được C truyền vào. | O8: OTP sai/hết hạn/dùng lại đều thất bại đúng mã; không log/response OTP thực. C08 tiêu thụ token và gắn member trong cùng transaction, không gọi HTTP nội bộ. | P8: Chưa làm | Q8: Chưa | R8: Chưa | S8: Chưa | T8: Chưa | U8: Chưa | V8: Chưa | W8: Chưa | X8: =COUNTIF(Q8:W8,"Xong")/7 -> 0 | Y8: =IF(AND(AND(INDEX(BE_Tasks!$P$2:$P$53,MATCH("BE-A03",BE_Tasks!$A$2:$A$53,0))="Hoàn thành",INDEX(BE_Tasks!$Z$2:$Z$53,MATCH("BE-A03",BE_Tasks!$A$2:$A$53,0))=""),AND(INDEX(BE_Tasks!$P$2:$P$53,MATCH("BE-A04",BE_Tasks!$A$2:$A$53,0))="Hoàn thành",INDEX(BE_Tasks!$Z$2:$Z$53,MATCH("BE-A04",BE_Tasks!$A$2:$A$53,0))="")),"Đủ điều kiện","Chờ phụ thuộc") -> Chờ phụ thuộc | Z8: =IF(AND(P8="Hoàn thành",OR(X8<1,Y8<>"Đủ điều kiện",AND(AE8="",AD8=""))),"Thiếu bước / phụ thuộc / bằng chứng","") | AG8: Mở task
A9: BE-A08 | B9: P2 | C9: 8 | D9: A | E9: B | F9: Chat hỏi phòng và cổng hội thoại cho lịch xem | G9: 8 | H9: 7 | I9: API-076, API-077, API-078, API-079, API-080, API-081, API-082 | J9: backend/src/modules/messaging/** backend/src/modules/notifications/** backend/tests/messaging/** backend/contracts/messaging.* | K9: BE-A03, BE-A04, BE-B04 | M9: D03, D08 | N9: Get-or-create inquiry có unique/khóa theo D08; một context ghi/post/room, gộp peer chỉ khi đọc. Gửi TEXT/IMAGE chống trùng; cập nhật participant/read-state/last_message và sự kiện nguyên tử. Công bố ensureRoommateConversation(tx) cho B13; ConnectionPort kiểm tra accepted từ DB/fixture dù endpoint kết nối chưa hoàn thiện. | O9: Có tin người thuê về đúng phòng cho B08/B09; ROOMMATE không dùng hẹn chủ trọ. Chỉ participant được đọc/gửi; sender+client key không tạo trùng. | P9: Chưa làm | Q9: Chưa | R9: Chưa | S9: Chưa | T9: Chưa | U9: Chưa | V9: Chưa | W9: Chưa | X9: =COUNTIF(Q9:W9,"Xong")/7 -> 0 | Y9: =IF(AND(AND(INDEX(BE_Tasks!$P$2:$P$53,MATCH("BE-A03",BE_Tasks!$A$2:$A$53,0))="Hoàn thành",INDEX(BE_Tasks!$Z$2:$Z$53,MATCH("BE-A03",BE_Tasks!$A$2:$A$53,0))=""),AND(INDEX(BE_Tasks!$P$2:$P$53,MATCH("BE-A04",BE_Tasks!$A$2:$A$53,0))="Hoàn thành",INDEX(BE_Tasks!$Z$2:$Z$53,MATCH("BE-A04",BE_Tasks!$A$2:$A$53,0))=""),AND(INDEX(BE_Tasks!$P$2:$P$53,MATCH("BE-B04",BE_Tasks!$A$2:$A$53,0))="Hoàn thành",INDEX(BE_Tasks!$Z$2:$Z$53,MATCH("BE-B04",BE_Tasks!$A$2:$A$53,0))="")),"Đủ điều kiện","Chờ phụ thuộc") -> Chờ phụ thuộc | Z9: =IF(AND(P9="Hoàn thành",OR(X9<1,Y9<>"Đủ điều kiện",AND(AE9="",AD9=""))),"Thiếu bước / phụ thuộc / bằng chứng","") | AG9: Mở task
A10: BE-A09 | B10: P3 | C10: 9 | D10: A | E10: B | F10: Feed thông báo, bộ đếm và đánh dấu đọc | G10: 3 | H10: 4 | I10: API-086, API-087, API-088, API-089 | J10: backend/src/modules/messaging/** backend/src/modules/notifications/** backend/tests/messaging/** backend/contracts/messaging.* | K10: BE-A04, BE-A08 | N10: Feed scoped user, counts, read một/tất cả đến mốc server. Chống event_key trùng, mở tài nguyên vẫn kiểm tra quyền lại. Chuẩn hóa thông báo do procedure và service phát, giữ popup là trạng thái UI. | O10: Đọc thông báo của user khác bị chặn; read-all không đọc nhầm sự kiện đến sau mốc. Tắt realtime không làm mất thông báo đã commit. | P10: Chưa làm | Q10: Chưa | R10: Chưa | S10: Chưa | T10: Chưa | U10: Chưa | V10: Chưa | W10: Chưa | X10: =COUNTIF(Q10:W10,"Xong")/7 -> 0 | Y10: =IF(AND(AND(INDEX(BE_Tasks!$P$2:$P$53,MATCH("BE-A04",BE_Tasks!$A$2:$A$53,0))="Hoàn thành",INDEX(BE_Tasks!$Z$2:$Z$53,MATCH("BE-A04",BE_Tasks!$A$2:$A$53,0))=""),AND(INDEX(BE_Tasks!$P$2:$P$53,MATCH("BE-A08",BE_Tasks!$A$2:$A$53,0))="Hoàn thành",INDEX(BE_Tasks!$Z$2:$Z$53,MATCH("BE-A08",BE_Tasks!$A$2:$A$53,0))="")),"Đủ điều kiện","Chờ phụ thuộc") -> Chờ phụ thuộc | Z10: =IF(AND(P10="Hoàn thành",OR(X10<1,Y10<>"Đủ điều kiện",AND(AE10="",AD10=""))),"Thiếu bước / phụ thuộc / bằng chứng","") | AG10: Mở task
A11: BE-A10 | B11: P4 | C11: 10 | D11: A | E11: B | F11: Hóa đơn nháp và snapshot giá/người trả | G11: 5 | H11: 4 | I11: API-145, API-146, API-147, API-148 | J11: backend/src/modules/billing/** backend/tests/billing/** backend/contracts/billing.* | K11: BE-A04, BE-B03, BE-C02 | L11: BE-C07 | M11: D12 | N11: Unique contract+kỳ chưa hủy; server tính quantity, meter, tiền thuê và giảm trừ bằng decimal. Snapshot revision, representative/payer và số ACTIVE trong cùng transaction đọc hợp đồng. Chỉ sửa DRAFT; hợp đồng ACTIVE thật cho E2E được bàn giao khi C07 hoàn thành. | O11: Override=0 giữ 0; người PLANNED không tính dịch vụ theo người; chỉ số cuối<đầu bị chặn. Đổi đại diện/giá sau lập không đổi snapshot hóa đơn cũ. | P11: Chưa làm | Q11: Chưa | R11: Chưa | S11: Chưa | T11: Chưa | U11: Chưa | V11: Chưa | W11: Chưa | X11: =COUNTIF(Q11:W11,"Xong")/7 -> 0 | Y11: =IF(AND(AND(INDEX(BE_Tasks!$P$2:$P$53,MATCH("BE-A04",BE_Tasks!$A$2:$A$53,0))="Hoàn thành",INDEX(BE_Tasks!$Z$2:$Z$53,MATCH("BE-A04",BE_Tasks!$A$2:$A$53,0))=""),AND(INDEX(BE_Tasks!$P$2:$P$53,MATCH("BE-B03",BE_Tasks!$A$2:$A$53,0))="Hoàn thành",INDEX(BE_Tasks!$Z$2:$Z$53,MATCH("BE-B03",BE_Tasks!$A$2:$A$53,0))=""),AND(INDEX(BE_Tasks!$P$2:$P$53,MATCH("BE-C02",BE_Tasks!$A$2:$A$53,0))="Hoàn thành",INDEX(BE_Tasks!$Z$2:$Z$53,MATCH("BE-C02",BE_Tasks!$A$2:$A$53,0))=""),AND(INDEX(BE_Tasks!$P$2:$P$53,MATCH("BE-C07",BE_Tasks!$A$2:$A$53,0))="Hoàn thành",INDEX(BE_Tasks!$Z$2:$Z$53,MATCH("BE-C07",BE_Tasks!$A$2:$A$53,0))="")),"Đủ điều kiện","Chờ phụ thuộc") -> Chờ phụ thuộc | Z11: =IF(AND(P11="Hoàn thành",OR(X11<1,Y11<>"Đủ điều kiện",AND(AE11="",AD11=""))),"Thiếu bước / phụ thuộc / bằng chứng","") | AG11: Mở task
A12: BE-A11 | B12: P4 | C12: 11 | D12: A | E12: B | F12: Thẻ lịch, chat bạn ghép và chia sẻ đúng tin | G12: 5 | H12: 3 | I12: API-083, API-084, API-085 | J12: backend/src/modules/messaging/** backend/src/modules/notifications/** backend/tests/messaging/** backend/contracts/messaging.* | K12: BE-A08, BE-B04, BE-C02 | L12: BE-B13, BE-B09 | M12: D03 | N12: Timeline lấy viewing/proposal theo conversation có quyền; share giữ đúng postId. ROOMMATE chỉ mở/gửi khi accepted còn hiệu lực; inactive post trả unavailable không lộ ảnh/tiêu đề. B13 dùng ensureRoommateConversation đã có ở A08; hai phần không phụ thuộc nhau theo vòng HTTP. | O12: Accept kết nối xong mở cùng conversation; share không tạo join/hold/lịch. Bài ẩn không tự đổi sang bài khác cùng phòng; chat inquiry và roommate không lẫn thẻ lịch. | P12: Chưa làm | Q12: Chưa | R12: Chưa | S12: Chưa | T12: Chưa | U12: Chưa | V12: Chưa | W12: Chưa | X12: =COUNTIF(Q12:W12,"Xong")/7 -> 0 | Y12: =IF(AND(AND(INDEX(BE_Tasks!$P$2:$P$53,MATCH("BE-A08",BE_Tasks!$A$2:$A$53,0))="Hoàn thành",INDEX(BE_Tasks!$Z$2:$Z$53,MATCH("BE-A08",BE_Tasks!$A$2:$A$53,0))=""),AND(INDEX(BE_Tasks!$P$2:$P$53,MATCH("BE-B04",BE_Tasks!$A$2:$A$53,0))="Hoàn thành",INDEX(BE_Tasks!$Z$2:$Z$53,MATCH("BE-B04",BE_Tasks!$A$2:$A$53,0))=""),AND(INDEX(BE_Tasks!$P$2:$P$53,MATCH("BE-C02",BE_Tasks!$A$2:$A$53,0))="Hoàn thành",INDEX(BE_Tasks!$Z$2:$Z$53,MATCH("BE-C02",BE_Tasks!$A$2:$A$53,0))=""),AND(INDEX(BE_Tasks!$P$2:$P$53,MATCH("BE-B13",BE_Tasks!$A$2:$A$53,0))="Hoàn thành",INDEX(BE_Tasks!$Z$2:$Z$53,MATCH("BE-B13",BE_Tasks!$A$2:$A$53,0))=""),AND(INDEX(BE_Tasks!$P$2:$P$53,MATCH("BE-B09",BE_Tasks!$A$2:$A$53,0))="Hoàn thành",INDEX(BE_Tasks!$Z$2:$Z$53,MATCH("BE-B09",BE_Tasks!$A$2:$A$53,0))="")),"Đủ điều kiện","Chờ phụ thuộc") -> Chờ phụ thuộc | Z12: =IF(AND(P12="Hoàn thành",OR(X12<1,Y12<>"Đủ điều kiện",AND(AE12="",AD12=""))),"Thiếu bước / phụ thuộc / bằng chứng","") | AG12: Mở task
A13: BE-A12 | B13: P4 | C13: 12 | D13: A | E13: B | F13: Quản trị tài khoản và tra cứu audit | G13: 5 | H13: 6 | I13: API-161, API-162, API-163, API-164, API-168, API-169 | J13: backend/src/modules/account-admin/** backend/src/modules/audit/** backend/src/modules/admin-dashboard/** backend/tests/account-admin/** | K13: BE-A03, BE-A04 | N13: Lock/unlock có reason, audit và revoke session; không xóa cư trú/nghĩa vụ. Audit chỉ đọc, lọc đối tượng và che secret/PII khỏi snapshot. Không sửa source SQL nhà của B để tính quyền; view hiệu lực đã xét trạng thái user. | O13: Tài khoản bị khóa mất quyền trên mọi module qua cùng middleware. Khóa landlord làm public view mất quyền, nhưng hợp đồng/người ở cũ được giữ. | P13: Chưa làm | Q13: Chưa | R13: Chưa | S13: Chưa | T13: Chưa | U13: Chưa | V13: Chưa | W13: Chưa | X13: =COUNTIF(Q13:W13,"Xong")/7 -> 0 | Y13: =IF(AND(AND(INDEX(BE_Tasks!$P$2:$P$53,MATCH("BE-A03",BE_Tasks!$A$2:$A$53,0))="Hoàn thành",INDEX(BE_Tasks!$Z$2:$Z$53,MATCH("BE-A03",BE_Tasks!$A$2:$A$53,0))=""),AND(INDEX(BE_Tasks!$P$2:$P$53,MATCH("BE-A04",BE_Tasks!$A$2:$A$53,0))="Hoàn thành",INDEX(BE_Tasks!$Z$2:$Z$53,MATCH("BE-A04",BE_Tasks!$A$2:$A$53,0))="")),"Đủ điều kiện","Chờ phụ thuộc") -> Chờ phụ thuộc | Z13: =IF(AND(P13="Hoàn thành",OR(X13<1,Y13<>"Đủ điều kiện",AND(AE13="",AD13=""))),"Thiếu bước / phụ thuộc / bằng chứng","") | AG13: Mở task
A14: BE-A13 | B14: P5 | C14: 13 | D14: A | E14: B | F14: Phát hành, thu đủ, hủy và thay hóa đơn | G14: 5 | H14: 4 | I14: API-149, API-150, API-151, API-152 | J14: backend/src/modules/billing/** backend/tests/billing/** backend/contracts/billing.* | K14: BE-A10 | M14: D12 | N14: Issue DRAFT có dòng tiền → UNPAID; PAID có người ghi nhận/time; hủy chưa thu có lý do. Replacement giữ cùng contract/kỳ và liên kết bản đã hủy; không sửa lines phát hành. JOB04 chuyển UNPAID quá due_date VN sang OVERDUE, chạy lặp an toàn; giữ quyền người trả cũ sau bàn giao, không giả có issued_at riêng. | O14: Hai lần thu cùng khóa không tạo thêm thu tiền; PAID/CANCELLED không sửa. Kỳ mới lấy đại diện hiện tại, kỳ cũ vẫn đúng payer. | P14: Chưa làm | Q14: Chưa | R14: Chưa | S14: Chưa | T14: Chưa | U14: Chưa | V14: Chưa | W14: Chưa | X14: =COUNTIF(Q14:W14,"Xong")/7 -> 0 | Y14: =IF(AND(AND(INDEX(BE_Tasks!$P$2:$P$53,MATCH("BE-A10",BE_Tasks!$A$2:$A$53,0))="Hoàn thành",INDEX(BE_Tasks!$Z$2:$Z$53,MATCH("BE-A10",BE_Tasks!$A$2:$A$53,0))="")),"Đủ điều kiện","Chờ phụ thuộc") -> Chờ phụ thuộc | Z14: =IF(AND(P14="Hoàn thành",OR(X14<1,Y14<>"Đủ điều kiện",AND(AE14="",AD14=""))),"Thiếu bước / phụ thuộc / bằng chứng","") | AG14: Mở task
A15: BE-A14 | B15: P5 | C15: 14 | D15: A | E15: B | F15: SSE có xác thực và nối lại sự kiện | G15: 5 | H15: 1 | I15: API-090 | J15: backend/src/modules/messaging/** backend/src/modules/notifications/** backend/tests/messaging/** backend/contracts/messaging.* | K15: BE-A04, BE-A09 | M15: D09 | N15: Auth phiên, Last-Event-ID, replay trong cửa sổ lưu, recipient scope và dedupe eventId. Phát sau commit; reconnect không coi popup đã đóng là đã đọc. Tải trọng tối thiểu rồi client fetch resource; kiểm tra session revoked khi stream còn mở. | O15: Mất kết nối/retry không mất nguồn dữ liệu gốc và không lộ sự kiện người khác. Crash/delivery lặp vẫn cho client dedupe và đọc lại feed. | P15: Chưa làm | Q15: Chưa | R15: Chưa | S15: Chưa | T15: Chưa | U15: Chưa | V15: Chưa | W15: Chưa | X15: =COUNTIF(Q15:W15,"Xong")/7 -> 0 | Y15: =IF(AND(AND(INDEX(BE_Tasks!$P$2:$P$53,MATCH("BE-A04",BE_Tasks!$A$2:$A$53,0))="Hoàn thành",INDEX(BE_Tasks!$Z$2:$Z$53,MATCH("BE-A04",BE_Tasks!$A$2:$A$53,0))=""),AND(INDEX(BE_Tasks!$P$2:$P$53,MATCH("BE-A09",BE_Tasks!$A$2:$A$53,0))="Hoàn thành",INDEX(BE_Tasks!$Z$2:$Z$53,MATCH("BE-A09",BE_Tasks!$A$2:$A$53,0))="")),"Đủ điều kiện","Chờ phụ thuộc") -> Chờ phụ thuộc | Z15: =IF(AND(P15="Hoàn thành",OR(X15<1,Y15<>"Đủ điều kiện",AND(AE15="",AD15=""))),"Thiếu bước / phụ thuộc / bằng chứng","") | AG15: Mở task
A16: BE-A15 | B16: P6 | C16: 15 | D16: A | E16: B | F16: Retention, audit mở rộng và dashboard quản trị | G16: 3 | H16: 1 | I16: API-176 | J16: backend/src/core/** backend/contracts/core.* backend/tests/fixtures/A/** backend/tests/contracts/A/** backend/tests/e2e/platform-*/** backend/bootstrap.* backend/package* backend/lockfile .github/workflows/backend-* backend/src/modules/account-admin/** backend/src/modules/audit/** backend/src/modules/admin-dashboard/** backend/tests/account-admin/** database/schema.sql database/migrations/* scripts/build-database.cjs backend/tests/e2e/release/** | K16: BE-A05, BE-A12, BE-A14 | L16: BE-B14 | M16: D04, D05, D14 | N16: D14 có migration/adapters và contract target mới trước B16; không gán nhầm review thành post. JOB05 dọn đúng scope/hạn lưu, tệp bị giữ làm chứng cứ được bảo toàn. Admin dashboard đếm riêng account identity/house proof/posts/reports; flags email/push chỉ bật khi provider được chốt. | O16: Job lặp an toàn, không xóa bằng chứng đang tham chiếu. Dashboard không công khai PII; số liệu có asOf và nguồn từng module. | P16: Chưa làm | Q16: Chưa | R16: Chưa | S16: Chưa | T16: Chưa | U16: Chưa | V16: Chưa | W16: Chưa | X16: =COUNTIF(Q16:W16,"Xong")/7 -> 0 | Y16: =IF(AND(AND(INDEX(BE_Tasks!$P$2:$P$53,MATCH("BE-A05",BE_Tasks!$A$2:$A$53,0))="Hoàn thành",INDEX(BE_Tasks!$Z$2:$Z$53,MATCH("BE-A05",BE_Tasks!$A$2:$A$53,0))=""),AND(INDEX(BE_Tasks!$P$2:$P$53,MATCH("BE-A12",BE_Tasks!$A$2:$A$53,0))="Hoàn thành",INDEX(BE_Tasks!$Z$2:$Z$53,MATCH("BE-A12",BE_Tasks!$A$2:$A$53,0))=""),AND(INDEX(BE_Tasks!$P$2:$P$53,MATCH("BE-A14",BE_Tasks!$A$2:$A$53,0))="Hoàn thành",INDEX(BE_Tasks!$Z$2:$Z$53,MATCH("BE-A14",BE_Tasks!$A$2:$A$53,0))=""),AND(INDEX(BE_Tasks!$P$2:$P$53,MATCH("BE-B14",BE_Tasks!$A$2:$A$53,0))="Hoàn thành",INDEX(BE_Tasks!$Z$2:$Z$53,MATCH("BE-B14",BE_Tasks!$A$2:$A$53,0))="")),"Đủ điều kiện","Chờ phụ thuộc") -> Chờ phụ thuộc | Z16: =IF(AND(P16="Hoàn thành",OR(X16<1,Y16<>"Đủ điều kiện",AND(AE16="",AD16=""))),"Thiếu bước / phụ thuộc / bằng chứng","") | AG16: Mở task
A17: BE-A16 | B17: P7 | C17: 16 | D17: A | E17: B | F17: Kiểm thử bảo mật, hóa đơn và lỗi hạ tầng | G17: 5 | H17: 0 | J17: backend/src/core/** backend/contracts/core.* backend/tests/fixtures/A/** backend/tests/contracts/A/** backend/tests/e2e/platform-*/** backend/bootstrap.* backend/package* backend/lockfile .github/workflows/backend-* backend/src/modules/billing/** backend/tests/billing/** backend/contracts/billing.* backend/src/modules/messaging/** backend/src/modules/notifications/** backend/tests/messaging/** backend/contracts/messaging.* | K17: BE-A15 | N17: Test scope chéo ID, nhiều vai trò, revoke/LOCKED, OTP và tài liệu riêng. Test idempotency sau commit/timeout, outbox/SSE reconnect và invoice snapshot. Ghi bằng chứng chạy CI, migration mới và cách rollback/retry về mặt vận hành. | O17: QA10/11/12/15/16 đạt trên DB tạm và storage test. Không dùng localStorage wireframe làm bằng chứng backend đã chạy. | P17: Chưa làm | Q17: Chưa | R17: Chưa | S17: Chưa | T17: Chưa | U17: Chưa | V17: Chưa | W17: Chưa | X17: =COUNTIF(Q17:W17,"Xong")/7 -> 0 | Y17: =IF(AND(AND(INDEX(BE_Tasks!$P$2:$P$53,MATCH("BE-A15",BE_Tasks!$A$2:$A$53,0))="Hoàn thành",INDEX(BE_Tasks!$Z$2:$Z$53,MATCH("BE-A15",BE_Tasks!$A$2:$A$53,0))="")),"Đủ điều kiện","Chờ phụ thuộc") -> Chờ phụ thuộc | Z17: =IF(AND(P17="Hoàn thành",OR(X17<1,Y17<>"Đủ điều kiện",AND(AE17="",AD17=""))),"Thiếu bước / phụ thuộc / bằng chứng","") | AG17: Mở task
A18: BE-A17 | B18: P7 | C18: 17 | D18: A | E18: B | F18: Tích hợp bản bàn giao Backend | G18: 3 | H18: 0 | J18: database/schema.sql database/migrations/* scripts/build-database.cjs backend/tests/e2e/release/** | K18: BE-A16, BE-B19, BE-C16 | N18: Tái sinh schema từ toàn bộ source, chốt thứ tự migration; test tạo mới/nâng cấp trên DB tạm. Đối chiếu 176 API có đúng một task/module owner, gom collection/API docs và hướng dẫn chạy. Xác nhận toàn bộ gate; ghi các quyết định ngoài phạm vi còn hoãn, không gọi backend hoàn tất nếu endpoint tương ứng chưa đạt. | O18: Feature CI, DB check, contract tests và E2E ba lane đều xanh. Không ai sửa tay schema sinh ra; không deploy hoặc áp dụng migration DB thật trong task tài liệu này. | P18: Chưa làm | Q18: Chưa | R18: Chưa | S18: Chưa | T18: Chưa | U18: Chưa | V18: Chưa | W18: Chưa | X18: =COUNTIF(Q18:W18,"Xong")/7 -> 0 | Y18: =IF(AND(AND(INDEX(BE_Tasks!$P$2:$P$53,MATCH("BE-A16",BE_Tasks!$A$2:$A$53,0))="Hoàn thành",INDEX(BE_Tasks!$Z$2:$Z$53,MATCH("BE-A16",BE_Tasks!$A$2:$A$53,0))=""),AND(INDEX(BE_Tasks!$P$2:$P$53,MATCH("BE-B19",BE_Tasks!$A$2:$A$53,0))="Hoàn thành",INDEX(BE_Tasks!$Z$2:$Z$53,MATCH("BE-B19",BE_Tasks!$A$2:$A$53,0))=""),AND(INDEX(BE_Tasks!$P$2:$P$53,MATCH("BE-C16",BE_Tasks!$A$2:$A$53,0))="Hoàn thành",INDEX(BE_Tasks!$Z$2:$Z$53,MATCH("BE-C16",BE_Tasks!$A$2:$A$53,0))="")),"Đủ điều kiện","Chờ phụ thuộc") -> Chờ phụ thuộc | Z18: =IF(AND(P18="Hoàn thành",OR(X18<1,Y18<>"Đủ điều kiện",AND(AE18="",AD18=""))),"Thiếu bước / phụ thuộc / bằng chứng","") | AG18: Mở task
A19: BE-B01 | B19: P0 | C19: 1 | D19: B | E19: C | F19: Chốt module nhà/tin/lịch và dữ liệu bàn giao | G19: 3 | H19: 0 | J19: backend/src/modules/properties/** backend/src/modules/house-rights/** backend/tests/properties/** backend/tests/fixtures/B/** backend/tests/contracts/B/** backend/tests/e2e/property-*/** backend/contracts/properties.* backend/src/modules/posts/** backend/tests/posts/** backend/contracts/posts.* backend/src/modules/services/** backend/tests/services/** backend/contracts/services.* backend/src/modules/viewings/** backend/tests/viewings/** backend/tests/e2e/viewing-contract/** backend/contracts/viewings.* backend/src/modules/roommates/** backend/tests/roommates/** backend/contracts/roommates.* | M19: D02, D07, D08, D13 | N19: Phân biệt postId/roomId, quyền nhà, capacity load, quote service và trạng thái kết nối. Tạo fixture trong backend/tests/fixtures/B/**; không sửa seed chung của A/C. Chốt cổng IF-ROOM/IF-SERVICE/IF-CONNECTION với A02/C01; các loại payload không đổi âm thầm. | O19: Consumer có thể chạy contract test với fixture chưa cần endpoint thật. D02/D07/D08/D13 được ghi rõ người đề xuất/người chốt và route bị ảnh hưởng. | P19: Chưa làm | Q19: Chưa | R19: Chưa | S19: Chưa | T19: Chưa | U19: Chưa | V19: Chưa | W19: Chưa | X19: =COUNTIF(Q19:W19,"Xong")/7 -> 0 | Y19: =IF(TRUE,"Đủ điều kiện","Chờ phụ thuộc") -> Đủ điều kiện | Z19: =IF(AND(P19="Hoàn thành",OR(X19<1,Y19<>"Đủ điều kiện",AND(AE19="",AD19=""))),"Thiếu bước / phụ thuộc / bằng chứng","") | AG19: Mở task
A20: BE-B02 | B20: P1 | C20: 2 | D20: B | E20: C | F20: Nhà/phòng CRUD và sức chứa | G20: 8 | H20: 8 | I20: API-029, API-030, API-031, API-032, API-042, API-043, API-044, API-045 | J20: backend/src/modules/properties/** backend/src/modules/house-rights/** backend/tests/properties/** backend/tests/fixtures/B/** backend/tests/contracts/B/** backend/tests/e2e/property-*/** backend/contracts/properties.* | K20: BE-A02, BE-B01 | L20: BE-A03 | N20: Nhà create idempotency, update row_version/verification_version đúng procedure. Mã phòng duy nhất/nhà; giá và diện tích hợp lệ, status suy từ người/hợp đồng. Capacity gọi sp_set_room_capacity; procedure nằm workflows.sql của C, cần đổi thì gửi C patch request. | O20: Không đặt phòng có ACTIVE thành AVAILABLE; không giảm dưới ACTIVE+PLANNED mở+hold còn hạn. Dùng auth middleware A khi tích hợp, không hardcode user Quân/demo. | P20: Chưa làm | Q20: Chưa | R20: Chưa | S20: Chưa | T20: Chưa | U20: Chưa | V20: Chưa | W20: Chưa | X20: =COUNTIF(Q20:W20,"Xong")/7 -> 0 | Y20: =IF(AND(AND(INDEX(BE_Tasks!$P$2:$P$53,MATCH("BE-A02",BE_Tasks!$A$2:$A$53,0))="Hoàn thành",INDEX(BE_Tasks!$Z$2:$Z$53,MATCH("BE-A02",BE_Tasks!$A$2:$A$53,0))=""),AND(INDEX(BE_Tasks!$P$2:$P$53,MATCH("BE-B01",BE_Tasks!$A$2:$A$53,0))="Hoàn thành",INDEX(BE_Tasks!$Z$2:$Z$53,MATCH("BE-B01",BE_Tasks!$A$2:$A$53,0))=""),AND(INDEX(BE_Tasks!$P$2:$P$53,MATCH("BE-A03",BE_Tasks!$A$2:$A$53,0))="Hoàn thành",INDEX(BE_Tasks!$Z$2:$Z$53,MATCH("BE-A03",BE_Tasks!$A$2:$A$53,0))="")),"Đủ điều kiện","Chờ phụ thuộc") -> Chờ phụ thuộc | Z20: =IF(AND(P20="Hoàn thành",OR(X20<1,Y20<>"Đủ điều kiện",AND(AE20="",AD20=""))),"Thiếu bước / phụ thuộc / bằng chứng","") | AG20: Mở task
A21: BE-B03 | B21: P1 | C21: 3 | D21: B | E21: C | F21: Dịch vụ nhà/phòng và giá hiệu lực | G21: 5 | H21: 9 | I21: API-049, API-137, API-138, API-139, API-140, API-141, API-142, API-143, API-144 | J21: backend/src/modules/services/** backend/tests/services/** backend/contracts/services.* | K21: BE-A02, BE-B02 | N21: Danh mục đúng rental_services hiện tại, không giả có code/active; dịch vụ riêng catalog_service_id null. Upsert đúng nhà/phòng, active cả hai cấp; null kế thừa, override 0 giữ 0. Công bố ServiceQuotePort có thể đọc bằng connection/UoW của consumer để chốt invoice snapshot. | O21: Không gán dịch vụ nhà khác; giá/phương pháp override hợp lệ. Đổi cấu hình không cập nhật dòng invoice đã có. | P21: Chưa làm | Q21: Chưa | R21: Chưa | S21: Chưa | T21: Chưa | U21: Chưa | V21: Chưa | W21: Chưa | X21: =COUNTIF(Q21:W21,"Xong")/7 -> 0 | Y21: =IF(AND(AND(INDEX(BE_Tasks!$P$2:$P$53,MATCH("BE-A02",BE_Tasks!$A$2:$A$53,0))="Hoàn thành",INDEX(BE_Tasks!$Z$2:$Z$53,MATCH("BE-A02",BE_Tasks!$A$2:$A$53,0))=""),AND(INDEX(BE_Tasks!$P$2:$P$53,MATCH("BE-B02",BE_Tasks!$A$2:$A$53,0))="Hoàn thành",INDEX(BE_Tasks!$Z$2:$Z$53,MATCH("BE-B02",BE_Tasks!$A$2:$A$53,0))="")),"Đủ điều kiện","Chờ phụ thuộc") -> Chờ phụ thuộc | Z21: =IF(AND(P21="Hoàn thành",OR(X21<1,Y21<>"Đủ điều kiện",AND(AE21="",AD21=""))),"Thiếu bước / phụ thuộc / bằng chứng","") | AG21: Mở task
A22: BE-B04 | B22: P1 | C22: 4 | D22: B | E22: C | F22: Cổng đọc nhà/phòng và kết nối cho A/C | G22: 3 | H22: 0 | J22: backend/src/modules/properties/** backend/src/modules/house-rights/** backend/tests/properties/** backend/tests/fixtures/B/** backend/tests/contracts/B/** backend/tests/e2e/property-*/** backend/contracts/properties.* backend/src/modules/services/** backend/tests/services/** backend/contracts/services.* backend/src/modules/roommates/** backend/tests/roommates/** backend/contracts/roommates.* | K22: BE-B02, BE-B03 | N22: RoomSnapshot có capacity/status/effectiveRight/currentLoad, không chứa PII cư dân. ConnectionPort đọc accepted/not-ended bằng transaction được truyền; dữ liệu test riêng dù B13 chưa tạo endpoint. ServiceQuotePort và FileContext resolver không tạo import vòng; injection ở composition root do A quản lý. | O22: Contract tests chạy cùng bộ fixture với mock B01. C vẫn recheck quyền/capacity dưới khóa trong procedure, không dùng snapshot cũ làm quyền thuê. | P22: Chưa làm | Q22: Chưa | R22: Chưa | S22: Chưa | T22: Chưa | U22: Chưa | V22: Chưa | W22: Chưa | X22: =COUNTIF(Q22:W22,"Xong")/7 -> 0 | Y22: =IF(AND(AND(INDEX(BE_Tasks!$P$2:$P$53,MATCH("BE-B02",BE_Tasks!$A$2:$A$53,0))="Hoàn thành",INDEX(BE_Tasks!$Z$2:$Z$53,MATCH("BE-B02",BE_Tasks!$A$2:$A$53,0))=""),AND(INDEX(BE_Tasks!$P$2:$P$53,MATCH("BE-B03",BE_Tasks!$A$2:$A$53,0))="Hoàn thành",INDEX(BE_Tasks!$Z$2:$Z$53,MATCH("BE-B03",BE_Tasks!$A$2:$A$53,0))="")),"Đủ điều kiện","Chờ phụ thuộc") -> Chờ phụ thuộc | Z22: =IF(AND(P22="Hoàn thành",OR(X22<1,Y22<>"Đủ điều kiện",AND(AE22="",AD22=""))),"Thiếu bước / phụ thuộc / bằng chứng","") | AG22: Mở task
A23: BE-B05 | B23: P2 | C23: 5 | D23: B | E23: C | F23: Xác minh quyền nhà và trạng thái hiệu lực | G23: 8 | H23: 9 | I23: API-033, API-034, API-035, API-036, API-037, API-038, API-039, API-040, API-041 | J23: backend/src/modules/properties/** backend/src/modules/house-rights/** backend/tests/properties/** backend/tests/fixtures/B/** backend/tests/contracts/B/** backend/tests/e2e/property-*/** backend/contracts/properties.* database/source/house-rights.sql database/source/post-review-quota.sql database/source/viewing-proposals.sql backend/tests/sql-property/** | K23: BE-B04, BE-A05 | M23: D05 | N23: Nộp/rút/duyệt/từ chối/thu hồi đúng procedure, đủ loại giấy theo OWNER/AUTHORIZED/SUBLESSOR. Ngày hiệu lực VN, định danh/version khớp; pending không tự làm mất quyền cũ. Dùng effective view khi đọc; mất quyền chặn công khai/thuê mới nhưng giữ lịch sử. | O23: Không có quyền chỉ nhờ account landlord được duyệt; admin cần evidenceChecked=true. Đổi định danh/rút/hết hạn/thu hồi giữ tệp bất biến và audit. | P23: Chưa làm | Q23: Chưa | R23: Chưa | S23: Chưa | T23: Chưa | U23: Chưa | V23: Chưa | W23: Chưa | X23: =COUNTIF(Q23:W23,"Xong")/7 -> 0 | Y23: =IF(AND(AND(INDEX(BE_Tasks!$P$2:$P$53,MATCH("BE-B04",BE_Tasks!$A$2:$A$53,0))="Hoàn thành",INDEX(BE_Tasks!$Z$2:$Z$53,MATCH("BE-B04",BE_Tasks!$A$2:$A$53,0))=""),AND(INDEX(BE_Tasks!$P$2:$P$53,MATCH("BE-A05",BE_Tasks!$A$2:$A$53,0))="Hoàn thành",INDEX(BE_Tasks!$Z$2:$Z$53,MATCH("BE-A05",BE_Tasks!$A$2:$A$53,0))="")),"Đủ điều kiện","Chờ phụ thuộc") -> Chờ phụ thuộc | Z23: =IF(AND(P23="Hoàn thành",OR(X23<1,Y23<>"Đủ điều kiện",AND(AE23="",AD23=""))),"Thiếu bước / phụ thuộc / bằng chứng","") | AG23: Mở task
A24: BE-B06 | B24: P2 | C24: 6 | D24: B | E24: C | F24: Gửi tin kèm ảnh nguyên tử và kiểm duyệt | G24: 8 | H24: 8 | I24: API-047, API-050, API-051, API-052, API-053, API-054, API-055, API-056 | J24: backend/src/modules/posts/** backend/tests/posts/** backend/contracts/posts.* database/source/house-rights.sql database/source/post-review-quota.sql database/source/viewing-proposals.sql backend/tests/sql-property/** | K24: BE-B05, BE-A04, BE-A05 | M24: D07 | N24: sp_submit_post nhận/ghi ảnh+amenities cùng transaction, content_version và quota 3 slot đúng hiện tại. Edit giữ roomId; pending edit không chiếm thêm lượt; moderate/hide/restore theo đúng postId. Các /admin/posts ở module posts; không sửa account-admin controller của A. | O24: 4 submit tranh slot chỉ có tối đa 3 pending; lỗi ảnh rollback cả bài và slot. Duyệt/restore yêu cầu quyền nhà hiệu lực; không ảnh hưởng các tin khác của phòng. | P24: Chưa làm | Q24: Chưa | R24: Chưa | S24: Chưa | T24: Chưa | U24: Chưa | V24: Chưa | W24: Chưa | X24: =COUNTIF(Q24:W24,"Xong")/7 -> 0 | Y24: =IF(AND(AND(INDEX(BE_Tasks!$P$2:$P$53,MATCH("BE-B05",BE_Tasks!$A$2:$A$53,0))="Hoàn thành",INDEX(BE_Tasks!$Z$2:$Z$53,MATCH("BE-B05",BE_Tasks!$A$2:$A$53,0))=""),AND(INDEX(BE_Tasks!$P$2:$P$53,MATCH("BE-A04",BE_Tasks!$A$2:$A$53,0))="Hoàn thành",INDEX(BE_Tasks!$Z$2:$Z$53,MATCH("BE-A04",BE_Tasks!$A$2:$A$53,0))=""),AND(INDEX(BE_Tasks!$P$2:$P$53,MATCH("BE-A05",BE_Tasks!$A$2:$A$53,0))="Hoàn thành",INDEX(BE_Tasks!$Z$2:$Z$53,MATCH("BE-A05",BE_Tasks!$A$2:$A$53,0))="")),"Đủ điều kiện","Chờ phụ thuộc") -> Chờ phụ thuộc | Z24: =IF(AND(P24="Hoàn thành",OR(X24<1,Y24<>"Đủ điều kiện",AND(AE24="",AD24=""))),"Thiếu bước / phụ thuộc / bằng chứng","") | AG24: Mở task
A25: BE-B07 | B25: P2 | C25: 7 | D25: B | E25: C | F25: Tìm phòng, chi tiết và lưu tin công khai | G25: 5 | H25: 6 | I25: API-046, API-057, API-058, API-059, API-060, API-061 | J25: backend/src/modules/posts/** backend/tests/posts/** backend/contracts/posts.* backend/src/modules/properties/** backend/src/modules/house-rights/** backend/tests/properties/** backend/tests/fixtures/B/** backend/tests/contracts/B/** backend/tests/e2e/property-*/** backend/contracts/properties.* | K25: BE-B06 | N25: Lọc/search/paging/sort whitelist; không lộ PII người ở trong room detail. Lưu theo postId; tin ẩn trả placeholder/404, không chuyển sang tin khác cùng phòng. Bàn giao PublicPostPort để A share card và tạo inquiry từ postId. | O25: Hết quyền nhà ẩn ngay không chờ job; khám phá loại OCCUPIED đúng rule. Public JSON không có residents/CCCD/tin chưa duyệt. | P25: Chưa làm | Q25: Chưa | R25: Chưa | S25: Chưa | T25: Chưa | U25: Chưa | V25: Chưa | W25: Chưa | X25: =COUNTIF(Q25:W25,"Xong")/7 -> 0 | Y25: =IF(AND(AND(INDEX(BE_Tasks!$P$2:$P$53,MATCH("BE-B06",BE_Tasks!$A$2:$A$53,0))="Hoàn thành",INDEX(BE_Tasks!$Z$2:$Z$53,MATCH("BE-B06",BE_Tasks!$A$2:$A$53,0))="")),"Đủ điều kiện","Chờ phụ thuộc") -> Chờ phụ thuộc | Z25: =IF(AND(P25="Hoàn thành",OR(X25<1,Y25<>"Đủ điều kiện",AND(AE25="",AD25=""))),"Thiếu bước / phụ thuộc / bằng chứng","") | AG25: Mở task
A26: BE-B08 | B26: P3 | C26: 8 | D26: B | E26: C | F26: Đề nghị lịch xem và xét duyệt | G26: 5 | H26: 4 | I26: API-091, API-092, API-093, API-094 | J26: backend/src/modules/viewings/** backend/tests/viewings/** backend/tests/e2e/viewing-contract/** backend/contracts/viewings.* database/source/house-rights.sql database/source/post-review-quota.sql database/source/viewing-proposals.sql backend/tests/sql-property/** | K26: BE-A08, BE-B07 | N26: Idempotency UUID; một PENDING/tenant+room; proposal chưa giữ giờ/chỗ. Accept khóa room, recheck context/quyền/tài khoản và overlap; tạo đúng một schedule cùng transaction. Withdraw/expire theo now, không đợi worker; kết quả gửi vào notification source. | O26: Hai proposal trùng giờ có thể chờ nhưng chỉ một schedule nếu xung đột. Duyệt lại trả linked schedule, không tạo lần hai. | P26: Chưa làm | Q26: Chưa | R26: Chưa | S26: Chưa | T26: Chưa | U26: Chưa | V26: Chưa | W26: Chưa | X26: =COUNTIF(Q26:W26,"Xong")/7 -> 0 | Y26: =IF(AND(AND(INDEX(BE_Tasks!$P$2:$P$53,MATCH("BE-A08",BE_Tasks!$A$2:$A$53,0))="Hoàn thành",INDEX(BE_Tasks!$Z$2:$Z$53,MATCH("BE-A08",BE_Tasks!$A$2:$A$53,0))=""),AND(INDEX(BE_Tasks!$P$2:$P$53,MATCH("BE-B07",BE_Tasks!$A$2:$A$53,0))="Hoàn thành",INDEX(BE_Tasks!$Z$2:$Z$53,MATCH("BE-B07",BE_Tasks!$A$2:$A$53,0))="")),"Đủ điều kiện","Chờ phụ thuộc") -> Chờ phụ thuộc | Z26: =IF(AND(P26="Hoàn thành",OR(X26<1,Y26<>"Đủ điều kiện",AND(AE26="",AD26=""))),"Thiếu bước / phụ thuộc / bằng chứng","") | AG26: Mở task
A27: BE-B09 | B27: P3 | C27: 9 | D27: B | E27: C | F27: Tạo lịch trực tiếp, tham dự và ý định thuê | G27: 5 | H27: 6 | I27: API-095, API-096, API-097, API-098, API-099, API-100 | J27: backend/src/modules/viewings/** backend/tests/viewings/** backend/tests/e2e/viewing-contract/** backend/contracts/viewings.* database/source/house-rights.sql database/source/post-review-quota.sql database/source/viewing-proposals.sql backend/tests/sql-property/** | K27: BE-B08 | N27: Hẹn trực tiếp cần tin thuê đúng conversation/room; UTC và duration 30/60/90/120. ATTENDED/NO_SHOW/CANCEL đúng vai trò/thời điểm; quyết định thuê theo chuyển trạng thái cho phép. Công bố fixture viewing đủ điều kiện và không đủ điều kiện; C không viết một lịch riêng. | O27: Khoảng [start,end) không chồng nhau, liền kề được; không hẹn bằng ROOMMATE. AGREED không giữ phòng; withdrawal bị chặn khi còn hợp đồng mở. | P27: Chưa làm | Q27: Chưa | R27: Chưa | S27: Chưa | T27: Chưa | U27: Chưa | V27: Chưa | W27: Chưa | X27: =COUNTIF(Q27:W27,"Xong")/7 -> 0 | Y27: =IF(AND(AND(INDEX(BE_Tasks!$P$2:$P$53,MATCH("BE-B08",BE_Tasks!$A$2:$A$53,0))="Hoàn thành",INDEX(BE_Tasks!$Z$2:$Z$53,MATCH("BE-B08",BE_Tasks!$A$2:$A$53,0))="")),"Đủ điều kiện","Chờ phụ thuộc") -> Chờ phụ thuộc | Z27: =IF(AND(P27="Hoàn thành",OR(X27<1,Y27<>"Đủ điều kiện",AND(AE27="",AD27=""))),"Thiếu bước / phụ thuộc / bằng chứng","") | AG27: Mở task
A28: BE-B10 | B28: P3 | C28: 10 | D28: B | E28: C | F28: Bàn giao và kiểm tra lịch khi hợp đồng giữ phòng | G28: 3 | H28: 0 | J28: backend/src/modules/viewings/** backend/tests/viewings/** backend/tests/e2e/viewing-contract/** backend/contracts/viewings.* | K28: BE-B09, BE-C05 | N28: Gửi contract từ lịch bàn giao, kiểm tra lịch/proposal ở mọi post cùng room. Phân biệt lịch chưa bắt đầu với đang diễn ra/đã hết; trả event tổng hợp cho A. Hủy contract không khôi phục lịch cũ; lập bug đúng owner file/SQL thay vì sửa chéo. | O28: QA03/04 chạy với cả endpoint lịch và contract thật. Timeline A11 và list lịch đều đọc cùng trạng thái. | P28: Chưa làm | Q28: Chưa | R28: Chưa | S28: Chưa | T28: Chưa | U28: Chưa | V28: Chưa | W28: Chưa | X28: =COUNTIF(Q28:W28,"Xong")/7 -> 0 | Y28: =IF(AND(AND(INDEX(BE_Tasks!$P$2:$P$53,MATCH("BE-B09",BE_Tasks!$A$2:$A$53,0))="Hoàn thành",INDEX(BE_Tasks!$Z$2:$Z$53,MATCH("BE-B09",BE_Tasks!$A$2:$A$53,0))=""),AND(INDEX(BE_Tasks!$P$2:$P$53,MATCH("BE-C05",BE_Tasks!$A$2:$A$53,0))="Hoàn thành",INDEX(BE_Tasks!$Z$2:$Z$53,MATCH("BE-C05",BE_Tasks!$A$2:$A$53,0))="")),"Đủ điều kiện","Chờ phụ thuộc") -> Chờ phụ thuộc | Z28: =IF(AND(P28="Hoàn thành",OR(X28<1,Y28<>"Đủ điều kiện",AND(AE28="",AD28=""))),"Thiếu bước / phụ thuộc / bằng chứng","") | AG28: Mở task
A29: BE-B11 | B29: P4 | C29: 11 | D29: B | E29: C | F29: Hồ sơ ở ghép và tình trạng nhà ở | G29: 5 | H29: 5 | I29: API-062, API-063, API-064, API-066, API-067 | J29: backend/src/modules/roommates/** backend/tests/roommates/** backend/contracts/roommates.* | K29: BE-B04, BE-C02 | N29: PUT profile version, budget/location/available date; IN_SYSTEM do server suy từ đúng member ACTIVE. EXTERNAL tối đa 1.000 ký tự và bỏ mô tả khi đổi trạng thái. Giá trị lifestyle giữ schema JSON theo criterion, không thêm cột mỗi thói quen. | O29: Không tự gắn memberId client gửi; stale version 409. Người chưa có ACTIVE được tự khai chưa có chỗ/ngoài hệ thống đúng rule. | P29: Chưa làm | Q29: Chưa | R29: Chưa | S29: Chưa | T29: Chưa | U29: Chưa | V29: Chưa | W29: Chưa | X29: =COUNTIF(Q29:W29,"Xong")/7 -> 0 | Y29: =IF(AND(AND(INDEX(BE_Tasks!$P$2:$P$53,MATCH("BE-B04",BE_Tasks!$A$2:$A$53,0))="Hoàn thành",INDEX(BE_Tasks!$Z$2:$Z$53,MATCH("BE-B04",BE_Tasks!$A$2:$A$53,0))=""),AND(INDEX(BE_Tasks!$P$2:$P$53,MATCH("BE-C02",BE_Tasks!$A$2:$A$53,0))="Hoàn thành",INDEX(BE_Tasks!$Z$2:$Z$53,MATCH("BE-C02",BE_Tasks!$A$2:$A$53,0))="")),"Đủ điều kiện","Chờ phụ thuộc") -> Chờ phụ thuộc | Z29: =IF(AND(P29="Hoàn thành",OR(X29<1,Y29<>"Đủ điều kiện",AND(AE29="",AD29=""))),"Thiếu bước / phụ thuộc / bằng chứng","") | AG29: Mở task
A30: BE-B12 | B30: P4 | C30: 12 | D30: B | E30: C | F30: Danh mục tiêu chí ghép linh động | G30: 3 | H30: 3 | I30: API-065, API-069, API-070 | J30: backend/src/modules/roommates/** backend/tests/roommates/** backend/contracts/roommates.* | K30: BE-B11 | M30: D02 | N30: Code duy nhất, valueType/allowedValues hợp lệ; mandatory cần preferredValue, importance 0–5. Không đổi kiểu khiến profile cũ mất nghĩa; thay đổi tương thích cần version/plan. Đề xuất D02 cho người chốt; giải thích score v1 và xử lý thiếu dữ liệu. | O30: Self/preferred JSON sai kiểu hoặc category ngoài tập bị chặn. Ngừng tiêu chí vẫn giữ giá trị lịch sử theo chính sách. | P30: Chưa làm | Q30: Chưa | R30: Chưa | S30: Chưa | T30: Chưa | U30: Chưa | V30: Chưa | W30: Chưa | X30: =COUNTIF(Q30:W30,"Xong")/7 -> 0 | Y30: =IF(AND(AND(INDEX(BE_Tasks!$P$2:$P$53,MATCH("BE-B11",BE_Tasks!$A$2:$A$53,0))="Hoàn thành",INDEX(BE_Tasks!$Z$2:$Z$53,MATCH("BE-B11",BE_Tasks!$A$2:$A$53,0))="")),"Đủ điều kiện","Chờ phụ thuộc") -> Chờ phụ thuộc | Z30: =IF(AND(P30="Hoàn thành",OR(X30<1,Y30<>"Đủ điều kiện",AND(AE30="",AD30=""))),"Thiếu bước / phụ thuộc / bằng chứng","") | AG30: Mở task
A31: BE-B13 | B31: P4 | C31: 13 | D31: B | E31: C | F31: Mời kết nối và tạo chat đúng một lần | G31: 5 | H31: 5 | I31: API-071, API-072, API-073, API-074, API-075 | J31: backend/src/modules/roommates/** backend/tests/roommates/** backend/contracts/roommates.* | K31: BE-B12, BE-A08 | M31: D03 | N31: Người gửi có profile, cặp chuẩn hóa chống hai chiều, receiver mới được phản hồi. ACCEPT ghi request và ensureRoommateConversation(tx) nguyên tử, không tạo join/hold. End ghi ended_at/reason, chặn gửi mới; policy đọc lịch sử D03 phải chốt cùng A. | O31: Gửi chéo không tự accept; retry accept không sinh chat trùng. Hồ sơ cũ vẫn phản hồi được; room capacity không chặn kết nối đơn thuần. | P31: Chưa làm | Q31: Chưa | R31: Chưa | S31: Chưa | T31: Chưa | U31: Chưa | V31: Chưa | W31: Chưa | X31: =COUNTIF(Q31:W31,"Xong")/7 -> 0 | Y31: =IF(AND(AND(INDEX(BE_Tasks!$P$2:$P$53,MATCH("BE-B12",BE_Tasks!$A$2:$A$53,0))="Hoàn thành",INDEX(BE_Tasks!$Z$2:$Z$53,MATCH("BE-B12",BE_Tasks!$A$2:$A$53,0))=""),AND(INDEX(BE_Tasks!$P$2:$P$53,MATCH("BE-A08",BE_Tasks!$A$2:$A$53,0))="Hoàn thành",INDEX(BE_Tasks!$Z$2:$Z$53,MATCH("BE-A08",BE_Tasks!$A$2:$A$53,0))="")),"Đủ điều kiện","Chờ phụ thuộc") -> Chờ phụ thuộc | Z31: =IF(AND(P31="Hoàn thành",OR(X31<1,Y31<>"Đủ điều kiện",AND(AE31="",AD31=""))),"Thiếu bước / phụ thuộc / bằng chứng","") | AG31: Mở task
A32: BE-B14 | B32: P5 | C32: 14 | D32: B | E32: C | F32: Báo cáo vi phạm và kết luận | G32: 5 | H32: 5 | I32: API-156, API-157, API-158, API-159, API-160 | J32: backend/src/modules/reviews/** backend/src/modules/reports/** backend/tests/content-moderation/** | K32: BE-B07, BE-A05, BE-A04 | N32: Target đúng một loại và người báo cáo có quyền đọc; file bằng chứng PRIVATE thuộc actor. Hàng đợi/details/decision với actor/time/resolution; audit không tự khóa user hoặc hủy thuê. Giữ các FK và che kết quả điều tra riêng tư khỏi reporter khi không được phép. | O32: Không nhắm nhiều target cùng report; bản đóng không bị form cũ mở lại. Nếu cần khóa account, gọi cổng A theo nghiệp vụ; không viết users repository mới. | P32: Chưa làm | Q32: Chưa | R32: Chưa | S32: Chưa | T32: Chưa | U32: Chưa | V32: Chưa | W32: Chưa | X32: =COUNTIF(Q32:W32,"Xong")/7 -> 0 | Y32: =IF(AND(AND(INDEX(BE_Tasks!$P$2:$P$53,MATCH("BE-B07",BE_Tasks!$A$2:$A$53,0))="Hoàn thành",INDEX(BE_Tasks!$Z$2:$Z$53,MATCH("BE-B07",BE_Tasks!$A$2:$A$53,0))=""),AND(INDEX(BE_Tasks!$P$2:$P$53,MATCH("BE-A05",BE_Tasks!$A$2:$A$53,0))="Hoàn thành",INDEX(BE_Tasks!$Z$2:$Z$53,MATCH("BE-A05",BE_Tasks!$A$2:$A$53,0))=""),AND(INDEX(BE_Tasks!$P$2:$P$53,MATCH("BE-A04",BE_Tasks!$A$2:$A$53,0))="Hoàn thành",INDEX(BE_Tasks!$Z$2:$Z$53,MATCH("BE-A04",BE_Tasks!$A$2:$A$53,0))="")),"Đủ điều kiện","Chờ phụ thuộc") -> Chờ phụ thuộc | Z32: =IF(AND(P32="Hoàn thành",OR(X32<1,Y32<>"Đủ điều kiện",AND(AE32="",AD32=""))),"Thiếu bước / phụ thuộc / bằng chứng","") | AG32: Mở task
A33: BE-B15 | B33: P6 | C33: 15 | D33: B | E33: C | F33: Danh sách người phù hợp theo chính sách đã chốt | G33: 5 | H33: 1 | I33: API-068 | J33: backend/src/modules/roommates/** backend/tests/roommates/** backend/contracts/roommates.* | K33: BE-B13 | M33: D02 | N33: Lọc self/inactive, location/budget và tiêu chí bắt buộc. AlgorithmVersion/score/explanations cố định theo D02, test cùng dữ liệu thiếu/ngân sách biên. Nếu D02 chưa chốt, ghi Bị chặn cho task; không trả score mẫu như kết quả thật. | O33: Cùng input+algorithmVersion có kết quả xác định, không lộ PII cư dân. Cấu trúc output giữ contract, có pagination/sort ổn định. | P33: Chưa làm | Q33: Chưa | R33: Chưa | S33: Chưa | T33: Chưa | U33: Chưa | V33: Chưa | W33: Chưa | X33: =COUNTIF(Q33:W33,"Xong")/7 -> 0 | Y33: =IF(AND(AND(INDEX(BE_Tasks!$P$2:$P$53,MATCH("BE-B13",BE_Tasks!$A$2:$A$53,0))="Hoàn thành",INDEX(BE_Tasks!$Z$2:$Z$53,MATCH("BE-B13",BE_Tasks!$A$2:$A$53,0))="")),"Đủ điều kiện","Chờ phụ thuộc") -> Chờ phụ thuộc | Z33: =IF(AND(P33="Hoàn thành",OR(X33<1,Y33<>"Đủ điều kiện",AND(AE33="",AD33=""))),"Thiếu bước / phụ thuộc / bằng chứng","") | AG33: Mở task
A34: BE-B16 | B34: P6 | C34: 16 | D34: B | E34: C | F34: Đánh giá theo bằng chứng cư trú và audit | G34: 5 | H34: 3 | I34: API-153, API-154, API-155 | J34: backend/src/modules/reviews/** backend/src/modules/reports/** backend/tests/content-moderation/** | K34: BE-B14, BE-C02, BE-A15 | M34: D13, D14 | N34: Unique reviewer+room+contract; đúng roomTenant evidence của actor, rating 1–5. Public chỉ PUBLISHED, moderation không sửa bằng chứng hợp đồng/cư trú. Giữ trạng thái cần chốt nếu D13/D14 chưa có quyết định, không ghi nhầm target_post_id. | O34: Tài khoản chỉ từng xem phòng không được review; không đánh giá trùng. Ẩn review giữ audit đúng đối tượng và không làm mất cư trú. | P34: Chưa làm | Q34: Chưa | R34: Chưa | S34: Chưa | T34: Chưa | U34: Chưa | V34: Chưa | W34: Chưa | X34: =COUNTIF(Q34:W34,"Xong")/7 -> 0 | Y34: =IF(AND(AND(INDEX(BE_Tasks!$P$2:$P$53,MATCH("BE-B14",BE_Tasks!$A$2:$A$53,0))="Hoàn thành",INDEX(BE_Tasks!$Z$2:$Z$53,MATCH("BE-B14",BE_Tasks!$A$2:$A$53,0))=""),AND(INDEX(BE_Tasks!$P$2:$P$53,MATCH("BE-C02",BE_Tasks!$A$2:$A$53,0))="Hoàn thành",INDEX(BE_Tasks!$Z$2:$Z$53,MATCH("BE-C02",BE_Tasks!$A$2:$A$53,0))=""),AND(INDEX(BE_Tasks!$P$2:$P$53,MATCH("BE-A15",BE_Tasks!$A$2:$A$53,0))="Hoàn thành",INDEX(BE_Tasks!$Z$2:$Z$53,MATCH("BE-A15",BE_Tasks!$A$2:$A$53,0))="")),"Đủ điều kiện","Chờ phụ thuộc") -> Chờ phụ thuộc | Z34: =IF(AND(P34="Hoàn thành",OR(X34<1,Y34<>"Đủ điều kiện",AND(AE34="",AD34=""))),"Thiếu bước / phụ thuộc / bằng chứng","") | AG34: Mở task
A35: BE-B17 | B35: P6 | C35: 17 | D35: B | E35: C | F35: Dashboard chủ trọ bằng metric ports | G35: 3 | H35: 1 | I35: API-175 | J35: backend/src/modules/properties/** backend/src/modules/house-rights/** backend/tests/properties/** backend/tests/fixtures/B/** backend/tests/contracts/B/** backend/tests/e2e/property-*/** backend/contracts/properties.* | K35: BE-B16, BE-A13, BE-C12 | N35: Scope landlord cho từng metric; ACTIVE tính occupied, không đồng nhất reserved với occupied. Lịch chưa hết giờ, hóa đơn UNPAID/OVERDUE và pending requests có nguồn đúng module. Có asOf, tách truy vấn count khỏi trả danh tính cư dân. | O35: Không cộng nhầm dữ liệu chủ khác; amount decimal và status phù hợp. Contract tests của metric ports phát hiện consumer dùng field cũ. | P35: Chưa làm | Q35: Chưa | R35: Chưa | S35: Chưa | T35: Chưa | U35: Chưa | V35: Chưa | W35: Chưa | X35: =COUNTIF(Q35:W35,"Xong")/7 -> 0 | Y35: =IF(AND(AND(INDEX(BE_Tasks!$P$2:$P$53,MATCH("BE-B16",BE_Tasks!$A$2:$A$53,0))="Hoàn thành",INDEX(BE_Tasks!$Z$2:$Z$53,MATCH("BE-B16",BE_Tasks!$A$2:$A$53,0))=""),AND(INDEX(BE_Tasks!$P$2:$P$53,MATCH("BE-A13",BE_Tasks!$A$2:$A$53,0))="Hoàn thành",INDEX(BE_Tasks!$Z$2:$Z$53,MATCH("BE-A13",BE_Tasks!$A$2:$A$53,0))=""),AND(INDEX(BE_Tasks!$P$2:$P$53,MATCH("BE-C12",BE_Tasks!$A$2:$A$53,0))="Hoàn thành",INDEX(BE_Tasks!$Z$2:$Z$53,MATCH("BE-C12",BE_Tasks!$A$2:$A$53,0))="")),"Đủ điều kiện","Chờ phụ thuộc") -> Chờ phụ thuộc | Z35: =IF(AND(P35="Hoàn thành",OR(X35<1,Y35<>"Đủ điều kiện",AND(AE35="",AD35=""))),"Thiếu bước / phụ thuộc / bằng chứng","") | AG35: Mở task
A36: BE-B18 | B36: P6 | C36: 18 | D36: B | E36: C | F36: Worker hết quyền nhà và bảo toàn dữ liệu cũ | G36: 2 | H36: 0 | J36: backend/src/modules/properties/** backend/src/modules/house-rights/** backend/tests/properties/** backend/tests/fixtures/B/** backend/tests/contracts/B/** backend/tests/e2e/property-*/** backend/contracts/properties.* database/source/house-rights.sql database/source/post-review-quota.sql database/source/viewing-proposals.sql backend/tests/sql-property/** | K36: BE-B05 | N36: APPROVED valid_until<todayVN → EXPIRED theo chính sách, giữ proof/history. Không xóa/ẩn vật lý từng post hoặc kết thúc contract để giả mất quyền. Đăng ký worker qua manifest riêng, không sửa worker registry chung. | O36: Job chậm vẫn không công khai tin hết quyền; chạy lặp an toàn. Luồng rời/kết thúc hợp đồng cũ tiếp tục dùng được. | P36: Chưa làm | Q36: Chưa | R36: Chưa | S36: Chưa | T36: Chưa | U36: Chưa | V36: Chưa | W36: Chưa | X36: =COUNTIF(Q36:W36,"Xong")/7 -> 0 | Y36: =IF(AND(AND(INDEX(BE_Tasks!$P$2:$P$53,MATCH("BE-B05",BE_Tasks!$A$2:$A$53,0))="Hoàn thành",INDEX(BE_Tasks!$Z$2:$Z$53,MATCH("BE-B05",BE_Tasks!$A$2:$A$53,0))="")),"Đủ điều kiện","Chờ phụ thuộc") -> Chờ phụ thuộc | Z36: =IF(AND(P36="Hoàn thành",OR(X36<1,Y36<>"Đủ điều kiện",AND(AE36="",AD36=""))),"Thiếu bước / phụ thuộc / bằng chứng","") | AG36: Mở task
A37: BE-B19 | B37: P7 | C37: 19 | D37: B | E37: C | F37: Kiểm thử module nhà/tin/lịch và nội dung | G37: 5 | H37: 0 | J37: backend/src/modules/properties/** backend/src/modules/house-rights/** backend/tests/properties/** backend/tests/fixtures/B/** backend/tests/contracts/B/** backend/tests/e2e/property-*/** backend/contracts/properties.* backend/src/modules/posts/** backend/tests/posts/** backend/contracts/posts.* backend/src/modules/viewings/** backend/tests/viewings/** backend/tests/e2e/viewing-contract/** backend/contracts/viewings.* backend/src/modules/roommates/** backend/tests/roommates/** backend/contracts/roommates.* backend/src/modules/reviews/** backend/src/modules/reports/** backend/tests/content-moderation/** | K37: BE-B10, BE-B15, BE-B16, BE-B17, BE-B18 | N37: QA01/02/04/09/13/14/15 có test concurrency và quyền chéo tài khoản. Kiểm tra D07 upload+post rollback; search/favorites/shared card sau mất quyền. Nộp report test, collection requests và danh sách source SQL đã thay cho A. | O37: Mỗi endpoint B có DTO/auth/logic/test/docs/review và phạm vi file đúng owner. Không sửa generated SQL/seed/tests của C để làm CI xanh. | P37: Chưa làm | Q37: Chưa | R37: Chưa | S37: Chưa | T37: Chưa | U37: Chưa | V37: Chưa | W37: Chưa | X37: =COUNTIF(Q37:W37,"Xong")/7 -> 0 | Y37: =IF(AND(AND(INDEX(BE_Tasks!$P$2:$P$53,MATCH("BE-B10",BE_Tasks!$A$2:$A$53,0))="Hoàn thành",INDEX(BE_Tasks!$Z$2:$Z$53,MATCH("BE-B10",BE_Tasks!$A$2:$A$53,0))=""),AND(INDEX(BE_Tasks!$P$2:$P$53,MATCH("BE-B15",BE_Tasks!$A$2:$A$53,0))="Hoàn thành",INDEX(BE_Tasks!$Z$2:$Z$53,MATCH("BE-B15",BE_Tasks!$A$2:$A$53,0))=""),AND(INDEX(BE_Tasks!$P$2:$P$53,MATCH("BE-B16",BE_Tasks!$A$2:$A$53,0))="Hoàn thành",INDEX(BE_Tasks!$Z$2:$Z$53,MATCH("BE-B16",BE_Tasks!$A$2:$A$53,0))=""),AND(INDEX(BE_Tasks!$P$2:$P$53,MATCH("BE-B17",BE_Tasks!$A$2:$A$53,0))="Hoàn thành",INDEX(BE_Tasks!$Z$2:$Z$53,MATCH("BE-B17",BE_Tasks!$A$2:$A$53,0))=""),AND(INDEX(BE_Tasks!$P$2:$P$53,MATCH("BE-B18",BE_Tasks!$A$2:$A$53,0))="Hoàn thành",INDEX(BE_Tasks!$Z$2:$Z$53,MATCH("BE-B18",BE_Tasks!$A$2:$A$53,0))="")),"Đủ điều kiện","Chờ phụ thuộc") -> Chờ phụ thuộc | Z37: =IF(AND(P37="Hoàn thành",OR(X37<1,Y37<>"Đủ điều kiện",AND(AE37="",AD37=""))),"Thiếu bước / phụ thuộc / bằng chứng","") | AG37: Mở task
A38: BE-C01 | B38: P0 | C38: 1 | D38: C | E38: A | F38: Chốt trạng thái thuê, transaction và cổng cư trú | G38: 5 | H38: 0 | J38: backend/src/modules/rentals/** backend/tests/rentals/** backend/tests/fixtures/C/** backend/tests/contracts/C/** backend/tests/e2e/rental-*/** backend/contracts/rentals.* database/source/workflows.sql database/source/contract-viewing-cleanup.sql backend/tests/sql-rental/** | M38: D06, D10, D11 | N38: Vẽ chuyển trạng thái và lock order roomId tăng dần; xác định procedure tự commit. Công bố ResidencyReadPort/contract snapshot và fixture của C; A/B không join/ghi trực tiếp các bảng này trong service của họ. D10 expectedRevision và D11 import được ghi là mở rộng cần làm; không xác nhận nhầm phiên bản. | O38: A02/B01 cùng duyệt contract; chưa chọn framework vẫn chuẩn bị SQL/fixture được. Planned/active/left/cancelled, payer cũ, đại diện ban đầu/hiện tại được phân biệt. | P38: Chưa làm | Q38: Chưa | R38: Chưa | S38: Chưa | T38: Chưa | U38: Chưa | V38: Chưa | W38: Chưa | X38: =COUNTIF(Q38:W38,"Xong")/7 -> 0 | Y38: =IF(TRUE,"Đủ điều kiện","Chờ phụ thuộc") -> Đủ điều kiện | Z38: =IF(AND(P38="Hoàn thành",OR(X38<1,Y38<>"Đủ điều kiện",AND(AE38="",AD38=""))),"Thiếu bước / phụ thuộc / bằng chứng","") | AG38: Mở task
A39: BE-C02 | B39: P1 | C39: 2 | D39: C | E39: A | F39: Cổng đọc hợp đồng/cư trú, thành viên và lịch sử | G39: 5 | H39: 9 | I39: API-048, API-101, API-102, API-105, API-114, API-115, API-116, API-126, API-127 | J39: backend/src/modules/rentals/** backend/tests/rentals/** backend/tests/fixtures/C/** backend/tests/contracts/C/** backend/tests/e2e/rental-*/** backend/contracts/rentals.* | K39: BE-A02, BE-C01 | N39: Danh sách/details/revisions/members/history, candidate representative và export CSV. ResidencyReadPort lấy ACTIVE kể cả contract đóng sai, hỗ trợ connection/UoW của consumer. Privacy theo quan hệ hợp đồng, không lộ CCCD thành viên khác; CSV chống formula injection. | O39: A lập invoice/B xác định IN_SYSTEM bằng port thật mà không import repository C. Không suy người ở chỉ từ representative; time không rõ trả null/chưa rõ. | P39: Chưa làm | Q39: Chưa | R39: Chưa | S39: Chưa | T39: Chưa | U39: Chưa | V39: Chưa | W39: Chưa | X39: =COUNTIF(Q39:W39,"Xong")/7 -> 0 | Y39: =IF(AND(AND(INDEX(BE_Tasks!$P$2:$P$53,MATCH("BE-A02",BE_Tasks!$A$2:$A$53,0))="Hoàn thành",INDEX(BE_Tasks!$Z$2:$Z$53,MATCH("BE-A02",BE_Tasks!$A$2:$A$53,0))=""),AND(INDEX(BE_Tasks!$P$2:$P$53,MATCH("BE-C01",BE_Tasks!$A$2:$A$53,0))="Hoàn thành",INDEX(BE_Tasks!$Z$2:$Z$53,MATCH("BE-C01",BE_Tasks!$A$2:$A$53,0))="")),"Đủ điều kiện","Chờ phụ thuộc") -> Chờ phụ thuộc | Z39: =IF(AND(P39="Hoàn thành",OR(X39<1,Y39<>"Đủ điều kiện",AND(AE39="",AD39=""))),"Thiếu bước / phụ thuộc / bằng chứng","") | AG39: Mở task
A40: BE-C03 | B40: P1 | C40: 3 | D40: C | E40: A | F40: Mẫu hợp đồng và phiên bản mẫu | G40: 3 | H40: 3 | I40: API-165, API-166, API-167 | J40: backend/src/modules/rentals/** backend/tests/rentals/** backend/tests/fixtures/C/** backend/tests/contracts/C/** backend/tests/e2e/rental-*/** backend/contracts/rentals.* | K40: BE-C02 | M40: D14 | N40: Tạo version mới theo name có unique/khóa; không sửa nội dung bản đã dùng. Chủ chỉ thấy active; admin bật/ngừng, snapshot revision giữ nội dung riêng. Nếu cần audit template, dùng A port và D14 sau khi đã mở rộng target. | O40: Hai lần tạo cùng name không đụng version; hợp đồng cũ không đổi khi ngừng mẫu. Không thêm templateController vào file admin chung. | P40: Chưa làm | Q40: Chưa | R40: Chưa | S40: Chưa | T40: Chưa | U40: Chưa | V40: Chưa | W40: Chưa | X40: =COUNTIF(Q40:W40,"Xong")/7 -> 0 | Y40: =IF(AND(AND(INDEX(BE_Tasks!$P$2:$P$53,MATCH("BE-C02",BE_Tasks!$A$2:$A$53,0))="Hoàn thành",INDEX(BE_Tasks!$Z$2:$Z$53,MATCH("BE-C02",BE_Tasks!$A$2:$A$53,0))="")),"Đủ điều kiện","Chờ phụ thuộc") -> Chờ phụ thuộc | Z40: =IF(AND(P40="Hoàn thành",OR(X40<1,Y40<>"Đủ điều kiện",AND(AE40="",AD40=""))),"Thiếu bước / phụ thuộc / bằng chứng","") | AG40: Mở task
A41: BE-C04 | B41: P2 | C41: 4 | D41: C | E41: A | F41: Bảo vệ expected revision và adapter procedure | G41: 5 | H41: 0 | J41: backend/src/modules/rentals/** backend/tests/rentals/** backend/tests/fixtures/C/** backend/tests/contracts/C/** backend/tests/e2e/rental-*/** backend/contracts/rentals.* database/source/workflows.sql database/source/contract-viewing-cleanup.sql backend/tests/sql-rental/** | K41: BE-C01, BE-A04 | M41: D10, D15 | N41: Procedure confirm nhận expectedRevisionId và so dưới cùng khóa; stale 409 không xác nhận bản mới. Mapper camelCase → SQL params/JSON snake_case; ProcedureRunner không bị bọc UoW ngoài. Race/rollback fixture cho create/move-in/handover/transfer; đưa patch source cho A tái sinh SQL trước tích hợp. | O41: QA06 xác nhận A sau khi B đã gửi bị chặn; test không chỉ check trước CALL ở controller. Các OUT ID và lỗi SIGNAL được ánh xạ ổn định, không lộ SQL ra HTTP. | P41: Chưa làm | Q41: Chưa | R41: Chưa | S41: Chưa | T41: Chưa | U41: Chưa | V41: Chưa | W41: Chưa | X41: =COUNTIF(Q41:W41,"Xong")/7 -> 0 | Y41: =IF(AND(AND(INDEX(BE_Tasks!$P$2:$P$53,MATCH("BE-C01",BE_Tasks!$A$2:$A$53,0))="Hoàn thành",INDEX(BE_Tasks!$Z$2:$Z$53,MATCH("BE-C01",BE_Tasks!$A$2:$A$53,0))=""),AND(INDEX(BE_Tasks!$P$2:$P$53,MATCH("BE-A04",BE_Tasks!$A$2:$A$53,0))="Hoàn thành",INDEX(BE_Tasks!$Z$2:$Z$53,MATCH("BE-A04",BE_Tasks!$A$2:$A$53,0))="")),"Đủ điều kiện","Chờ phụ thuộc") -> Chờ phụ thuộc | Z41: =IF(AND(P41="Hoàn thành",OR(X41<1,Y41<>"Đủ điều kiện",AND(AE41="",AD41=""))),"Thiếu bước / phụ thuộc / bằng chứng","") | AG41: Mở task
A42: BE-C05 | B42: P3 | C42: 5 | D42: C | E42: A | F42: Gửi hợp đồng thuê mới và đóng lịch tương lai | G42: 8 | H42: 2 | I42: API-103, API-104 | J42: backend/src/modules/rentals/** backend/tests/rentals/** backend/tests/fixtures/C/** backend/tests/contracts/C/** backend/tests/e2e/rental-*/** backend/contracts/rentals.* database/source/workflows.sql database/source/contract-viewing-cleanup.sql backend/tests/sql-rental/** | K42: BE-C03, BE-C04, BE-B09 | N42: Lịch COMPLETED+AGREED, phòng/quyền nhà/capacity, một open contract; tạo revision+PLANNED+history. Đóng lịch/proposal theo room trên mọi post, thông báo cùng giao dịch; preview chỉ là read-only. Không sửa source lịch của B để hủy contract/viewings; thay đổi helper thuộc B đi qua B. | O42: Tranh giữ phòng chỉ một hợp đồng thắng; lỗi bất kỳ rollback mọi side effect. Hủy contract không hồi lịch cũ, đang diễn ra không bị tự hủy. | P42: Chưa làm | Q42: Chưa | R42: Chưa | S42: Chưa | T42: Chưa | U42: Chưa | V42: Chưa | W42: Chưa | X42: =COUNTIF(Q42:W42,"Xong")/7 -> 0 | Y42: =IF(AND(AND(INDEX(BE_Tasks!$P$2:$P$53,MATCH("BE-C03",BE_Tasks!$A$2:$A$53,0))="Hoàn thành",INDEX(BE_Tasks!$Z$2:$Z$53,MATCH("BE-C03",BE_Tasks!$A$2:$A$53,0))=""),AND(INDEX(BE_Tasks!$P$2:$P$53,MATCH("BE-C04",BE_Tasks!$A$2:$A$53,0))="Hoàn thành",INDEX(BE_Tasks!$Z$2:$Z$53,MATCH("BE-C04",BE_Tasks!$A$2:$A$53,0))=""),AND(INDEX(BE_Tasks!$P$2:$P$53,MATCH("BE-B09",BE_Tasks!$A$2:$A$53,0))="Hoàn thành",INDEX(BE_Tasks!$Z$2:$Z$53,MATCH("BE-B09",BE_Tasks!$A$2:$A$53,0))="")),"Đủ điều kiện","Chờ phụ thuộc") -> Chờ phụ thuộc | Z42: =IF(AND(P42="Hoàn thành",OR(X42<1,Y42<>"Đủ điều kiện",AND(AE42="",AD42=""))),"Thiếu bước / phụ thuộc / bằng chứng","") | AG42: Mở task
A43: BE-C06 | B43: P4 | C43: 6 | D43: C | E43: A | F43: Yêu cầu sửa, gửi lại và xác nhận phiên bản | G43: 5 | H43: 4 | I43: API-106, API-107, API-108, API-109 | J43: backend/src/modules/rentals/** backend/tests/rentals/** backend/tests/fixtures/C/** backend/tests/contracts/C/** backend/tests/e2e/rental-*/** backend/contracts/rentals.* database/source/workflows.sql database/source/contract-viewing-cleanup.sql backend/tests/sql-rental/** | K43: BE-C05 | M43: D10 | N43: Feedback hủy bản chờ/tạo DRAFT mới; chỉ sửa nháp rồi submit phiên bản có snapshot. Confirm đúng đại diện và expected revision bằng procedure đã sửa ở C04. Ghi đủ landlord/tenant confirmation/time; quyền nhà kiểm tra lại, không tự ACTIVE. | O43: Form revision cũ không ghi đè/xác nhận bản mới. Xác nhận giữ người PLANNED và hợp đồng CONFIRMED. | P43: Chưa làm | Q43: Chưa | R43: Chưa | S43: Chưa | T43: Chưa | U43: Chưa | V43: Chưa | W43: Chưa | X43: =COUNTIF(Q43:W43,"Xong")/7 -> 0 | Y43: =IF(AND(AND(INDEX(BE_Tasks!$P$2:$P$53,MATCH("BE-C05",BE_Tasks!$A$2:$A$53,0))="Hoàn thành",INDEX(BE_Tasks!$Z$2:$Z$53,MATCH("BE-C05",BE_Tasks!$A$2:$A$53,0))="")),"Đủ điều kiện","Chờ phụ thuộc") -> Chờ phụ thuộc | Z43: =IF(AND(P43="Hoàn thành",OR(X43<1,Y43<>"Đủ điều kiện",AND(AE43="",AD43=""))),"Thiếu bước / phụ thuộc / bằng chứng","") | AG43: Mở task
A44: BE-C07 | B44: P4 | C44: 7 | D44: C | E44: A | F44: Vào ở từng người, hủy dự kiến và hủy trước ở | G44: 5 | H44: 3 | I44: API-110, API-111, API-112 | J44: backend/src/modules/rentals/** backend/tests/rentals/** backend/tests/fixtures/C/** backend/tests/contracts/C/** backend/tests/e2e/rental-*/** backend/contracts/rentals.* database/source/workflows.sql database/source/contract-viewing-cleanup.sql backend/tests/sql-rental/** | K44: BE-C06 | N44: Lần đầu có đại diện; đúng ngày VN/contract/revision/quyền nhà; một ACTIVE/account toàn hệ thống. Hủy member chỉ PLANNED và không hủy riêng đại diện; hủy contract trước ACTIVE. Publish snapshot/metrics mới, không tạo invoice hoặc sửa roommate profile thay A/B. | O44: Confirm contract không tự move-in; date tương lai/ngoài kỳ bị chặn. Load phòng không đếm trùng, hủy không giả ngày vào/ra. | P44: Chưa làm | Q44: Chưa | R44: Chưa | S44: Chưa | T44: Chưa | U44: Chưa | V44: Chưa | W44: Chưa | X44: =COUNTIF(Q44:W44,"Xong")/7 -> 0 | Y44: =IF(AND(AND(INDEX(BE_Tasks!$P$2:$P$53,MATCH("BE-C06",BE_Tasks!$A$2:$A$53,0))="Hoàn thành",INDEX(BE_Tasks!$Z$2:$Z$53,MATCH("BE-C06",BE_Tasks!$A$2:$A$53,0))="")),"Đủ điều kiện","Chờ phụ thuộc") -> Chờ phụ thuộc | Z44: =IF(AND(P44="Hoàn thành",OR(X44<1,Y44<>"Đủ điều kiện",AND(AE44="",AD44=""))),"Thiếu bước / phụ thuộc / bằng chứng","") | AG44: Mở task
A45: BE-C08 | B45: P4 | C45: 8 | D45: C | E45: A | F45: Liên kết cư dân với tài khoản bằng token | G45: 5 | H45: 2 | I45: API-027, API-028 | J45: backend/src/modules/rentals/** backend/tests/rentals/** backend/tests/fixtures/C/** backend/tests/contracts/C/** backend/tests/e2e/rental-*/** backend/contracts/rentals.* | K45: BE-C07, BE-A07 | M45: D06 | N45: Chủ mời member đúng contract chưa có tenant; OCCUPANT_LINK gắn target room_tenant. Tiêu thụ token và gắn account trong UoW của C, gọi A token adapter bằng cùng connection. Chốt D06 kênh/đối chiếu người nhận; không gắn tài khoản theo tên tự khai. | O45: User đang ACTIVE nơi khác không được gắn thêm ACTIVE; token dùng lại/hết hạn thất bại. Rollback gắn member cũng rollback consume, không mất token sau lỗi. | P45: Chưa làm | Q45: Chưa | R45: Chưa | S45: Chưa | T45: Chưa | U45: Chưa | V45: Chưa | W45: Chưa | X45: =COUNTIF(Q45:W45,"Xong")/7 -> 0 | Y45: =IF(AND(AND(INDEX(BE_Tasks!$P$2:$P$53,MATCH("BE-C07",BE_Tasks!$A$2:$A$53,0))="Hoàn thành",INDEX(BE_Tasks!$Z$2:$Z$53,MATCH("BE-C07",BE_Tasks!$A$2:$A$53,0))=""),AND(INDEX(BE_Tasks!$P$2:$P$53,MATCH("BE-A07",BE_Tasks!$A$2:$A$53,0))="Hoàn thành",INDEX(BE_Tasks!$Z$2:$Z$53,MATCH("BE-A07",BE_Tasks!$A$2:$A$53,0))="")),"Đủ điều kiện","Chờ phụ thuộc") -> Chờ phụ thuộc | Z45: =IF(AND(P45="Hoàn thành",OR(X45<1,Y45<>"Đủ điều kiện",AND(AE45="",AD45=""))),"Thiếu bước / phụ thuộc / bằng chứng","") | AG45: Mở task
A46: BE-C09 | B46: P4 | C46: 9 | D46: C | E46: A | F46: Yêu cầu thêm người và hai consent riêng | G46: 5 | H46: 4 | I46: API-117, API-118, API-119, API-120 | J46: backend/src/modules/rentals/** backend/tests/rentals/** backend/tests/fixtures/C/** backend/tests/contracts/C/** backend/tests/e2e/rental-*/** backend/contracts/rentals.* | K46: BE-C07 | N46: Đại diện hiện tại tạo request, applicant khác requester, một yêu cầu mở. Mỗi bên tự consent theo actor; đủ hai mới PENDING_LANDLORD, bản cũ sau handover không tái dùng. Cancel đúng vai trò/trạng thái, snapshot representative/revision hợp lệ. | O46: Không copy ACCEPTED của roommate_request làm consent; không giả người đồng ý trong body. Hợp đồng/đại diện không còn ACTIVE thì không gửi/duyệt tiếp. | P46: Chưa làm | Q46: Chưa | R46: Chưa | S46: Chưa | T46: Chưa | U46: Chưa | V46: Chưa | W46: Chưa | X46: =COUNTIF(Q46:W46,"Xong")/7 -> 0 | Y46: =IF(AND(AND(INDEX(BE_Tasks!$P$2:$P$53,MATCH("BE-C07",BE_Tasks!$A$2:$A$53,0))="Hoàn thành",INDEX(BE_Tasks!$Z$2:$Z$53,MATCH("BE-C07",BE_Tasks!$A$2:$A$53,0))="")),"Đủ điều kiện","Chờ phụ thuộc") -> Chờ phụ thuộc | Z46: =IF(AND(P46="Hoàn thành",OR(X46<1,Y46<>"Đủ điều kiện",AND(AE46="",AD46=""))),"Thiếu bước / phụ thuộc / bằng chứng","") | AG46: Mở task
A47: BE-C10 | B47: P5 | C47: 10 | D47: C | E47: A | F47: Duyệt giữ chỗ 48 giờ và hoàn tất thêm người | G47: 8 | H47: 4 | I47: API-121, API-122, API-123, API-124 | J47: backend/src/modules/rentals/** backend/tests/rentals/** backend/tests/fixtures/C/** backend/tests/contracts/C/** backend/tests/e2e/rental-*/** backend/contracts/rentals.* database/source/workflows.sql database/source/contract-viewing-cleanup.sql backend/tests/sql-rental/** | K47: BE-C09 | N47: Approve/reject/cancel hold theo quyền và consent; 48 giờ theo chính sách đã có. Complete recheck hold/time/account/capacity, tạo member ACTIVE và liên kết hai chiều đúng FK. Retry đã completed trả kết quả cũ qua idempotency, không gọi lại procedure tạo thêm member. | O47: Hai người tranh chỗ cuối chỉ một approve; hold quá hạn không tính tải dù job chưa chạy. Complete fail không để member mồ côi/hold đã consume. | P47: Chưa làm | Q47: Chưa | R47: Chưa | S47: Chưa | T47: Chưa | U47: Chưa | V47: Chưa | W47: Chưa | X47: =COUNTIF(Q47:W47,"Xong")/7 -> 0 | Y47: =IF(AND(AND(INDEX(BE_Tasks!$P$2:$P$53,MATCH("BE-C09",BE_Tasks!$A$2:$A$53,0))="Hoàn thành",INDEX(BE_Tasks!$Z$2:$Z$53,MATCH("BE-C09",BE_Tasks!$A$2:$A$53,0))="")),"Đủ điều kiện","Chờ phụ thuộc") -> Chờ phụ thuộc | Z47: =IF(AND(P47="Hoàn thành",OR(X47<1,Y47<>"Đủ điều kiện",AND(AE47="",AD47=""))),"Thiếu bước / phụ thuộc / bằng chứng","") | AG47: Mở task
A48: BE-C11 | B48: P5 | C48: 11 | D48: C | E48: A | F48: Rời phòng và bàn giao đại diện | G48: 5 | H48: 2 | I48: API-125, API-128 | J48: backend/src/modules/rentals/** backend/tests/rentals/** backend/tests/fixtures/C/** backend/tests/contracts/C/** backend/tests/e2e/rental-*/** backend/contracts/rentals.* database/source/workflows.sql database/source/contract-viewing-cleanup.sql backend/tests/sql-rental/** | K48: BE-C10 | L48: BE-A13 | N48: Chọn successor ACTIVE cùng contract có account ACTIVE; consent landlord recorded, reason bắt buộc. Đóng history, LEFT người cũ, đại diện mới, hủy request cũ, notify cùng giao dịch. Người cuối rời xử lý mọi member mở; không đổi payer invoice cũ, viewing gốc hoặc terms cũ. | O48: QA07 giữ nguyên giá/cọc/thời hạn/contract; không chọn planned/left/locked. Nhà hết quyền vẫn rời/kết thúc được; thiếu chứng cứ không tự đoán ngày. | P48: Chưa làm | Q48: Chưa | R48: Chưa | S48: Chưa | T48: Chưa | U48: Chưa | V48: Chưa | W48: Chưa | X48: =COUNTIF(Q48:W48,"Xong")/7 -> 0 | Y48: =IF(AND(AND(INDEX(BE_Tasks!$P$2:$P$53,MATCH("BE-C10",BE_Tasks!$A$2:$A$53,0))="Hoàn thành",INDEX(BE_Tasks!$Z$2:$Z$53,MATCH("BE-C10",BE_Tasks!$A$2:$A$53,0))=""),AND(INDEX(BE_Tasks!$P$2:$P$53,MATCH("BE-A13",BE_Tasks!$A$2:$A$53,0))="Hoàn thành",INDEX(BE_Tasks!$Z$2:$Z$53,MATCH("BE-A13",BE_Tasks!$A$2:$A$53,0))="")),"Đủ điều kiện","Chờ phụ thuộc") -> Chờ phụ thuộc | Z48: =IF(AND(P48="Hoàn thành",OR(X48<1,Y48<>"Đủ điều kiện",AND(AE48="",AD48=""))),"Thiếu bước / phụ thuộc / bằng chứng","") | AG48: Mở task
A49: BE-C12 | B49: P5 | C49: 12 | D49: C | E49: A | F49: Gia hạn, đổi phòng và chấm dứt có xác nhận | G49: 8 | H49: 8 | I49: API-129, API-130, API-131, API-132, API-133, API-134, API-135, API-136 | J49: backend/src/modules/rentals/** backend/tests/rentals/** backend/tests/fixtures/C/** backend/tests/contracts/C/** backend/tests/e2e/rental-*/** backend/contracts/rentals.* database/source/workflows.sql database/source/contract-viewing-cleanup.sql backend/tests/sql-rental/** | K49: BE-C11, BE-B04 | N49: Một yêu cầu mở; baseRevision/current representative/proposal bất biến và effective date. Renewal có proposed revision confirmed và quyền nhà; transfer lock room theo ID, kiểm tra mọi điều kiện trước đóng nguồn. Termination đóng ACTIVE, hủy PLANNED, history/yêu cầu, không xóa invoice; chuyển phòng đích tạo PLANNED chờ vào thực tế. | O49: QA08 lỗi đích rollback nguồn; chuyển đủ ACTIVE+PLANNED, không chỉ đại diện. Gửi/approve/confirm chưa đổi contract; apply stale/hết quyền/đến ngày sai bị chặn. | P49: Chưa làm | Q49: Chưa | R49: Chưa | S49: Chưa | T49: Chưa | U49: Chưa | V49: Chưa | W49: Chưa | X49: =COUNTIF(Q49:W49,"Xong")/7 -> 0 | Y49: =IF(AND(AND(INDEX(BE_Tasks!$P$2:$P$53,MATCH("BE-C11",BE_Tasks!$A$2:$A$53,0))="Hoàn thành",INDEX(BE_Tasks!$Z$2:$Z$53,MATCH("BE-C11",BE_Tasks!$A$2:$A$53,0))=""),AND(INDEX(BE_Tasks!$P$2:$P$53,MATCH("BE-B04",BE_Tasks!$A$2:$A$53,0))="Hoàn thành",INDEX(BE_Tasks!$Z$2:$Z$53,MATCH("BE-B04",BE_Tasks!$A$2:$A$53,0))="")),"Đủ điều kiện","Chờ phụ thuộc") -> Chờ phụ thuộc | Z49: =IF(AND(P49="Hoàn thành",OR(X49<1,Y49<>"Đủ điều kiện",AND(AE49="",AD49=""))),"Thiếu bước / phụ thuộc / bằng chứng","") | AG49: Mở task
A50: BE-C13 | B50: P6 | C50: 13 | D50: C | E50: A | F50: Nhập hợp đồng giấy có phân quyền riêng | G50: 8 | H50: 1 | I50: API-113 | J50: backend/src/modules/rentals/** backend/tests/rentals/** backend/tests/fixtures/C/** backend/tests/contracts/C/** backend/tests/e2e/rental-*/** backend/contracts/rentals.* database/source/workflows.sql database/source/contract-viewing-cleanup.sql backend/tests/sql-rental/** | K50: BE-C12, BE-A05 | M50: D11 | N50: Chốt JSON members/state/date, chứng cứ đã ký, quyền import riêng và policy dữ liệu lịch sử. Tạo contract/revision IMPORTED/member/history đúng FK và capacity, không giả tenant confirmation. Không dùng source PAPER_IMPORT trên thuê mới để né quy trình quyền nhà/lịch xem. | O50: Không có quyền/tệp/identity mapping hợp lệ thì không nhập nửa chừng. Không điền ngày nhận đại diện/ngày rời bằng suy đoán. | P50: Chưa làm | Q50: Chưa | R50: Chưa | S50: Chưa | T50: Chưa | U50: Chưa | V50: Chưa | W50: Chưa | X50: =COUNTIF(Q50:W50,"Xong")/7 -> 0 | Y50: =IF(AND(AND(INDEX(BE_Tasks!$P$2:$P$53,MATCH("BE-C12",BE_Tasks!$A$2:$A$53,0))="Hoàn thành",INDEX(BE_Tasks!$Z$2:$Z$53,MATCH("BE-C12",BE_Tasks!$A$2:$A$53,0))=""),AND(INDEX(BE_Tasks!$P$2:$P$53,MATCH("BE-A05",BE_Tasks!$A$2:$A$53,0))="Hoàn thành",INDEX(BE_Tasks!$Z$2:$Z$53,MATCH("BE-A05",BE_Tasks!$A$2:$A$53,0))="")),"Đủ điều kiện","Chờ phụ thuộc") -> Chờ phụ thuộc | Z50: =IF(AND(P50="Hoàn thành",OR(X50<1,Y50<>"Đủ điều kiện",AND(AE50="",AD50=""))),"Thiếu bước / phụ thuộc / bằng chứng","") | AG50: Mở task
A51: BE-C14 | B51: P6 | C51: 14 | D51: C | E51: A | F51: Worker thuê, hết hold và đối soát cư trú | G51: 3 | H51: 0 | J51: backend/src/modules/rentals/** backend/tests/rentals/** backend/tests/fixtures/C/** backend/tests/contracts/C/** backend/tests/e2e/rental-*/** backend/contracts/rentals.* database/source/workflows.sql database/source/contract-viewing-cleanup.sql backend/tests/sql-rental/** | K51: BE-C12 | N51: JOB01 expire proposal gọi thủ tục B sở hữu; thay thuật toán lịch thì gửi B. JOB02 hold hết hạn; OPS02 báo ACTIVE trên contract đóng; OPS03 chốt quy trình hết hạn lease. Không tự cho người ở LEFT hoặc đóng lease vì chỉ đến end_date; dữ liệu mâu thuẫn cần đối soát. | O51: Job lặp không tạo side effects mới; read/write vẫn recheck now khi worker trễ. Hợp đồng cũ, lịch sử và nghĩa vụ hóa đơn được giữ. | P51: Chưa làm | Q51: Chưa | R51: Chưa | S51: Chưa | T51: Chưa | U51: Chưa | V51: Chưa | W51: Chưa | X51: =COUNTIF(Q51:W51,"Xong")/7 -> 0 | Y51: =IF(AND(AND(INDEX(BE_Tasks!$P$2:$P$53,MATCH("BE-C12",BE_Tasks!$A$2:$A$53,0))="Hoàn thành",INDEX(BE_Tasks!$Z$2:$Z$53,MATCH("BE-C12",BE_Tasks!$A$2:$A$53,0))="")),"Đủ điều kiện","Chờ phụ thuộc") -> Chờ phụ thuộc | Z51: =IF(AND(P51="Hoàn thành",OR(X51<1,Y51<>"Đủ điều kiện",AND(AE51="",AD51=""))),"Thiếu bước / phụ thuộc / bằng chứng","") | AG51: Mở task
A52: BE-C15 | B52: P7 | C52: 15 | D52: C | E52: A | F52: Kiểm thử race/rollback toàn bộ giao dịch thuê | G52: 5 | H52: 0 | J52: backend/src/modules/rentals/** backend/tests/rentals/** backend/tests/fixtures/C/** backend/tests/contracts/C/** backend/tests/e2e/rental-*/** backend/contracts/rentals.* database/source/workflows.sql database/source/contract-viewing-cleanup.sql backend/tests/sql-rental/** | K52: BE-C13, BE-C14, BE-B10 | N52: QA03/05/06/07/08/09 chạy hai connection và fault injection trong transaction. Kiểm tra lock order, OUT ID, FK ghép, snapshot và notification không ghi nửa chừng. Đọc lại lịch sử/account scope sau handover, termination, transfer; lưu bằng chứng DB tạm. | O52: Một phòng một open contract; một account một ACTIVE; không vượt capacity. Main SQL sinh ra và feature adapter cùng chữ ký procedure mới. | P52: Chưa làm | Q52: Chưa | R52: Chưa | S52: Chưa | T52: Chưa | U52: Chưa | V52: Chưa | W52: Chưa | X52: =COUNTIF(Q52:W52,"Xong")/7 -> 0 | Y52: =IF(AND(AND(INDEX(BE_Tasks!$P$2:$P$53,MATCH("BE-C13",BE_Tasks!$A$2:$A$53,0))="Hoàn thành",INDEX(BE_Tasks!$Z$2:$Z$53,MATCH("BE-C13",BE_Tasks!$A$2:$A$53,0))=""),AND(INDEX(BE_Tasks!$P$2:$P$53,MATCH("BE-C14",BE_Tasks!$A$2:$A$53,0))="Hoàn thành",INDEX(BE_Tasks!$Z$2:$Z$53,MATCH("BE-C14",BE_Tasks!$A$2:$A$53,0))=""),AND(INDEX(BE_Tasks!$P$2:$P$53,MATCH("BE-B10",BE_Tasks!$A$2:$A$53,0))="Hoàn thành",INDEX(BE_Tasks!$Z$2:$Z$53,MATCH("BE-B10",BE_Tasks!$A$2:$A$53,0))="")),"Đủ điều kiện","Chờ phụ thuộc") -> Chờ phụ thuộc | Z52: =IF(AND(P52="Hoàn thành",OR(X52<1,Y52<>"Đủ điều kiện",AND(AE52="",AD52=""))),"Thiếu bước / phụ thuộc / bằng chứng","") | AG52: Mở task
A53: BE-C16 | B53: P7 | C53: 16 | D53: C | E53: A | F53: E2E thuê xuyên ba module và bàn giao API | G53: 3 | H53: 0 | J53: backend/src/modules/rentals/** backend/tests/rentals/** backend/tests/fixtures/C/** backend/tests/contracts/C/** backend/tests/e2e/rental-*/** backend/contracts/rentals.* | K53: BE-C15, BE-A16, BE-B19 | N53: Auth → upload → nhà/quyền → post → chat → viewing → contract → confirm/move-in → invoice → handover/transfer/terminate. Đối chiếu API coverage/task owner và collection request; báo lỗi về đúng người, không sửa chéo file. Nộp report G7, các limit ngoài phạm vi và dữ liệu reset/test cho A17. | O53: Không còn stub tại production composition root; toàn bộ API được kế hoạch đánh dấu đạt có test thật. D11/D02 và các điểm chưa chốt không bị tự đánh dấu hoàn thành vì có fixture. | P53: Chưa làm | Q53: Chưa | R53: Chưa | S53: Chưa | T53: Chưa | U53: Chưa | V53: Chưa | W53: Chưa | X53: =COUNTIF(Q53:W53,"Xong")/7 -> 0 | Y53: =IF(AND(AND(INDEX(BE_Tasks!$P$2:$P$53,MATCH("BE-C15",BE_Tasks!$A$2:$A$53,0))="Hoàn thành",INDEX(BE_Tasks!$Z$2:$Z$53,MATCH("BE-C15",BE_Tasks!$A$2:$A$53,0))=""),AND(INDEX(BE_Tasks!$P$2:$P$53,MATCH("BE-A16",BE_Tasks!$A$2:$A$53,0))="Hoàn thành",INDEX(BE_Tasks!$Z$2:$Z$53,MATCH("BE-A16",BE_Tasks!$A$2:$A$53,0))=""),AND(INDEX(BE_Tasks!$P$2:$P$53,MATCH("BE-B19",BE_Tasks!$A$2:$A$53,0))="Hoàn thành",INDEX(BE_Tasks!$Z$2:$Z$53,MATCH("BE-B19",BE_Tasks!$A$2:$A$53,0))="")),"Đủ điều kiện","Chờ phụ thuộc") -> Chờ phụ thuộc | Z53: =IF(AND(P53="Hoàn thành",OR(X53<1,Y53<>"Đủ điều kiện",AND(AE53="",AD53=""))),"Thiếu bước / phụ thuộc / bằng chứng","") | AG53: Mở task

Sheet API_176
A1: API ID | B1: Method | C1: Endpoint | D1: Chức năng | E1: Owner | F1: Task | G1: Mốc | H1: Luồng | I1: Trạng thái task | J1: Tiến độ task | K1: Quyết định | L1: Đặc tả API | M1: Phân công
A2: API-001 | B2: POST | C2: /api/v1/auth/register | D2: Đăng ký tài khoản người thuê | E2: A | F2: BE-A03 | G2: P1 | H2: account-access | I2: =INDEX(BE_Tasks!$P$2:$P$53,MATCH("BE-A03",BE_Tasks!$A$2:$A$53,0)) -> Chưa làm | J2: =INDEX(BE_Tasks!$X$2:$X$53,MATCH("BE-A03",BE_Tasks!$A$2:$A$53,0)) -> 0 | L2: Mở API | M2: Mở task
A3: API-002 | B3: POST | C3: /api/v1/auth/login | D3: Đăng nhập và mở phiên | E3: A | F3: BE-A03 | G3: P1 | H3: account-access | I3: =INDEX(BE_Tasks!$P$2:$P$53,MATCH("BE-A03",BE_Tasks!$A$2:$A$53,0)) -> Chưa làm | J3: =INDEX(BE_Tasks!$X$2:$X$53,MATCH("BE-A03",BE_Tasks!$A$2:$A$53,0)) -> 0 | L3: Mở API | M3: Mở task
A4: API-003 | B4: GET | C4: /api/v1/me | D4: Đọc tài khoản và các vai trò thực | E4: A | F4: BE-A03 | G4: P1 | H4: account-access | I4: =INDEX(BE_Tasks!$P$2:$P$53,MATCH("BE-A03",BE_Tasks!$A$2:$A$53,0)) -> Chưa làm | J4: =INDEX(BE_Tasks!$X$2:$X$53,MATCH("BE-A03",BE_Tasks!$A$2:$A$53,0)) -> 0 | L4: Mở API | M4: Mở task
A5: API-004 | B5: PATCH | C5: /api/v1/me/profile | D5: Cập nhật hồ sơ cá nhân | E5: A | F5: BE-A03 | G5: P1 | H5: profile | I5: =INDEX(BE_Tasks!$P$2:$P$53,MATCH("BE-A03",BE_Tasks!$A$2:$A$53,0)) -> Chưa làm | J5: =INDEX(BE_Tasks!$X$2:$X$53,MATCH("BE-A03",BE_Tasks!$A$2:$A$53,0)) -> 0 | L5: Mở API | M5: Mở task
A6: API-005 | B6: PATCH | C6: /api/v1/me/notification-settings | D6: Cấu hình kênh thông báo | E6: A | F6: BE-A03 | G6: P1 | H6: profile | I6: =INDEX(BE_Tasks!$P$2:$P$53,MATCH("BE-A03",BE_Tasks!$A$2:$A$53,0)) -> Chưa làm | J6: =INDEX(BE_Tasks!$X$2:$X$53,MATCH("BE-A03",BE_Tasks!$A$2:$A$53,0)) -> 0 | K6: D04 | L6: Mở API | M6: Mở task
A7: API-006 | B7: POST | C7: /api/v1/me/identity-verifications | D7: Nộp xác minh danh tính người thuê | E7: A | F7: BE-A06 | G7: P2 | H7: identity | I7: =INDEX(BE_Tasks!$P$2:$P$53,MATCH("BE-A06",BE_Tasks!$A$2:$A$53,0)) -> Chưa làm | J7: =INDEX(BE_Tasks!$X$2:$X$53,MATCH("BE-A06",BE_Tasks!$A$2:$A$53,0)) -> 0 | K7: D05 | L7: Mở API | M7: Mở task
A8: API-007 | B8: GET | C8: /api/v1/me/identity-verifications | D8: Lịch sử xác minh của mình | E8: A | F8: BE-A06 | G8: P2 | H8: identity | I8: =INDEX(BE_Tasks!$P$2:$P$53,MATCH("BE-A06",BE_Tasks!$A$2:$A$53,0)) -> Chưa làm | J8: =INDEX(BE_Tasks!$X$2:$X$53,MATCH("BE-A06",BE_Tasks!$A$2:$A$53,0)) -> 0 | L8: Mở API | M8: Mở task
A9: API-008 | B9: POST | C9: /api/v1/me/identity-verifications/{verificationId}/withdraw | D9: Rút hồ sơ danh tính đang chờ | E9: A | F9: BE-A06 | G9: P2 | H9: identity | I9: =INDEX(BE_Tasks!$P$2:$P$53,MATCH("BE-A06",BE_Tasks!$A$2:$A$53,0)) -> Chưa làm | J9: =INDEX(BE_Tasks!$X$2:$X$53,MATCH("BE-A06",BE_Tasks!$A$2:$A$53,0)) -> 0 | L9: Mở API | M9: Mở task
A10: API-009 | B10: POST | C10: /api/v1/me/landlord-verifications | D10: Xin cấp vai trò chủ trọ | E10: A | F10: BE-A06 | G10: P2 | H10: identity | I10: =INDEX(BE_Tasks!$P$2:$P$53,MATCH("BE-A06",BE_Tasks!$A$2:$A$53,0)) -> Chưa làm | J10: =INDEX(BE_Tasks!$X$2:$X$53,MATCH("BE-A06",BE_Tasks!$A$2:$A$53,0)) -> 0 | L10: Mở API | M10: Mở task
A11: API-010 | B11: GET | C11: /api/v1/me/landlord-verifications | D11: Lịch sử hồ sơ xin làm chủ trọ | E11: A | F11: BE-A06 | G11: P2 | H11: identity | I11: =INDEX(BE_Tasks!$P$2:$P$53,MATCH("BE-A06",BE_Tasks!$A$2:$A$53,0)) -> Chưa làm | J11: =INDEX(BE_Tasks!$X$2:$X$53,MATCH("BE-A06",BE_Tasks!$A$2:$A$53,0)) -> 0 | L11: Mở API | M11: Mở task
A12: API-011 | B12: POST | C12: /api/v1/me/landlord-verifications/{verificationId}/withdraw | D12: Rút hồ sơ chủ trọ đang chờ | E12: A | F12: BE-A06 | G12: P2 | H12: identity | I12: =INDEX(BE_Tasks!$P$2:$P$53,MATCH("BE-A06",BE_Tasks!$A$2:$A$53,0)) -> Chưa làm | J12: =INDEX(BE_Tasks!$X$2:$X$53,MATCH("BE-A06",BE_Tasks!$A$2:$A$53,0)) -> 0 | L12: Mở API | M12: Mở task
A13: API-012 | B13: GET | C13: /api/v1/admin/identity-verifications | D13: Danh sách hồ sơ identity | E13: A | F13: BE-A06 | G13: P2 | H13: identity | I13: =INDEX(BE_Tasks!$P$2:$P$53,MATCH("BE-A06",BE_Tasks!$A$2:$A$53,0)) -> Chưa làm | J13: =INDEX(BE_Tasks!$X$2:$X$53,MATCH("BE-A06",BE_Tasks!$A$2:$A$53,0)) -> 0 | L13: Mở API | M13: Mở task
A14: API-013 | B14: GET | C14: /api/v1/admin/identity-verifications/{verificationId} | D14: Chi tiết hồ sơ identity | E14: A | F14: BE-A06 | G14: P2 | H14: identity | I14: =INDEX(BE_Tasks!$P$2:$P$53,MATCH("BE-A06",BE_Tasks!$A$2:$A$53,0)) -> Chưa làm | J14: =INDEX(BE_Tasks!$X$2:$X$53,MATCH("BE-A06",BE_Tasks!$A$2:$A$53,0)) -> 0 | L14: Mở API | M14: Mở task
A15: API-014 | B15: POST | C15: /api/v1/admin/identity-verifications/{verificationId}/decision | D15: Duyệt hoặc từ chối hồ sơ identity | E15: A | F15: BE-A06 | G15: P2 | H15: identity | I15: =INDEX(BE_Tasks!$P$2:$P$53,MATCH("BE-A06",BE_Tasks!$A$2:$A$53,0)) -> Chưa làm | J15: =INDEX(BE_Tasks!$X$2:$X$53,MATCH("BE-A06",BE_Tasks!$A$2:$A$53,0)) -> 0 | L15: Mở API | M15: Mở task
A16: API-015 | B16: GET | C16: /api/v1/admin/landlord-verifications | D16: Danh sách hồ sơ landlord | E16: A | F16: BE-A06 | G16: P2 | H16: identity | I16: =INDEX(BE_Tasks!$P$2:$P$53,MATCH("BE-A06",BE_Tasks!$A$2:$A$53,0)) -> Chưa làm | J16: =INDEX(BE_Tasks!$X$2:$X$53,MATCH("BE-A06",BE_Tasks!$A$2:$A$53,0)) -> 0 | L16: Mở API | M16: Mở task
A17: API-016 | B17: GET | C17: /api/v1/admin/landlord-verifications/{verificationId} | D17: Chi tiết hồ sơ landlord | E17: A | F17: BE-A06 | G17: P2 | H17: identity | I17: =INDEX(BE_Tasks!$P$2:$P$53,MATCH("BE-A06",BE_Tasks!$A$2:$A$53,0)) -> Chưa làm | J17: =INDEX(BE_Tasks!$X$2:$X$53,MATCH("BE-A06",BE_Tasks!$A$2:$A$53,0)) -> 0 | L17: Mở API | M17: Mở task
A18: API-017 | B18: POST | C18: /api/v1/admin/landlord-verifications/{verificationId}/decision | D18: Duyệt hoặc từ chối hồ sơ landlord | E18: A | F18: BE-A06 | G18: P2 | H18: identity | I18: =INDEX(BE_Tasks!$P$2:$P$53,MATCH("BE-A06",BE_Tasks!$A$2:$A$53,0)) -> Chưa làm | J18: =INDEX(BE_Tasks!$X$2:$X$53,MATCH("BE-A06",BE_Tasks!$A$2:$A$53,0)) -> 0 | L18: Mở API | M18: Mở task
A19: API-018 | B19: POST | C19: /api/v1/auth/refresh | D19: Luân chuyển refresh token | E19: A | F19: BE-A03 | G19: P1 | H19: sessions | I19: =INDEX(BE_Tasks!$P$2:$P$53,MATCH("BE-A03",BE_Tasks!$A$2:$A$53,0)) -> Chưa làm | J19: =INDEX(BE_Tasks!$X$2:$X$53,MATCH("BE-A03",BE_Tasks!$A$2:$A$53,0)) -> 0 | L19: Mở API | M19: Mở task
A20: API-019 | B20: POST | C20: /api/v1/auth/logout | D20: Đăng xuất phiên hiện tại | E20: A | F20: BE-A03 | G20: P1 | H20: sessions | I20: =INDEX(BE_Tasks!$P$2:$P$53,MATCH("BE-A03",BE_Tasks!$A$2:$A$53,0)) -> Chưa làm | J20: =INDEX(BE_Tasks!$X$2:$X$53,MATCH("BE-A03",BE_Tasks!$A$2:$A$53,0)) -> 0 | L20: Mở API | M20: Mở task
A21: API-020 | B21: GET | C21: /api/v1/me/sessions | D21: Danh sách phiên của mình | E21: A | F21: BE-A03 | G21: P1 | H21: sessions | I21: =INDEX(BE_Tasks!$P$2:$P$53,MATCH("BE-A03",BE_Tasks!$A$2:$A$53,0)) -> Chưa làm | J21: =INDEX(BE_Tasks!$X$2:$X$53,MATCH("BE-A03",BE_Tasks!$A$2:$A$53,0)) -> 0 | L21: Mở API | M21: Mở task
A22: API-021 | B22: DELETE | C22: /api/v1/me/sessions/{sessionId} | D22: Thu hồi một phiên | E22: A | F22: BE-A03 | G22: P1 | H22: sessions | I22: =INDEX(BE_Tasks!$P$2:$P$53,MATCH("BE-A03",BE_Tasks!$A$2:$A$53,0)) -> Chưa làm | J22: =INDEX(BE_Tasks!$X$2:$X$53,MATCH("BE-A03",BE_Tasks!$A$2:$A$53,0)) -> 0 | L22: Mở API | M22: Mở task
A23: API-022 | B23: POST | C23: /api/v1/auth/phone-verifications | D23: Gửi OTP xác minh điện thoại | E23: A | F23: BE-A07 | G23: P2 | H23: sessions | I23: =INDEX(BE_Tasks!$P$2:$P$53,MATCH("BE-A07",BE_Tasks!$A$2:$A$53,0)) -> Chưa làm | J23: =INDEX(BE_Tasks!$X$2:$X$53,MATCH("BE-A07",BE_Tasks!$A$2:$A$53,0)) -> 0 | K23: D01 | L23: Mở API | M23: Mở task
A24: API-023 | B24: POST | C24: /api/v1/auth/phone-verifications/confirm | D24: Xác nhận OTP điện thoại | E24: A | F24: BE-A07 | G24: P2 | H24: sessions | I24: =INDEX(BE_Tasks!$P$2:$P$53,MATCH("BE-A07",BE_Tasks!$A$2:$A$53,0)) -> Chưa làm | J24: =INDEX(BE_Tasks!$X$2:$X$53,MATCH("BE-A07",BE_Tasks!$A$2:$A$53,0)) -> 0 | L24: Mở API | M24: Mở task
A25: API-024 | B25: POST | C25: /api/v1/auth/password-resets | D25: Yêu cầu đặt lại mật khẩu | E25: A | F25: BE-A07 | G25: P2 | H25: sessions | I25: =INDEX(BE_Tasks!$P$2:$P$53,MATCH("BE-A07",BE_Tasks!$A$2:$A$53,0)) -> Chưa làm | J25: =INDEX(BE_Tasks!$X$2:$X$53,MATCH("BE-A07",BE_Tasks!$A$2:$A$53,0)) -> 0 | K25: D01 | L25: Mở API | M25: Mở task
A26: API-025 | B26: POST | C26: /api/v1/auth/password-resets/verify | D26: Đổi OTP hợp lệ lấy quyền reset ngắn hạn | E26: A | F26: BE-A07 | G26: P2 | H26: sessions | I26: =INDEX(BE_Tasks!$P$2:$P$53,MATCH("BE-A07",BE_Tasks!$A$2:$A$53,0)) -> Chưa làm | J26: =INDEX(BE_Tasks!$X$2:$X$53,MATCH("BE-A07",BE_Tasks!$A$2:$A$53,0)) -> 0 | L26: Mở API | M26: Mở task
A27: API-026 | B27: POST | C27: /api/v1/auth/password-resets/complete | D27: Đặt mật khẩu mới | E27: A | F27: BE-A07 | G27: P2 | H27: sessions | I27: =INDEX(BE_Tasks!$P$2:$P$53,MATCH("BE-A07",BE_Tasks!$A$2:$A$53,0)) -> Chưa làm | J27: =INDEX(BE_Tasks!$X$2:$X$53,MATCH("BE-A07",BE_Tasks!$A$2:$A$53,0)) -> 0 | L27: Mở API | M27: Mở task
A28: API-027 | B28: POST | C28: /api/v1/contracts/{contractId}/members/{memberId}/account-invitations | D28: Mời cư dân chưa có tài khoản liên kết | E28: C | F28: BE-C08 | G28: P4 | H28: sessions | I28: =INDEX(BE_Tasks!$P$2:$P$53,MATCH("BE-C08",BE_Tasks!$A$2:$A$53,0)) -> Chưa làm | J28: =INDEX(BE_Tasks!$X$2:$X$53,MATCH("BE-C08",BE_Tasks!$A$2:$A$53,0)) -> 0 | K28: D06 | L28: Mở API | M28: Mở task
A29: API-028 | B29: POST | C29: /api/v1/me/residency-links | D29: Nhận liên kết tài khoản với lượt cư trú | E29: C | F29: BE-C08 | G29: P4 | H29: sessions | I29: =INDEX(BE_Tasks!$P$2:$P$53,MATCH("BE-C08",BE_Tasks!$A$2:$A$53,0)) -> Chưa làm | J29: =INDEX(BE_Tasks!$X$2:$X$53,MATCH("BE-C08",BE_Tasks!$A$2:$A$53,0)) -> 0 | K29: D06 | L29: Mở API | M29: Mở task
A30: API-029 | B30: GET | C30: /api/v1/houses | D30: Danh sách nhà thuộc chủ trọ | E30: B | F30: BE-B02 | G30: P1 | H30: create-house | I30: =INDEX(BE_Tasks!$P$2:$P$53,MATCH("BE-B02",BE_Tasks!$A$2:$A$53,0)) -> Chưa làm | J30: =INDEX(BE_Tasks!$X$2:$X$53,MATCH("BE-B02",BE_Tasks!$A$2:$A$53,0)) -> 0 | L30: Mở API | M30: Mở task
A31: API-030 | B31: POST | C31: /api/v1/houses | D31: Tạo nhà nháp | E31: B | F31: BE-B02 | G31: P1 | H31: create-house | I31: =INDEX(BE_Tasks!$P$2:$P$53,MATCH("BE-B02",BE_Tasks!$A$2:$A$53,0)) -> Chưa làm | J31: =INDEX(BE_Tasks!$X$2:$X$53,MATCH("BE-B02",BE_Tasks!$A$2:$A$53,0)) -> 0 | L31: Mở API | M31: Mở task
A32: API-031 | B32: GET | C32: /api/v1/houses/{houseId} | D32: Chi tiết nhà quản lý | E32: B | F32: BE-B02 | G32: P1 | H32: create-house | I32: =INDEX(BE_Tasks!$P$2:$P$53,MATCH("BE-B02",BE_Tasks!$A$2:$A$53,0)) -> Chưa làm | J32: =INDEX(BE_Tasks!$X$2:$X$53,MATCH("BE-B02",BE_Tasks!$A$2:$A$53,0)) -> 0 | L32: Mở API | M32: Mở task
A33: API-032 | B33: PATCH | C33: /api/v1/houses/{houseId} | D33: Sửa nhà và kiểm tra phiên bản | E33: B | F33: BE-B02 | G33: P1 | H33: create-house | I33: =INDEX(BE_Tasks!$P$2:$P$53,MATCH("BE-B02",BE_Tasks!$A$2:$A$53,0)) -> Chưa làm | J33: =INDEX(BE_Tasks!$X$2:$X$53,MATCH("BE-B02",BE_Tasks!$A$2:$A$53,0)) -> 0 | L33: Mở API | M33: Mở task
A34: API-033 | B34: GET | C34: /api/v1/houses/{houseId}/verifications | D34: Lịch sử quyền cho thuê từng nhà | E34: B | F34: BE-B05 | G34: P2 | H34: house-proof | I34: =INDEX(BE_Tasks!$P$2:$P$53,MATCH("BE-B05",BE_Tasks!$A$2:$A$53,0)) -> Chưa làm | J34: =INDEX(BE_Tasks!$X$2:$X$53,MATCH("BE-B05",BE_Tasks!$A$2:$A$53,0)) -> 0 | L34: Mở API | M34: Mở task
A35: API-034 | B35: POST | C35: /api/v1/houses/{houseId}/verifications | D35: Nộp minh chứng quyền cho thuê | E35: B | F35: BE-B05 | G35: P2 | H35: house-proof | I35: =INDEX(BE_Tasks!$P$2:$P$53,MATCH("BE-B05",BE_Tasks!$A$2:$A$53,0)) -> Chưa làm | J35: =INDEX(BE_Tasks!$X$2:$X$53,MATCH("BE-B05",BE_Tasks!$A$2:$A$53,0)) -> 0 | L35: Mở API | M35: Mở task
A36: API-035 | B36: GET | C36: /api/v1/houses/{houseId}/verifications/{verificationId} | D36: Chi tiết hồ sơ quyền nhà của mình | E36: B | F36: BE-B05 | G36: P2 | H36: house-proof | I36: =INDEX(BE_Tasks!$P$2:$P$53,MATCH("BE-B05",BE_Tasks!$A$2:$A$53,0)) -> Chưa làm | J36: =INDEX(BE_Tasks!$X$2:$X$53,MATCH("BE-B05",BE_Tasks!$A$2:$A$53,0)) -> 0 | L36: Mở API | M36: Mở task
A37: API-036 | B37: POST | C37: /api/v1/houses/{houseId}/verifications/{verificationId}/withdraw | D37: Rút hồ sơ quyền nhà đang chờ | E37: B | F37: BE-B05 | G37: P2 | H37: house-proof | I37: =INDEX(BE_Tasks!$P$2:$P$53,MATCH("BE-B05",BE_Tasks!$A$2:$A$53,0)) -> Chưa làm | J37: =INDEX(BE_Tasks!$X$2:$X$53,MATCH("BE-B05",BE_Tasks!$A$2:$A$53,0)) -> 0 | L37: Mở API | M37: Mở task
A38: API-037 | B38: GET | C38: /api/v1/admin/house-verifications | D38: Hàng đợi xác minh quyền nhà | E38: B | F38: BE-B05 | G38: P2 | H38: house-proof | I38: =INDEX(BE_Tasks!$P$2:$P$53,MATCH("BE-B05",BE_Tasks!$A$2:$A$53,0)) -> Chưa làm | J38: =INDEX(BE_Tasks!$X$2:$X$53,MATCH("BE-B05",BE_Tasks!$A$2:$A$53,0)) -> 0 | L38: Mở API | M38: Mở task
A39: API-038 | B39: GET | C39: /api/v1/admin/house-verifications/{verificationId} | D39: Chi tiết và minh chứng để đối chiếu | E39: B | F39: BE-B05 | G39: P2 | H39: house-proof | I39: =INDEX(BE_Tasks!$P$2:$P$53,MATCH("BE-B05",BE_Tasks!$A$2:$A$53,0)) -> Chưa làm | J39: =INDEX(BE_Tasks!$X$2:$X$53,MATCH("BE-B05",BE_Tasks!$A$2:$A$53,0)) -> 0 | L39: Mở API | M39: Mở task
A40: API-039 | B40: POST | C40: /api/v1/admin/house-verifications/{verificationId}/decision | D40: Duyệt/từ chối quyền cho thuê | E40: B | F40: BE-B05 | G40: P2 | H40: house-proof | I40: =INDEX(BE_Tasks!$P$2:$P$53,MATCH("BE-B05",BE_Tasks!$A$2:$A$53,0)) -> Chưa làm | J40: =INDEX(BE_Tasks!$X$2:$X$53,MATCH("BE-B05",BE_Tasks!$A$2:$A$53,0)) -> 0 | L40: Mở API | M40: Mở task
A41: API-040 | B41: POST | C41: /api/v1/admin/house-verifications/{verificationId}/revoke | D41: Thu hồi quyền đã duyệt | E41: B | F41: BE-B05 | G41: P2 | H41: house-rights-expiry | I41: =INDEX(BE_Tasks!$P$2:$P$53,MATCH("BE-B05",BE_Tasks!$A$2:$A$53,0)) -> Chưa làm | J41: =INDEX(BE_Tasks!$X$2:$X$53,MATCH("BE-B05",BE_Tasks!$A$2:$A$53,0)) -> 0 | L41: Mở API | M41: Mở task
A42: API-041 | B42: GET | C42: /api/v1/houses/{houseId}/rental-right | D42: Đọc quyền hiệu lực hiện tại | E42: B | F42: BE-B05 | G42: P2 | H42: house-rights-expiry | I42: =INDEX(BE_Tasks!$P$2:$P$53,MATCH("BE-B05",BE_Tasks!$A$2:$A$53,0)) -> Chưa làm | J42: =INDEX(BE_Tasks!$X$2:$X$53,MATCH("BE-B05",BE_Tasks!$A$2:$A$53,0)) -> 0 | L42: Mở API | M42: Mở task
A43: API-042 | B43: GET | C43: /api/v1/houses/{houseId}/rooms | D43: Danh sách phòng của nhà | E43: B | F43: BE-B02 | G43: P1 | H43: rooms | I43: =INDEX(BE_Tasks!$P$2:$P$53,MATCH("BE-B02",BE_Tasks!$A$2:$A$53,0)) -> Chưa làm | J43: =INDEX(BE_Tasks!$X$2:$X$53,MATCH("BE-B02",BE_Tasks!$A$2:$A$53,0)) -> 0 | L43: Mở API | M43: Mở task
A44: API-043 | B44: POST | C44: /api/v1/houses/{houseId}/rooms | D44: Thêm phòng trong nhà | E44: B | F44: BE-B02 | G44: P1 | H44: rooms | I44: =INDEX(BE_Tasks!$P$2:$P$53,MATCH("BE-B02",BE_Tasks!$A$2:$A$53,0)) -> Chưa làm | J44: =INDEX(BE_Tasks!$X$2:$X$53,MATCH("BE-B02",BE_Tasks!$A$2:$A$53,0)) -> 0 | L44: Mở API | M44: Mở task
A45: API-044 | B45: PATCH | C45: /api/v1/rooms/{roomId} | D45: Sửa thông tin vật lý và giá phòng | E45: B | F45: BE-B02 | G45: P1 | H45: rooms | I45: =INDEX(BE_Tasks!$P$2:$P$53,MATCH("BE-B02",BE_Tasks!$A$2:$A$53,0)) -> Chưa làm | J45: =INDEX(BE_Tasks!$X$2:$X$53,MATCH("BE-B02",BE_Tasks!$A$2:$A$53,0)) -> 0 | L45: Mở API | M45: Mở task
A46: API-045 | B46: PUT | C46: /api/v1/rooms/{roomId}/capacity | D46: Đổi sức chứa có khóa phòng | E46: B | F46: BE-B02 | G46: P1 | H46: rooms | I46: =INDEX(BE_Tasks!$P$2:$P$53,MATCH("BE-B02",BE_Tasks!$A$2:$A$53,0)) -> Chưa làm | J46: =INDEX(BE_Tasks!$X$2:$X$53,MATCH("BE-B02",BE_Tasks!$A$2:$A$53,0)) -> 0 | L46: Mở API | M46: Mở task
A47: API-046 | B47: GET | C47: /api/v1/rooms/{roomId} | D47: Chi tiết phòng theo quyền người xem | E47: B | F47: BE-B07 | G47: P2 | H47: room-detail | I47: =INDEX(BE_Tasks!$P$2:$P$53,MATCH("BE-B07",BE_Tasks!$A$2:$A$53,0)) -> Chưa làm | J47: =INDEX(BE_Tasks!$X$2:$X$53,MATCH("BE-B07",BE_Tasks!$A$2:$A$53,0)) -> 0 | L47: Mở API | M47: Mở task
A48: API-047 | B48: GET | C48: /api/v1/rooms/{roomId}/posts | D48: Bài đăng của một phòng | E48: B | F48: BE-B06 | G48: P2 | H48: room-detail | I48: =INDEX(BE_Tasks!$P$2:$P$53,MATCH("BE-B06",BE_Tasks!$A$2:$A$53,0)) -> Chưa làm | J48: =INDEX(BE_Tasks!$X$2:$X$53,MATCH("BE-B06",BE_Tasks!$A$2:$A$53,0)) -> 0 | L48: Mở API | M48: Mở task
A49: API-048 | B49: GET | C49: /api/v1/rooms/{roomId}/residents | D49: Người đang ở trong phòng | E49: C | F49: BE-C02 | G49: P1 | H49: room-detail | I49: =INDEX(BE_Tasks!$P$2:$P$53,MATCH("BE-C02",BE_Tasks!$A$2:$A$53,0)) -> Chưa làm | J49: =INDEX(BE_Tasks!$X$2:$X$53,MATCH("BE-C02",BE_Tasks!$A$2:$A$53,0)) -> 0 | L49: Mở API | M49: Mở task
A50: API-049 | B50: GET | C50: /api/v1/rooms/{roomId}/services | D50: Dịch vụ hiệu lực của phòng | E50: B | F50: BE-B03 | G50: P1 | H50: room-detail | I50: =INDEX(BE_Tasks!$P$2:$P$53,MATCH("BE-B03",BE_Tasks!$A$2:$A$53,0)) -> Chưa làm | J50: =INDEX(BE_Tasks!$X$2:$X$53,MATCH("BE-B03",BE_Tasks!$A$2:$A$53,0)) -> 0 | L50: Mở API | M50: Mở task
A51: API-050 | B51: GET | C51: /api/v1/landlord/posts | D51: Danh sách tin chủ trọ quản lý | E51: B | F51: BE-B06 | G51: P2 | H51: submit-post | I51: =INDEX(BE_Tasks!$P$2:$P$53,MATCH("BE-B06",BE_Tasks!$A$2:$A$53,0)) -> Chưa làm | J51: =INDEX(BE_Tasks!$X$2:$X$53,MATCH("BE-B06",BE_Tasks!$A$2:$A$53,0)) -> 0 | L51: Mở API | M51: Mở task
A52: API-051 | B52: POST | C52: /api/v1/posts | D52: Tạo bài mới và gửi duyệt | E52: B | F52: BE-B06 | G52: P2 | H52: submit-post | I52: =INDEX(BE_Tasks!$P$2:$P$53,MATCH("BE-B06",BE_Tasks!$A$2:$A$53,0)) -> Chưa làm | J52: =INDEX(BE_Tasks!$X$2:$X$53,MATCH("BE-B06",BE_Tasks!$A$2:$A$53,0)) -> 0 | K52: D07 | L52: Mở API | M52: Mở task
A53: API-052 | B53: PATCH | C53: /api/v1/posts/{postId} | D53: Sửa đúng bài và gửi duyệt lại | E53: B | F53: BE-B06 | G53: P2 | H53: submit-post | I53: =INDEX(BE_Tasks!$P$2:$P$53,MATCH("BE-B06",BE_Tasks!$A$2:$A$53,0)) -> Chưa làm | J53: =INDEX(BE_Tasks!$X$2:$X$53,MATCH("BE-B06",BE_Tasks!$A$2:$A$53,0)) -> 0 | K53: D07 | L53: Mở API | M53: Mở task
A54: API-053 | B54: GET | C54: /api/v1/admin/posts | D54: Hàng đợi kiểm duyệt tin | E54: B | F54: BE-B06 | G54: P2 | H54: moderate-post | I54: =INDEX(BE_Tasks!$P$2:$P$53,MATCH("BE-B06",BE_Tasks!$A$2:$A$53,0)) -> Chưa làm | J54: =INDEX(BE_Tasks!$X$2:$X$53,MATCH("BE-B06",BE_Tasks!$A$2:$A$53,0)) -> 0 | L54: Mở API | M54: Mở task
A55: API-054 | B55: POST | C55: /api/v1/admin/posts/{postId}/decision | D55: Duyệt hoặc từ chối đúng bài | E55: B | F55: BE-B06 | G55: P2 | H55: moderate-post | I55: =INDEX(BE_Tasks!$P$2:$P$53,MATCH("BE-B06",BE_Tasks!$A$2:$A$53,0)) -> Chưa làm | J55: =INDEX(BE_Tasks!$X$2:$X$53,MATCH("BE-B06",BE_Tasks!$A$2:$A$53,0)) -> 0 | L55: Mở API | M55: Mở task
A56: API-055 | B56: POST | C56: /api/v1/posts/{postId}/hide | D56: Ẩn tin đang công khai | E56: B | F56: BE-B06 | G56: P2 | H56: moderate-post | I56: =INDEX(BE_Tasks!$P$2:$P$53,MATCH("BE-B06",BE_Tasks!$A$2:$A$53,0)) -> Chưa làm | J56: =INDEX(BE_Tasks!$X$2:$X$53,MATCH("BE-B06",BE_Tasks!$A$2:$A$53,0)) -> 0 | L56: Mở API | M56: Mở task
A57: API-056 | B57: POST | C57: /api/v1/admin/posts/{postId}/restore | D57: Hiện lại tin đã ẩn | E57: B | F57: BE-B06 | G57: P2 | H57: moderate-post | I57: =INDEX(BE_Tasks!$P$2:$P$53,MATCH("BE-B06",BE_Tasks!$A$2:$A$53,0)) -> Chưa làm | J57: =INDEX(BE_Tasks!$X$2:$X$53,MATCH("BE-B06",BE_Tasks!$A$2:$A$53,0)) -> 0 | L57: Mở API | M57: Mở task
A58: API-057 | B58: GET | C58: /api/v1/posts | D58: Khám phá và lọc tin công khai | E58: B | F58: BE-B07 | G58: P2 | H58: discover | I58: =INDEX(BE_Tasks!$P$2:$P$53,MATCH("BE-B07",BE_Tasks!$A$2:$A$53,0)) -> Chưa làm | J58: =INDEX(BE_Tasks!$X$2:$X$53,MATCH("BE-B07",BE_Tasks!$A$2:$A$53,0)) -> 0 | L58: Mở API | M58: Mở task
A59: API-058 | B59: GET | C59: /api/v1/posts/{postId} | D59: Chi tiết đúng tin công khai | E59: B | F59: BE-B07 | G59: P2 | H59: discover | I59: =INDEX(BE_Tasks!$P$2:$P$53,MATCH("BE-B07",BE_Tasks!$A$2:$A$53,0)) -> Chưa làm | J59: =INDEX(BE_Tasks!$X$2:$X$53,MATCH("BE-B07",BE_Tasks!$A$2:$A$53,0)) -> 0 | L59: Mở API | M59: Mở task
A60: API-059 | B60: GET | C60: /api/v1/me/favorites | D60: Danh sách bài đã lưu | E60: B | F60: BE-B07 | G60: P2 | H60: discover | I60: =INDEX(BE_Tasks!$P$2:$P$53,MATCH("BE-B07",BE_Tasks!$A$2:$A$53,0)) -> Chưa làm | J60: =INDEX(BE_Tasks!$X$2:$X$53,MATCH("BE-B07",BE_Tasks!$A$2:$A$53,0)) -> 0 | L60: Mở API | M60: Mở task
A61: API-060 | B61: PUT | C61: /api/v1/me/favorites/{postId} | D61: Lưu bài theo ID | E61: B | F61: BE-B07 | G61: P2 | H61: discover | I61: =INDEX(BE_Tasks!$P$2:$P$53,MATCH("BE-B07",BE_Tasks!$A$2:$A$53,0)) -> Chưa làm | J61: =INDEX(BE_Tasks!$X$2:$X$53,MATCH("BE-B07",BE_Tasks!$A$2:$A$53,0)) -> 0 | L61: Mở API | M61: Mở task
A62: API-061 | B62: DELETE | C62: /api/v1/me/favorites/{postId} | D62: Bỏ lưu bài | E62: B | F62: BE-B07 | G62: P2 | H62: discover | I62: =INDEX(BE_Tasks!$P$2:$P$53,MATCH("BE-B07",BE_Tasks!$A$2:$A$53,0)) -> Chưa làm | J62: =INDEX(BE_Tasks!$X$2:$X$53,MATCH("BE-B07",BE_Tasks!$A$2:$A$53,0)) -> 0 | L62: Mở API | M62: Mở task
A63: API-062 | B63: GET | C63: /api/v1/me/roommate-profile | D63: Đọc hồ sơ ở ghép của mình | E63: B | F63: BE-B11 | G63: P4 | H63: roommate-profile | I63: =INDEX(BE_Tasks!$P$2:$P$53,MATCH("BE-B11",BE_Tasks!$A$2:$A$53,0)) -> Chưa làm | J63: =INDEX(BE_Tasks!$X$2:$X$53,MATCH("BE-B11",BE_Tasks!$A$2:$A$53,0)) -> 0 | L63: Mở API | M63: Mở task
A64: API-063 | B64: PUT | C64: /api/v1/me/roommate-profile | D64: Tạo hoặc thay thế hồ sơ ở ghép | E64: B | F64: BE-B11 | G64: P4 | H64: roommate-profile | I64: =INDEX(BE_Tasks!$P$2:$P$53,MATCH("BE-B11",BE_Tasks!$A$2:$A$53,0)) -> Chưa làm | J64: =INDEX(BE_Tasks!$X$2:$X$53,MATCH("BE-B11",BE_Tasks!$A$2:$A$53,0)) -> 0 | L64: Mở API | M64: Mở task
A65: API-064 | B65: GET | C65: /api/v1/roommate-profiles/{profileId} | D65: Xem hồ sơ ứng viên theo quyền | E65: B | F65: BE-B11 | G65: P4 | H65: roommate-profile | I65: =INDEX(BE_Tasks!$P$2:$P$53,MATCH("BE-B11",BE_Tasks!$A$2:$A$53,0)) -> Chưa làm | J65: =INDEX(BE_Tasks!$X$2:$X$53,MATCH("BE-B11",BE_Tasks!$A$2:$A$53,0)) -> 0 | L65: Mở API | M65: Mở task
A66: API-065 | B66: GET | C66: /api/v1/lifestyle-criteria | D66: Danh mục tiêu chí đang áp dụng | E66: B | F66: BE-B12 | G66: P4 | H66: matching-criteria | I66: =INDEX(BE_Tasks!$P$2:$P$53,MATCH("BE-B12",BE_Tasks!$A$2:$A$53,0)) -> Chưa làm | J66: =INDEX(BE_Tasks!$X$2:$X$53,MATCH("BE-B12",BE_Tasks!$A$2:$A$53,0)) -> 0 | L66: Mở API | M66: Mở task
A67: API-066 | B67: GET | C67: /api/v1/me/roommate-profile/lifestyles | D67: Đọc đặc điểm và mong muốn đã lưu | E67: B | F67: BE-B11 | G67: P4 | H67: matching-criteria | I67: =INDEX(BE_Tasks!$P$2:$P$53,MATCH("BE-B11",BE_Tasks!$A$2:$A$53,0)) -> Chưa làm | J67: =INDEX(BE_Tasks!$X$2:$X$53,MATCH("BE-B11",BE_Tasks!$A$2:$A$53,0)) -> 0 | L67: Mở API | M67: Mở task
A68: API-067 | B68: PUT | C68: /api/v1/me/roommate-profile/lifestyles | D68: Thay bộ tiêu chí của hồ sơ | E68: B | F68: BE-B11 | G68: P4 | H68: matching-criteria | I68: =INDEX(BE_Tasks!$P$2:$P$53,MATCH("BE-B11",BE_Tasks!$A$2:$A$53,0)) -> Chưa làm | J68: =INDEX(BE_Tasks!$X$2:$X$53,MATCH("BE-B11",BE_Tasks!$A$2:$A$53,0)) -> 0 | L68: Mở API | M68: Mở task
A69: API-068 | B69: GET | C69: /api/v1/roommate-matches | D69: Danh sách người phù hợp | E69: B | F69: BE-B15 | G69: P6 | H69: matching-criteria | I69: =INDEX(BE_Tasks!$P$2:$P$53,MATCH("BE-B15",BE_Tasks!$A$2:$A$53,0)) -> Chưa làm | J69: =INDEX(BE_Tasks!$X$2:$X$53,MATCH("BE-B15",BE_Tasks!$A$2:$A$53,0)) -> 0 | K69: D02 | L69: Mở API | M69: Mở task
A70: API-069 | B70: POST | C70: /api/v1/admin/lifestyle-criteria | D70: Tạo tiêu chí ghép linh động | E70: B | F70: BE-B12 | G70: P4 | H70: matching-criteria | I70: =INDEX(BE_Tasks!$P$2:$P$53,MATCH("BE-B12",BE_Tasks!$A$2:$A$53,0)) -> Chưa làm | J70: =INDEX(BE_Tasks!$X$2:$X$53,MATCH("BE-B12",BE_Tasks!$A$2:$A$53,0)) -> 0 | L70: Mở API | M70: Mở task
A71: API-070 | B71: PATCH | C71: /api/v1/admin/lifestyle-criteria/{criterionId} | D71: Sửa/ngừng tiêu chí | E71: B | F71: BE-B12 | G71: P4 | H71: matching-criteria | I71: =INDEX(BE_Tasks!$P$2:$P$53,MATCH("BE-B12",BE_Tasks!$A$2:$A$53,0)) -> Chưa làm | J71: =INDEX(BE_Tasks!$X$2:$X$53,MATCH("BE-B12",BE_Tasks!$A$2:$A$53,0)) -> 0 | K71: D02 | L71: Mở API | M71: Mở task
A72: API-071 | B72: GET | C72: /api/v1/roommate-requests | D72: Lời mời đến/đã gửi và bộ đếm | E72: B | F72: BE-B13 | G72: P4 | H72: roommate-invite | I72: =INDEX(BE_Tasks!$P$2:$P$53,MATCH("BE-B13",BE_Tasks!$A$2:$A$53,0)) -> Chưa làm | J72: =INDEX(BE_Tasks!$X$2:$X$53,MATCH("BE-B13",BE_Tasks!$A$2:$A$53,0)) -> 0 | L72: Mở API | M72: Mở task
A73: API-072 | B73: POST | C73: /api/v1/roommate-requests | D73: Gửi lời mời kết nối | E73: B | F73: BE-B13 | G73: P4 | H73: roommate-invite | I73: =INDEX(BE_Tasks!$P$2:$P$53,MATCH("BE-B13",BE_Tasks!$A$2:$A$53,0)) -> Chưa làm | J73: =INDEX(BE_Tasks!$X$2:$X$53,MATCH("BE-B13",BE_Tasks!$A$2:$A$53,0)) -> 0 | L73: Mở API | M73: Mở task
A74: API-073 | B74: POST | C74: /api/v1/roommate-requests/{requestId}/response | D74: Người nhận chấp nhận/từ chối kết nối | E74: B | F74: BE-B13 | G74: P4 | H74: roommate-invite | I74: =INDEX(BE_Tasks!$P$2:$P$53,MATCH("BE-B13",BE_Tasks!$A$2:$A$53,0)) -> Chưa làm | J74: =INDEX(BE_Tasks!$X$2:$X$53,MATCH("BE-B13",BE_Tasks!$A$2:$A$53,0)) -> 0 | L74: Mở API | M74: Mở task
A75: API-074 | B75: POST | C75: /api/v1/roommate-requests/{requestId}/cancel | D75: Người gửi hủy lời mời chờ | E75: B | F75: BE-B13 | G75: P4 | H75: roommate-invite | I75: =INDEX(BE_Tasks!$P$2:$P$53,MATCH("BE-B13",BE_Tasks!$A$2:$A$53,0)) -> Chưa làm | J75: =INDEX(BE_Tasks!$X$2:$X$53,MATCH("BE-B13",BE_Tasks!$A$2:$A$53,0)) -> 0 | L75: Mở API | M75: Mở task
A76: API-075 | B76: POST | C76: /api/v1/roommate-requests/{requestId}/end | D76: Kết thúc kết nối đã nhận | E76: B | F76: BE-B13 | G76: P4 | H76: roommate-invite | I76: =INDEX(BE_Tasks!$P$2:$P$53,MATCH("BE-B13",BE_Tasks!$A$2:$A$53,0)) -> Chưa làm | J76: =INDEX(BE_Tasks!$X$2:$X$53,MATCH("BE-B13",BE_Tasks!$A$2:$A$53,0)) -> 0 | K76: D03 | L76: Mở API | M76: Mở task
A77: API-076 | B77: POST | C77: /api/v1/conversations/room-inquiries | D77: Mở/lấy hội thoại hỏi đúng bài | E77: A | F77: BE-A08 | G77: P2 | H77: room-chat | I77: =INDEX(BE_Tasks!$P$2:$P$53,MATCH("BE-A08",BE_Tasks!$A$2:$A$53,0)) -> Chưa làm | J77: =INDEX(BE_Tasks!$X$2:$X$53,MATCH("BE-A08",BE_Tasks!$A$2:$A$53,0)) -> 0 | K77: D08 | L77: Mở API | M77: Mở task
A78: API-077 | B78: GET | C78: /api/v1/conversations | D78: Hội thoại của tài khoản | E78: A | F78: BE-A08 | G78: P2 | H78: room-chat | I78: =INDEX(BE_Tasks!$P$2:$P$53,MATCH("BE-A08",BE_Tasks!$A$2:$A$53,0)) -> Chưa làm | J78: =INDEX(BE_Tasks!$X$2:$X$53,MATCH("BE-A08",BE_Tasks!$A$2:$A$53,0)) -> 0 | L78: Mở API | M78: Mở task
A79: API-078 | B79: GET | C79: /api/v1/conversations/{conversationId} | D79: Chi tiết hội thoại và thành viên | E79: A | F79: BE-A08 | G79: P2 | H79: room-chat | I79: =INDEX(BE_Tasks!$P$2:$P$53,MATCH("BE-A08",BE_Tasks!$A$2:$A$53,0)) -> Chưa làm | J79: =INDEX(BE_Tasks!$X$2:$X$53,MATCH("BE-A08",BE_Tasks!$A$2:$A$53,0)) -> 0 | L79: Mở API | M79: Mở task
A80: API-079 | B80: GET | C80: /api/v1/conversations/{conversationId}/messages | D80: Lịch sử tin và thẻ chia sẻ | E80: A | F80: BE-A08 | G80: P2 | H80: room-chat | I80: =INDEX(BE_Tasks!$P$2:$P$53,MATCH("BE-A08",BE_Tasks!$A$2:$A$53,0)) -> Chưa làm | J80: =INDEX(BE_Tasks!$X$2:$X$53,MATCH("BE-A08",BE_Tasks!$A$2:$A$53,0)) -> 0 | L80: Mở API | M80: Mở task
A81: API-080 | B81: POST | C81: /api/v1/conversations/{conversationId}/messages | D81: Gửi tin nhắn chữ/ảnh | E81: A | F81: BE-A08 | G81: P2 | H81: room-chat | I81: =INDEX(BE_Tasks!$P$2:$P$53,MATCH("BE-A08",BE_Tasks!$A$2:$A$53,0)) -> Chưa làm | J81: =INDEX(BE_Tasks!$X$2:$X$53,MATCH("BE-A08",BE_Tasks!$A$2:$A$53,0)) -> 0 | L81: Mở API | M81: Mở task
A82: API-081 | B82: PUT | C82: /api/v1/conversations/{conversationId}/read-state | D82: Đánh dấu đã đọc đến tin xác định | E82: A | F82: BE-A08 | G82: P2 | H82: room-chat | I82: =INDEX(BE_Tasks!$P$2:$P$53,MATCH("BE-A08",BE_Tasks!$A$2:$A$53,0)) -> Chưa làm | J82: =INDEX(BE_Tasks!$X$2:$X$53,MATCH("BE-A08",BE_Tasks!$A$2:$A$53,0)) -> 0 | L82: Mở API | M82: Mở task
A83: API-082 | B83: PATCH | C83: /api/v1/conversations/{conversationId}/preferences | D83: Ẩn/lưu trữ/tắt thông báo phía mình | E83: A | F83: BE-A08 | G83: P2 | H83: room-chat | I83: =INDEX(BE_Tasks!$P$2:$P$53,MATCH("BE-A08",BE_Tasks!$A$2:$A$53,0)) -> Chưa làm | J83: =INDEX(BE_Tasks!$X$2:$X$53,MATCH("BE-A08",BE_Tasks!$A$2:$A$53,0)) -> 0 | L83: Mở API | M83: Mở task
A84: API-083 | B84: GET | C84: /api/v1/conversations/{conversationId}/viewing-timeline | D84: Thẻ lịch và đề nghị trong chat | E84: A | F84: BE-A11 | G84: P4 | H84: room-chat, propose-viewing, schedule-viewing | I84: =INDEX(BE_Tasks!$P$2:$P$53,MATCH("BE-A11",BE_Tasks!$A$2:$A$53,0)) -> Chưa làm | J84: =INDEX(BE_Tasks!$X$2:$X$53,MATCH("BE-A11",BE_Tasks!$A$2:$A$53,0)) -> 0 | L84: Mở API | M84: Mở task
A85: API-084 | B85: POST | C85: /api/v1/roommate-requests/{requestId}/conversation | D85: Mở lại đúng chat bạn ghép | E85: A | F85: BE-A11 | G85: P4 | H85: roommate-chat | I85: =INDEX(BE_Tasks!$P$2:$P$53,MATCH("BE-A11",BE_Tasks!$A$2:$A$53,0)) -> Chưa làm | J85: =INDEX(BE_Tasks!$X$2:$X$53,MATCH("BE-A11",BE_Tasks!$A$2:$A$53,0)) -> 0 | L85: Mở API | M85: Mở task
A86: API-085 | B86: POST | C86: /api/v1/conversations/{conversationId}/post-shares | D86: Chia sẻ đúng bài cho bạn ghép | E86: A | F86: BE-A11 | G86: P4 | H86: share-post | I86: =INDEX(BE_Tasks!$P$2:$P$53,MATCH("BE-A11",BE_Tasks!$A$2:$A$53,0)) -> Chưa làm | J86: =INDEX(BE_Tasks!$X$2:$X$53,MATCH("BE-A11",BE_Tasks!$A$2:$A$53,0)) -> 0 | L86: Mở API | M86: Mở task
A87: API-086 | B87: GET | C87: /api/v1/me/notifications | D87: Feed thông báo của mình | E87: A | F87: BE-A09 | G87: P3 | H87: notifications | I87: =INDEX(BE_Tasks!$P$2:$P$53,MATCH("BE-A09",BE_Tasks!$A$2:$A$53,0)) -> Chưa làm | J87: =INDEX(BE_Tasks!$X$2:$X$53,MATCH("BE-A09",BE_Tasks!$A$2:$A$53,0)) -> 0 | L87: Mở API | M87: Mở task
A88: API-087 | B88: GET | C88: /api/v1/me/notification-counts | D88: Bộ đếm chưa đọc | E88: A | F88: BE-A09 | G88: P3 | H88: notifications | I88: =INDEX(BE_Tasks!$P$2:$P$53,MATCH("BE-A09",BE_Tasks!$A$2:$A$53,0)) -> Chưa làm | J88: =INDEX(BE_Tasks!$X$2:$X$53,MATCH("BE-A09",BE_Tasks!$A$2:$A$53,0)) -> 0 | L88: Mở API | M88: Mở task
A89: API-088 | B89: PUT | C89: /api/v1/me/notifications/{notificationId}/read-state | D89: Đánh dấu một thông báo đã đọc | E89: A | F89: BE-A09 | G89: P3 | H89: notifications | I89: =INDEX(BE_Tasks!$P$2:$P$53,MATCH("BE-A09",BE_Tasks!$A$2:$A$53,0)) -> Chưa làm | J89: =INDEX(BE_Tasks!$X$2:$X$53,MATCH("BE-A09",BE_Tasks!$A$2:$A$53,0)) -> 0 | L89: Mở API | M89: Mở task
A90: API-089 | B90: POST | C90: /api/v1/me/notifications/read-all | D90: Đọc tất cả đến mốc xác định | E90: A | F90: BE-A09 | G90: P3 | H90: notifications | I90: =INDEX(BE_Tasks!$P$2:$P$53,MATCH("BE-A09",BE_Tasks!$A$2:$A$53,0)) -> Chưa làm | J90: =INDEX(BE_Tasks!$X$2:$X$53,MATCH("BE-A09",BE_Tasks!$A$2:$A$53,0)) -> 0 | L90: Mở API | M90: Mở task
A91: API-090 | B91: GET | C91: /api/v1/events | D91: Kênh sự kiện SSE có xác thực | E91: A | F91: BE-A14 | G91: P5 | H91: notifications | I91: =INDEX(BE_Tasks!$P$2:$P$53,MATCH("BE-A14",BE_Tasks!$A$2:$A$53,0)) -> Chưa làm | J91: =INDEX(BE_Tasks!$X$2:$X$53,MATCH("BE-A14",BE_Tasks!$A$2:$A$53,0)) -> 0 | K91: D09 | L91: Mở API | M91: Mở task
A92: API-091 | B92: GET | C92: /api/v1/viewing-proposals | D92: Danh sách đề nghị đúng các bên | E92: B | F92: BE-B08 | G92: P3 | H92: propose-viewing | I92: =INDEX(BE_Tasks!$P$2:$P$53,MATCH("BE-B08",BE_Tasks!$A$2:$A$53,0)) -> Chưa làm | J92: =INDEX(BE_Tasks!$X$2:$X$53,MATCH("BE-B08",BE_Tasks!$A$2:$A$53,0)) -> 0 | L92: Mở API | M92: Mở task
A93: API-092 | B93: POST | C93: /api/v1/viewing-proposals | D93: Người thuê gửi đề nghị lịch xem | E93: B | F93: BE-B08 | G93: P3 | H93: propose-viewing | I93: =INDEX(BE_Tasks!$P$2:$P$53,MATCH("BE-B08",BE_Tasks!$A$2:$A$53,0)) -> Chưa làm | J93: =INDEX(BE_Tasks!$X$2:$X$53,MATCH("BE-B08",BE_Tasks!$A$2:$A$53,0)) -> 0 | L93: Mở API | M93: Mở task
A94: API-093 | B94: POST | C94: /api/v1/viewing-proposals/{proposalId}/decision | D94: Chủ trọ chấp nhận/từ chối đề nghị | E94: B | F94: BE-B08 | G94: P3 | H94: propose-viewing | I94: =INDEX(BE_Tasks!$P$2:$P$53,MATCH("BE-B08",BE_Tasks!$A$2:$A$53,0)) -> Chưa làm | J94: =INDEX(BE_Tasks!$X$2:$X$53,MATCH("BE-B08",BE_Tasks!$A$2:$A$53,0)) -> 0 | L94: Mở API | M94: Mở task
A95: API-094 | B95: POST | C95: /api/v1/viewing-proposals/{proposalId}/withdraw | D95: Rút đề nghị của mình | E95: B | F95: BE-B08 | G95: P3 | H95: propose-viewing | I95: =INDEX(BE_Tasks!$P$2:$P$53,MATCH("BE-B08",BE_Tasks!$A$2:$A$53,0)) -> Chưa làm | J95: =INDEX(BE_Tasks!$X$2:$X$53,MATCH("BE-B08",BE_Tasks!$A$2:$A$53,0)) -> 0 | L95: Mở API | M95: Mở task
A96: API-095 | B96: GET | C96: /api/v1/viewings | D96: Danh sách lịch đã chốt | E96: B | F96: BE-B09 | G96: P3 | H96: schedule-viewing | I96: =INDEX(BE_Tasks!$P$2:$P$53,MATCH("BE-B09",BE_Tasks!$A$2:$A$53,0)) -> Chưa làm | J96: =INDEX(BE_Tasks!$X$2:$X$53,MATCH("BE-B09",BE_Tasks!$A$2:$A$53,0)) -> 0 | L96: Mở API | M96: Mở task
A97: API-096 | B97: GET | C97: /api/v1/viewings/{viewingId} | D97: Chi tiết lịch xem | E97: B | F97: BE-B09 | G97: P3 | H97: schedule-viewing | I97: =INDEX(BE_Tasks!$P$2:$P$53,MATCH("BE-B09",BE_Tasks!$A$2:$A$53,0)) -> Chưa làm | J97: =INDEX(BE_Tasks!$X$2:$X$53,MATCH("BE-B09",BE_Tasks!$A$2:$A$53,0)) -> 0 | L97: Mở API | M97: Mở task
A98: API-097 | B98: POST | C98: /api/v1/viewings | D98: Chủ trọ tự chốt lịch sau trao đổi | E98: B | F98: BE-B09 | G98: P3 | H98: schedule-viewing | I98: =INDEX(BE_Tasks!$P$2:$P$53,MATCH("BE-B09",BE_Tasks!$A$2:$A$53,0)) -> Chưa làm | J98: =INDEX(BE_Tasks!$X$2:$X$53,MATCH("BE-B09",BE_Tasks!$A$2:$A$53,0)) -> 0 | L98: Mở API | M98: Mở task
A99: API-098 | B99: POST | C99: /api/v1/viewings/{viewingId}/attendance | D99: Chủ trọ ghi nhận đã xem hoặc không đến | E99: B | F99: BE-B09 | G99: P3 | H99: viewing-outcome | I99: =INDEX(BE_Tasks!$P$2:$P$53,MATCH("BE-B09",BE_Tasks!$A$2:$A$53,0)) -> Chưa làm | J99: =INDEX(BE_Tasks!$X$2:$X$53,MATCH("BE-B09",BE_Tasks!$A$2:$A$53,0)) -> 0 | L99: Mở API | M99: Mở task
A100: API-099 | B100: POST | C100: /api/v1/viewings/{viewingId}/cancel | D100: Hai bên hủy lịch đang hẹn | E100: B | F100: BE-B09 | G100: P3 | H100: viewing-outcome | I100: =INDEX(BE_Tasks!$P$2:$P$53,MATCH("BE-B09",BE_Tasks!$A$2:$A$53,0)) -> Chưa làm | J100: =INDEX(BE_Tasks!$X$2:$X$53,MATCH("BE-B09",BE_Tasks!$A$2:$A$53,0)) -> 0 | L100: Mở API | M100: Mở task
...

Sheet Owner_Files
A1: Module | B1: Owner | C1: Phạm vi file | D1: Nghiệp vụ | E1: Quy tắc bàn giao
A2: Khung backend & adapter chung | B2: A | C2: backend/src/core/** backend/contracts/core.* backend/tests/fixtures/A/** backend/tests/contracts/A/** backend/tests/e2e/platform-*/** backend/bootstrap.* backend/package* backend/lockfile .github/workflows/backend-* | D2: ActorContext, envelope, DB/UoW, procedure runner, idempotency, event/audit ports; không chứa nghiệp vụ nhà/thuê. | E2: Dựng router tự đăng ký manifest module; B/C không cùng sửa một routes.* hoặc DI container.
A3: Tài khoản & danh tính | B3: A | C3: backend/src/modules/identity/** backend/tests/identity/** backend/contracts/identity.* | D3: users, roles, profiles, auth_sessions, verification_tokens, identity verification. | E3: C dùng TokenPort cho OCCUPANT_LINK, không tự sửa token repository của A.
A4: Kho tệp & quyền đọc | B4: A | C4: backend/src/modules/files/** backend/tests/files/** backend/contracts/files.* | D4: Metadata, upload/complete/download, MIME/hash/retention, private authorization. | E4: B/C truyền fileId và business context; không viết thêm một file service riêng.
A5: Hội thoại & thông báo | B5: A | C5: backend/src/modules/messaging/** backend/src/modules/notifications/** backend/tests/messaging/** backend/contracts/messaging.* | D5: Hội thoại, participant, message, notifications, SSE. | E5: Chat gộp theo cặp ở read model; context ghi vẫn đúng conversation/post/room của v5.
A6: Hóa đơn & thu tiền | B6: A | C6: backend/src/modules/billing/** backend/tests/billing/** backend/contracts/billing.* | D6: invoices/invoice_items, snapshot người trả/giá; thu toàn bộ theo phạm vi hiện tại. | E6: Nhận dữ liệu hợp đồng/cư trú qua cổng C, giá dịch vụ qua cổng B; không sửa bảng giá/hợp đồng.
A7: Quản trị tài khoản & audit | B7: A | C7: backend/src/modules/account-admin/** backend/src/modules/audit/** backend/src/modules/admin-dashboard/** backend/tests/account-admin/** | D7: Khóa phiên/tài khoản, truy vết và tổng quan quản trị; các /admin khác nằm tại module nghiệp vụ của B/C. | E7: Không gom mọi endpoint /admin vào một controller chung.
A8: Nhà, quyền nhà & phòng | B8: B | C8: backend/src/modules/properties/** backend/src/modules/house-rights/** backend/tests/properties/** backend/tests/fixtures/B/** backend/tests/contracts/B/** backend/tests/e2e/property-*/** backend/contracts/properties.* | D8: Nhà/phòng, quyền cho thuê, tải phòng, dashboard chủ trọ và các nguồn đọc công khai. | E8: C chỉ gọi cổng đọc/SQL procedure dưới khóa; không đổi trạng thái phòng bằng setter từ controller.
A9: Tin đăng & tìm kiếm | B9: B | C9: backend/src/modules/posts/** backend/tests/posts/** backend/contracts/posts.* | D9: posts/post_images/post_amenities/favorites, quota 3 bài chờ và public view. | E9: Mọi tham chiếu giữ postId; ảnh và bài phải lưu nguyên tử sau mở rộng D07.
A10: Dịch vụ & giá hiệu lực | B10: B | C10: backend/src/modules/services/** backend/tests/services/** backend/contracts/services.* | D10: rental_services/house_services/room_services và báo giá hiện tại. | E10: A sở hữu hóa đơn; đổi dịch vụ không sửa invoice_items cũ.
A11: Lịch xem & quyết định thuê | B11: B | C11: backend/src/modules/viewings/** backend/tests/viewings/** backend/tests/e2e/viewing-contract/** backend/contracts/viewings.* | D11: Proposal, schedule, attendance, rental decision. | E11: C tạo hợp đồng bằng viewingId; cùng bản ghi lịch được dùng cho chat và màn hình lịch.
A12: Hồ sơ, tiêu chí & kết nối | B12: B | C12: backend/src/modules/roommates/** backend/tests/roommates/** backend/contracts/roommates.* | D12: roommate_profiles/lifestyles/requests và matching theo chính sách đã chốt. | E12: ACCEPTED chỉ tạo kết nối/chat, không tạo occupant_join_request hoặc consent thuê.
... A17: Tệp chung & SQL sinh ra | B17: A | C17: database/schema.sql database/migrations/* scripts/build-database.cjs backend/tests/e2e/release/** | D17: A cấp thứ tự migration, build/commit output SQL, khóa phiên bản dependency và CI. | E17: B/C có thể chạy build trong thư mục tạm để test; A tái sinh output trên nhánh tích hợp từ toàn bộ nguồn mới nhất.

Sheet Giai_doan
A1: Mốc | B1: Tên | C1: Mục tiêu | D1: Task | E1: SP | F1: Gate | G1: Điều kiện qua gate | H1: Trạng thái gate
A2: P0 | B2: Chốt giao diện & cách làm chung | C2: Đóng băng contract v1, quyền sở hữu file và cách build/test; B/C chuẩn bị adapter, fixture song song với A dựng khung. | D2: BE-A01, BE-A02, BE-B01, BE-C01 | E2: 16 | F2: G0 | G2: Cả ba duyệt core/domain contracts và fixture; manifest, nhánh và quy tắc thay đổi chung đã rõ. | H2: =IF(AND(AND(INDEX(BE_Tasks!$P$2:$P$53,MATCH("BE-A01",BE_Tasks!$A$2:$A$53,0))="Hoàn thành",INDEX(BE_Tasks!$Z$2:$Z$53,MATCH("BE-A01",BE_Tasks!$A$2:$A$53,0))=""),AND(INDEX(BE_Tasks!$P$2:$P$53,MATCH("BE-A02",BE_Tasks!$A$2:$A$53,0))="Hoàn thành",INDEX(BE_Tasks!$Z$2:$Z$53,MATCH("BE-A02",BE_Tasks!$A$2:$A$53,0))=""),AND(INDEX(BE_Tasks!$P$2:$P$53,MATCH("BE-B01",BE_Tasks!$A$2:$A$53,0))="Hoàn thành",INDEX(BE_Tasks!$Z$2:$Z$53,MATCH("BE-B01",BE_Tasks!$A$2:$A$53,0))=""),AND(INDEX(BE_Tasks!$P$2:$P$53,MATCH("BE-C01",BE_Tasks!$A$2:$A$53,0))="Hoàn thành",INDEX(BE_Tasks!$Z$2:$Z$53,MATCH("BE-C01",BE_Tasks!$A$2:$A$53,0))="")),"Đạt","Chưa đạt") -> Chưa đạt
A3: P1 | B3: Nền tảng & dữ liệu gốc | C3: Có auth, tệp, idempotency, CRUD nhà/phòng, dịch vụ và các cổng đọc nghiệp vụ. Chưa phụ thuộc việc có người thuê thực tế. | D3: BE-A03, BE-A04, BE-A05, BE-B02, BE-B03, BE-B04, BE-C02, BE-C03 | E3: 45 | F3: G1 | G3: Auth thật, kho tệp test, idempotency và các cổng đọc đạt contract test; test DB độc lập. | H3: =IF(AND(AND(INDEX(BE_Tasks!$P$2:$P$53,MATCH("BE-A03",BE_Tasks!$A$2:$A$53,0))="Hoàn thành",INDEX(BE_Tasks!$Z$2:$Z$53,MATCH("BE-A03",BE_Tasks!$A$2:$A$53,0))=""),AND(INDEX(BE_Tasks!$P$2:$P$53,MATCH("BE-A04",BE_Tasks!$A$2:$A$53,0))="Hoàn thành",INDEX(BE_Tasks!$Z$2:$Z$53,MATCH("BE-A04",BE_Tasks!$A$2:$A$53,0))=""),AND(INDEX(BE_Tasks!$P$2:$P$53,MATCH("BE-A05",BE_Tasks!$A$2:$A$53,0))="Hoàn thành",INDEX(BE_Tasks!$Z$2:$Z$53,MATCH("BE-A05",BE_Tasks!$A$2:$A$53,0))=""),AND(INDEX(BE_Tasks!$P$2:$P$53,MATCH("BE-B04",BE_Tasks!$A$2:$A$53,0))="Hoàn thành",INDEX(BE_Tasks!$Z$2:$Z$53,MATCH("BE-B04",BE_Tasks!$A$2:$A$53,0))=""),AND(INDEX(BE_Tasks!$P$2:$P$53,MATCH("BE-C02",BE_Tasks!$A$2:$A$53,0))="Hoàn thành",INDEX(BE_Tasks!$Z$2:$Z$53,MATCH("BE-C02",BE_Tasks!$A$2:$A$53,0))=""),AND(INDEX(BE_Tasks!$P$2:$P$53,MATCH("BE-C03",BE_Tasks!$A$2:$A$53,0))="Hoàn thành",INDEX(BE_Tasks!$Z$2:$Z$53,MATCH("BE-C03",BE_Tasks!$A$2:$A$53,0))="")),"Đạt","Chưa đạt") -> Chưa đạt
A4: P2 | B4: Công khai phòng & chat hỏi phòng | C4: Hoàn thành minh chứng nhà, quota tin, tìm phòng, xác minh tài khoản và chat để làm đầu vào cho lịch xem. | D4: BE-A06, BE-A07, BE-A08, BE-B05, BE-B06, BE-B07, BE-C04 | E4: 44 | F4: G2 | G4: Có quyền nhà, post đã duyệt và tin tenant gửi đúng room; expected revision được bảo vệ trong SQL. | H4: =IF(AND(AND(INDEX(BE_Tasks!$P$2:$P$53,MATCH("BE-A06",BE_Tasks!$A$2:$A$53,0))="Hoàn thành",INDEX(BE_Tasks!$Z$2:$Z$53,MATCH("BE-A06",BE_Tasks!$A$2:$A$53,0))=""),AND(INDEX(BE_Tasks!$P$2:$P$53,MATCH("BE-A07",BE_Tasks!$A$2:$A$53,0))="Hoàn thành",INDEX(BE_Tasks!$Z$2:$Z$53,MATCH("BE-A07",BE_Tasks!$A$2:$A$53,0))=""),AND(INDEX(BE_Tasks!$P$2:$P$53,MATCH("BE-A08",BE_Tasks!$A$2:$A$53,0))="Hoàn thành",INDEX(BE_Tasks!$Z$2:$Z$53,MATCH("BE-A08",BE_Tasks!$A$2:$A$53,0))=""),AND(INDEX(BE_Tasks!$P$2:$P$53,MATCH("BE-B05",BE_Tasks!$A$2:$A$53,0))="Hoàn thành",INDEX(BE_Tasks!$Z$2:$Z$53,MATCH("BE-B05",BE_Tasks!$A$2:$A$53,0))=""),AND(INDEX(BE_Tasks!$P$2:$P$53,MATCH("BE-B06",BE_Tasks!$A$2:$A$53,0))="Hoàn thành",INDEX(BE_Tasks!$Z$2:$Z$53,MATCH("BE-B06",BE_Tasks!$A$2:$A$53,0))=""),AND(INDEX(BE_Tasks!$P$2:$P$53,MATCH("BE-B07",BE_Tasks!$A$2:$A$53,0))="Hoàn thành",INDEX(BE_Tasks!$Z$2:$Z$53,MATCH("BE-B07",BE_Tasks!$A$2:$A$53,0))=""),AND(INDEX(BE_Tasks!$P$2:$P$53,MATCH("BE-C04",BE_Tasks!$A$2:$A$53,0))="Hoàn thành",INDEX(BE_Tasks!$Z$2:$Z$53,MATCH("BE-C04",BE_Tasks!$A$2:$A$53,0))="")),"Đạt","Chưa đạt") -> Chưa đạt
A5: P3 | B5: Hẹn xem → gửi hợp đồng | C5: B chốt lịch/ý định thuê; C dùng lịch đủ điều kiện để giữ phòng và đóng lịch tương lai; A hoàn thiện thông báo. | D5: BE-A09, BE-B08, BE-B09, BE-B10, BE-C05 | E5: 24 | F5: G3 | G5: Tenant COMPLETED+AGREED → contract pending giữ room; lịch/proposal đóng đúng, hai người tranh phòng chỉ một thắng. | H5: =IF(AND(AND(INDEX(BE_Tasks!$P$2:$P$53,MATCH("BE-A09",BE_Tasks!$A$2:$A$53,0))="Hoàn thành",INDEX(BE_Tasks!$Z$2:$Z$53,MATCH("BE-A09",BE_Tasks!$A$2:$A$53,0))=""),AND(INDEX(BE_Tasks!$P$2:$P$53,MATCH("BE-B08",BE_Tasks!$A$2:$A$53,0))="Hoàn thành",INDEX(BE_Tasks!$Z$2:$Z$53,MATCH("BE-B08",BE_Tasks!$A$2:$A$53,0))=""),AND(INDEX(BE_Tasks!$P$2:$P$53,MATCH("BE-B09",BE_Tasks!$A$2:$A$53,0))="Hoàn thành",INDEX(BE_Tasks!$Z$2:$Z$53,MATCH("BE-B09",BE_Tasks!$A$2:$A$53,0))=""),AND(INDEX(BE_Tasks!$P$2:$P$53,MATCH("BE-B10",BE_Tasks!$A$2:$A$53,0))="Hoàn thành",INDEX(BE_Tasks!$Z$2:$Z$53,MATCH("BE-B10",BE_Tasks!$A$2:$A$53,0))=""),AND(INDEX(BE_Tasks!$P$2:$P$53,MATCH("BE-C05",BE_Tasks!$A$2:$A$53,0))="Hoàn thành",INDEX(BE_Tasks!$Z$2:$Z$53,MATCH("BE-C05",BE_Tasks!$A$2:$A$53,0))="")),"Đạt","Chưa đạt") -> Chưa đạt
A6: P4 | B6: Xác nhận → vào ở → hóa đơn nháp | C6: C xác nhận phiên bản và người ở thực tế; A lập hóa đơn bằng snapshot; B triển khai hồ sơ/kết nối và thẻ chat dùng cổng đã công bố. | D6: BE-A10, BE-A11, BE-A12, BE-B11, BE-B12, BE-B13, BE-C06, BE-C07, BE-C08, BE-C09 | E6: 48 | F6: G4 | G6: Move-in mới ACTIVE, invoice đếm đúng người, kết nối/chat không tự thành thuê chung, token link nguyên tử. | H6: =IF(AND(AND(INDEX(BE_Tasks!$P$2:$P$53,MATCH("BE-A10",BE_Tasks!$A$2:$A$53,0))="Hoàn thành",INDEX(BE_Tasks!$Z$2:$Z$53,MATCH("BE-A10",BE_Tasks!$A$2:$A$53,0))=""),AND(INDEX(BE_Tasks!$P$2:$P$53,MATCH("BE-A11",BE_Tasks!$A$2:$A$53,0))="Hoàn thành",INDEX(BE_Tasks!$Z$2:$Z$53,MATCH("BE-A11",BE_Tasks!$A$2:$A$53,0))=""),AND(INDEX(BE_Tasks!$P$2:$P$53,MATCH("BE-A12",BE_Tasks!$A$2:$A$53,0))="Hoàn thành",INDEX(BE_Tasks!$Z$2:$Z$53,MATCH("BE-A12",BE_Tasks!$A$2:$A$53,0))=""),AND(INDEX(BE_Tasks!$P$2:$P$53,MATCH("BE-B11",BE_Tasks!$A$2:$A$53,0))="Hoàn thành",INDEX(BE_Tasks!$Z$2:$Z$53,MATCH("BE-B11",BE_Tasks!$A$2:$A$53,0))=""),AND(INDEX(BE_Tasks!$P$2:$P$53,MATCH("BE-B12",BE_Tasks!$A$2:$A$53,0))="Hoàn thành",INDEX(BE_Tasks!$Z$2:$Z$53,MATCH("BE-B12",BE_Tasks!$A$2:$A$53,0))=""),AND(INDEX(BE_Tasks!$P$2:$P$53,MATCH("BE-B13",BE_Tasks!$A$2:$A$53,0))="Hoàn thành",INDEX(BE_Tasks!$Z$2:$Z$53,MATCH("BE-B13",BE_Tasks!$A$2:$A$53,0))=""),AND(INDEX(BE_Tasks!$P$2:$P$53,MATCH("BE-C06",BE_Tasks!$A$2:$A$53,0))="Hoàn thành",INDEX(BE_Tasks!$Z$2:$Z$53,MATCH("BE-C06",BE_Tasks!$A$2:$A$53,0))=""),AND(INDEX(BE_Tasks!$P$2:$P$53,MATCH("BE-C07",BE_Tasks!$A$2:$A$53,0))="Hoàn thành",INDEX(BE_Tasks!$Z$2:$Z$53,MATCH("BE-C07",BE_Tasks!$A$2:$A$53,0))=""),AND(INDEX(BE_Tasks!$P$2:$P$53,MATCH("BE-C08",BE_Tasks!$A$2:$A$53,0))="Hoàn thành",INDEX(BE_Tasks!$Z$2:$Z$53,MATCH("BE-C08",BE_Tasks!$A$2:$A$53,0))=""),AND(INDEX(BE_Tasks!$P$2:$P$53,MATCH("BE-C09",BE_Tasks!$A$2:$A$53,0))="Hoàn thành",INDEX(BE_Tasks!$Z$2:$Z$53,MATCH("BE-C09",BE_Tasks!$A$2:$A$53,0))="")),"Đạt","Chưa đạt") -> Chưa đạt
A7: P5 | B7: Thuê chung, thay đổi & thu tiền | C7: Hoàn tất giữ chỗ, bàn giao, gia hạn/đổi phòng/chấm dứt, thu tiền và vận chuyển sự kiện SSE. | D7: BE-A13, BE-A14, BE-B14, BE-C10, BE-C11, BE-C12 | E7: 36 | F7: G5 | G7: Giữ invoice/payer cũ, chuyển đủ nhóm và rollback, hold 48h đúng, SSE phát sau commit. | H7: =IF(AND(AND(INDEX(BE_Tasks!$P$2:$P$53,MATCH("BE-A13",BE_Tasks!$A$2:$A$53,0))="Hoàn thành",INDEX(BE_Tasks!$Z$2:$Z$53,MATCH("BE-A13",BE_Tasks!$A$2:$A$53,0))=""),AND(INDEX(BE_Tasks!$P$2:$P$53,MATCH("BE-A14",BE_Tasks!$A$2:$A$53,0))="Hoàn thành",INDEX(BE_Tasks!$Z$2:$Z$53,MATCH("BE-A14",BE_Tasks!$A$2:$A$53,0))=""),AND(INDEX(BE_Tasks!$P$2:$P$53,MATCH("BE-B14",BE_Tasks!$A$2:$A$53,0))="Hoàn thành",INDEX(BE_Tasks!$Z$2:$Z$53,MATCH("BE-B14",BE_Tasks!$A$2:$A$53,0))=""),AND(INDEX(BE_Tasks!$P$2:$P$53,MATCH("BE-C10",BE_Tasks!$A$2:$A$53,0))="Hoàn thành",INDEX(BE_Tasks!$Z$2:$Z$53,MATCH("BE-C10",BE_Tasks!$A$2:$A$53,0))=""),AND(INDEX(BE_Tasks!$P$2:$P$53,MATCH("BE-C11",BE_Tasks!$A$2:$A$53,0))="Hoàn thành",INDEX(BE_Tasks!$Z$2:$Z$53,MATCH("BE-C11",BE_Tasks!$A$2:$A$53,0))=""),AND(INDEX(BE_Tasks!$P$2:$P$53,MATCH("BE-C12",BE_Tasks!$A$2:$A$53,0))="Hoàn thành",INDEX(BE_Tasks!$Z$2:$Z$53,MATCH("BE-C12",BE_Tasks!$A$2:$A$53,0))="")),"Đạt","Chưa đạt") -> Chưa đạt
A8: P6 | B8: Chính sách mở rộng & tác vụ nền | C8: Chốt thuật toán ghép, nhập giấy, audit mở rộng, đánh giá, dashboard và worker. Các mục chưa chốt tiếp tục được đánh dấu phụ thuộc. | D8: BE-A15, BE-B15, BE-B16, BE-B17, BE-B18, BE-C13, BE-C14 | E8: 29 | F8: G6 | G8: D02/D11/D13/D14 được chốt trước tính năng tương ứng; worker không tự kết thúc cư trú bằng suy đoán. | H8: =IF(AND(AND(INDEX(BE_Tasks!$P$2:$P$53,MATCH("BE-A15",BE_Tasks!$A$2:$A$53,0))="Hoàn thành",INDEX(BE_Tasks!$Z$2:$Z$53,MATCH("BE-A15",BE_Tasks!$A$2:$A$53,0))=""),AND(INDEX(BE_Tasks!$P$2:$P$53,MATCH("BE-B15",BE_Tasks!$A$2:$A$53,0))="Hoàn thành",INDEX(BE_Tasks!$Z$2:$Z$53,MATCH("BE-B15",BE_Tasks!$A$2:$A$53,0))=""),AND(INDEX(BE_Tasks!$P$2:$P$53,MATCH("BE-B16",BE_Tasks!$A$2:$A$53,0))="Hoàn thành",INDEX(BE_Tasks!$Z$2:$Z$53,MATCH("BE-B16",BE_Tasks!$A$2:$A$53,0))=""),AND(INDEX(BE_Tasks!$P$2:$P$53,MATCH("BE-B17",BE_Tasks!$A$2:$A$53,0))="Hoàn thành",INDEX(BE_Tasks!$Z$2:$Z$53,MATCH("BE-B17",BE_Tasks!$A$2:$A$53,0))=""),AND(INDEX(BE_Tasks!$P$2:$P$53,MATCH("BE-B18",BE_Tasks!$A$2:$A$53,0))="Hoàn thành",INDEX(BE_Tasks!$Z$2:$Z$53,MATCH("BE-B18",BE_Tasks!$A$2:$A$53,0))=""),AND(INDEX(BE_Tasks!$P$2:$P$53,MATCH("BE-C13",BE_Tasks!$A$2:$A$53,0))="Hoàn thành",INDEX(BE_Tasks!$Z$2:$Z$53,MATCH("BE-C13",BE_Tasks!$A$2:$A$53,0))=""),AND(INDEX(BE_Tasks!$P$2:$P$53,MATCH("BE-C14",BE_Tasks!$A$2:$A$53,0))="Hoàn thành",INDEX(BE_Tasks!$Z$2:$Z$53,MATCH("BE-C14",BE_Tasks!$A$2:$A$53,0))="")),"Đạt","Chưa đạt") -> Chưa đạt
A9: P7 | B9: Kiểm thử tích hợp & bàn giao | C9: Ba người kiểm thử các phạm vi riêng; A tích hợp bản release sau khi các gate, SQL và tài liệu đạt. | D9: BE-A16, BE-A17, BE-B19, BE-C15, BE-C16 | E9: 21 | F9: G7 | G9: Module tests, concurrency, E2E, SQL tạo mới/nâng cấp và 176 API coverage đạt; không có stub trong cấu hình production. | H9: =IF(AND(AND(INDEX(BE_Tasks!$P$2:$P$53,MATCH("BE-A16",BE_Tasks!$A$2:$A$53,0))="Hoàn thành",INDEX(BE_Tasks!$Z$2:$Z$53,MATCH("BE-A16",BE_Tasks!$A$2:$A$53,0))=""),AND(INDEX(BE_Tasks!$P$2:$P$53,MATCH("BE-A17",BE_Tasks!$A$2:$A$53,0))="Hoàn thành",INDEX(BE_Tasks!$Z$2:$Z$53,MATCH("BE-A17",BE_Tasks!$A$2:$A$53,0))=""),AND(INDEX(BE_Tasks!$P$2:$P$53,MATCH("BE-B19",BE_Tasks!$A$2:$A$53,0))="Hoàn thành",INDEX(BE_Tasks!$Z$2:$Z$53,MATCH("BE-B19",BE_Tasks!$A$2:$A$53,0))=""),AND(INDEX(BE_Tasks!$P$2:$P$53,MATCH("BE-C15",BE_Tasks!$A$2:$A$53,0))="Hoàn thành",INDEX(BE_Tasks!$Z$2:$Z$53,MATCH("BE-C15",BE_Tasks!$A$2:$A$53,0))=""),AND(INDEX(BE_Tasks!$P$2:$P$53,MATCH("BE-C16",BE_Tasks!$A$2:$A$53,0))="Hoàn thành",INDEX(BE_Tasks!$Z$2:$Z$53,MATCH("BE-C16",BE_Tasks!$A$2:$A$53,0))="")),"Đạt","Chưa đạt") -> Chưa đạt

Sheet Ban_giao
A1: Interface | B1: Provider | C1: Task cung cấp | D1: Consumer | E1: Chữ ký đề xuất | F1: Payload / dữ liệu | G1: Ràng buộc | H1: Trạng thái provider
A2: IF-CORE | B2: A | C2: BE-A02 | D2: B, C | E2: ActorContext; ResultEnvelope; DomainError; UnitOfWork; ProcedureRunner | F2: actor.userId/roles/sessionId/requestId; ID string; decimal/date; UoW(connection) hoặc CALL tự transaction | G2: Không tin actor trong body; CALL không chạy bên trong transaction app. | H2: =INDEX(BE_Tasks!$P$2:$P$53,MATCH("BE-A02",BE_Tasks!$A$2:$A$53,0)) -> Chưa làm
A3: IF-TOKEN | B3: A | C3: BE-A07 | D3: C | E3: TokenPort.issue/consume(purpose,target,actor,tx) | F3: Purpose OCCUPANT_LINK; targetRoomTenantId; expiresAt; attempt/consumed/revoked | G3: C mở UoW khi liên kết; adapter A dùng cùng tx, không gọi HTTP hoặc commit riêng. | H3: =INDEX(BE_Tasks!$P$2:$P$53,MATCH("BE-A07",BE_Tasks!$A$2:$A$53,0)) -> Chưa làm
A4: IF-FILES | B4: A | C4: BE-A05 | D4: B, C | E4: FilePort.assertUsable/authorizeDownload(actor,fileId,purpose,context,tx?) | F4: Metadata PRIVATE/ACTIVE, owner, MIME/size/hash/expiry; fileId, không có bucket URL cố định | G4: Context resolver đăng ký theo module; proof đã nộp bất biến, không tạo import vòng. | H4: =INDEX(BE_Tasks!$P$2:$P$53,MATCH("BE-A05",BE_Tasks!$A$2:$A$53,0)) -> Chưa làm
A5: IF-ROOM | B5: B | C5: BE-B04 | D5: A, C | E5: PropertyReadPort.getRentalSnapshot(roomId,actor,tx?) | F5: houseId/landlordId/status/capacity/load/effectiveRight/verificationVersion/asOf | G5: Chỉ snapshot; khi giữ phòng/gia hạn/chuyển phải kiểm tra lại dưới khóa SQL. | H5: =INDEX(BE_Tasks!$P$2:$P$53,MATCH("BE-B04",BE_Tasks!$A$2:$A$53,0)) -> Chưa làm
A6: IF-SERVICE | B6: B | C6: BE-B03 | D6: A | E6: ServiceQuotePort.getEffective(roomId,tx) | F6: name/unit/method/unitPrice từ active_room_services, null kế thừa/0 giữ 0 | G6: A chốt bản sao invoice dưới UoW; B đổi bảng giá không sửa invoice_items. | H6: =INDEX(BE_Tasks!$P$2:$P$53,MATCH("BE-B03",BE_Tasks!$A$2:$A$53,0)) -> Chưa làm
A7: IF-RESIDENT | B7: C | C7: BE-C02 | D7: A, B | E7: ResidencyReadPort.getContractSnapshot/getActiveStay(actor,contractId?,tx?) | F7: currentRevision/payer/member ACTIVE+PLANNED/roomId; field privacy theo actor | G7: Không tính cư trú chỉ bằng status contract/representative. Consumer không ghi room_tenants. | H7: =INDEX(BE_Tasks!$P$2:$P$53,MATCH("BE-C02",BE_Tasks!$A$2:$A$53,0)) -> Chưa làm
A8: IF-CHAT | B8: A | C8: BE-A08 | D8: B, C | E8: ConversationPort.assertInquiry/ensureRoommateConversation(tx,request) | F8: conversationId/postId/roomId/tenantId/landlordId; đúng hai participant | G8: B13 accept và tạo chat dùng cùng tx; không gọi API A qua mạng trong transaction. | H8: =INDEX(BE_Tasks!$P$2:$P$53,MATCH("BE-A08",BE_Tasks!$A$2:$A$53,0)) -> Chưa làm
A9: IF-VIEWING | B9: B | C9: BE-B08 | D9: A, C | E9: ViewingReadPort.getTimeline/getRentalEvidence(actor,context,tx?) | F9: Proposal/schedule hiện tại theo conversation, viewingId/status/tenantDecision cho hợp đồng | G9: Chỉ đọc bảng lịch gốc; người gọi kiểm tra quyền, không tạo bản sao trạng thái trong chat. | H9: =INDEX(BE_Tasks!$P$2:$P$53,MATCH("BE-B08",BE_Tasks!$A$2:$A$53,0)) -> Chưa làm
A10: IF-CONNECTION | B10: B | C10: BE-B04 | D10: A, C | E10: ConnectionReadPort.assertAccepted(actor,connectionId,tx?) | F10: sender/receiver/status/endedAt, không dùng làm consent thuê | G10: A kiểm tra khi mở/gửi, C lấy consent riêng từ đại diện và applicant. | H10: =INDEX(BE_Tasks!$P$2:$P$53,MATCH("BE-B04",BE_Tasks!$A$2:$A$53,0)) -> Chưa làm
A11: IF-EVENT | B11: A | C11: BE-A04 | D11: B, C | E11: EventPort.append(tx,event) + procedure notification dispatcher | F11: eventId/eventKey/recipient/resource/occurredAt; business event version | G11: Service append cùng tx; procedure theo cơ chế sau COMMIT đã chốt, không insert thông báo trùng. | H11: =INDEX(BE_Tasks!$P$2:$P$53,MATCH("BE-A04",BE_Tasks!$A$2:$A$53,0)) -> Chưa làm
A12: IF-AUDIT | B12: A | C12: BE-A04 | D12: B, C | E12: AuditPort.append(tx,actor,action,target,before,after,reason) | F12: Đúng target FK hiện có; extension D14 có migration trước khi dùng | G12: Procedure đã audit thì không ghi lần hai. Không nhét review/template vào target_post_id. | H12: =INDEX(BE_Tasks!$P$2:$P$53,MATCH("BE-A04",BE_Tasks!$A$2:$A$53,0)) -> Chưa làm

Sheet Quyet_dinh
A1: ID | B1: Vấn đề | C1: Người đề xuất | D1: Task | E1: Người cần chốt | F1: Nội dung | G1: Trạng thái quyết định | H1: Kết luận / ngày | I1: Bằng chứng
A2: D01 | B2: Chính sách xác thực | C2: A | D2: BE-A02 | E2: Người phụ trách sản phẩm + cả team | F2: TTL access/refresh/OTP, giới hạn gửi/thử, mật khẩu, provider email/SMS. SQL có expires_at/max_attempts; chưa có cấu hình vận hành. | G2: Chưa chốt
A3: D02 | B3: Thuật toán ghép cặp | C3: B | D3: BE-B15 | E3: Người phụ trách sản phẩm | F3: Điểm số, trọng số, tiêu chí bắt buộc, xử lý thiếu dữ liệu và phiên bản thuật toán; chưa có thuật toán thật. | G3: Chưa chốt
A4: D03 | B4: Đọc chat sau kết thúc kết nối | C4: A | D4: BE-A11 | E4: Người phụ trách sản phẩm + B | F4: Wireframe chỉ mở/gửi khi kết nối còn hiệu lực; đề xuất giữ lịch sử đọc cho hai bên sau ended, chặn gửi. Chưa coi đề xuất là rule đã duyệt. | G4: Chưa chốt
A5: D04 | B5: Kênh email/push | C5: A | D5: BE-A15 | E5: Người phụ trách sản phẩm | F5: users có flags nhưng chưa có provider, device token registry hoặc delivery ledger; chỉ bảo đảm in-app trước. | G5: Chưa chốt
A6: D05 | B6: Kho tệp và hạn lưu | C6: A | D6: BE-A05 | E6: Người phụ trách sản phẩm + B/C | F6: Proof nhà có giới hạn rõ 8×5 MB; giới hạn mục đích khác, quét nội dung, TTL link, hạn lưu CCCD/hợp đồng và xóa object cần chính sách. | G6: Chưa chốt
A7: D06 | B7: Liên kết cư dân với tài khoản | C7: C | D7: BE-C08 | E7: Người phụ trách sản phẩm + A | F7: Xác minh đúng người nhận token OCCUPANT_LINK, kênh gửi và xử lý danh tính không khớp; không ghép theo tên tự khai. | G7: Chưa chốt
A8: D07 | B8: Gửi tin kèm nhiều ảnh atomically | C8: B | D8: BE-B06 | E8: B đề xuất, A tích hợp SQL, C review giao dịch | F8: sp_submit_post chỉ ghi posts và tự COMMIT. Muốn gửi imageFileIds/amenities cùng transaction phải mở rộng procedure/DTO; không bọc CALL trong transaction ngoài. | G8: Chưa chốt
A9: D08 | B9: Get-or-create chat hỏi phòng | C9: A | D9: BE-A08 | E9: A đề xuất, B review ngữ cảnh | F9: Giữ một conversation/room/post ở lớp ghi; gộp nhiều context theo peer ở lớp đọc. Cần unique/khóa cho cặp inquiry để chống trùng đồng thời. | G9: Chưa chốt
A10: D09 | B10: Idempotency và realtime bền vững | C10: A | D10: BE-A04 | E10: Cả team chốt semantics transaction/delivery | F10: Chỉ nhà/proposal/chat có khóa riêng hiện hữu; các POST khác cần idempotency store, request hash và response cache. Replay SSE bền vững cần outbox/event store, không có bảng sẵn. | G10: Chưa chốt
A11: D10 | B11: Xác nhận đúng phiên bản | C11: C | D11: BE-C04 | E11: C đề xuất, A tích hợp SQL | F11: sp_confirm_contract nhận contract+tenant, không nhận expected revision; cần so revisionId dưới cùng khóa transaction trước xác nhận để tránh TOCTOU. | G11: Chưa chốt
A12: D11 | B12: Nhập hợp đồng giấy | C12: C | D12: BE-C13 | E12: Người phụ trách sản phẩm + A/B | F12: Source PAPER_IMPORT có trong SQL nhưng chưa có import transaction đầy đủ; yêu cầu quyền riêng, chứng cứ đã ký và JSON member/state/date. Chưa tính route này sẵn sàng coding ngay. | G12: Chưa chốt
A13: D12 | B13: Thanh toán và trường người ghi nhận | C13: A | D13: BE-A13 | E13: Người phụ trách sản phẩm + C | F13: Chỉ thu toàn bộ do chủ ghi nhận; kiểm tra paid_by_id/payer theo schema. Thanh toán online, trả một phần, hoàn cọc và đối soát cần bảng giao dịch mới, không thuộc API cơ sở. | G13: Chưa chốt
... A16: D15 | B16: Phiên bản CRUD tổng quát | C16: A | D16: BE-A02 | E16: Cả team chốt cơ chế version | F16: Chỉ house.row_version, post.content_version, roommate.profile_version có sẵn. Các tài nguyên khác dùng revision ID/state/updated_at compare-and-swap trong service; không giả có row_version toàn hệ thống. | G16: Chưa chốt

Sheet Worker_OPS
A1: ID | B1: Công việc | C1: Owner | D1: Task | E1: Lịch đề xuất | F1: Nghiệp vụ | G1: Nghiệm thu | H1: Trạng thái task
A2: JOB01 | B2: Hết hạn đề nghị xem | C2: C | D2: BE-C14 | E2: Theo phút (đề xuất) | F2: PENDING có starts_at≤UTC now → EXPIRED. Read/write vẫn kiểm tra thời gian ngay cả khi job trễ. | G2: Retry không tạo thêm lịch; không công khai API job. | H2: =INDEX(BE_Tasks!$P$2:$P$53,MATCH("BE-C14",BE_Tasks!$A$2:$A$53,0)) -> Chưa làm
A3: JOB02 | B3: Hết hạn giữ chỗ thêm người | C3: C | D3: BE-C14 | E3: Theo phút (đề xuất) | F3: APPROVED hold_expires_at≤now → EXPIRED; không chạm COMPLETED/member đã tạo. | G3: Capacity không tính hold quá hạn kể cả job chưa chạy. | H3: =INDEX(BE_Tasks!$P$2:$P$53,MATCH("BE-C14",BE_Tasks!$A$2:$A$53,0)) -> Chưa làm
A4: JOB03 | B4: Quyền nhà quá hạn | C4: B | D4: BE-B18 | E4: Hàng ngày theo Việt Nam (đề xuất) | F4: APPROVED valid_until < todayVN → EXPIRED, giữ hồ sơ/tệp; view hiệu lực chặn ngay. | G4: Không tự kết thúc hợp đồng cũ, không tự xóa tin. | H4: =INDEX(BE_Tasks!$P$2:$P$53,MATCH("BE-B18",BE_Tasks!$A$2:$A$53,0)) -> Chưa làm
A5: JOB04 | B5: Hóa đơn quá hạn | C5: A | D5: BE-A13 | E5: Hàng ngày theo Việt Nam (đề xuất) | F5: UNPAID có due_date<todayVN → OVERDUE; không sửa PAID/CANCELLED. | G5: Lặp không gửi trùng nhắc nợ; event_key ổn định. | H5: =INDEX(BE_Tasks!$P$2:$P$53,MATCH("BE-A13",BE_Tasks!$A$2:$A$53,0)) -> Chưa làm
A6: JOB05 | B6: Dọn token/phiên/tệp staged | C6: A | D6: BE-A15 | E6: Hàng ngày (đề xuất) | F6: Thu hồi/xóa theo chính sách D01/D05, không xóa tệp proof/hợp đồng đang được giữ. | G6: Kiểm tra tham chiếu trước khi xóa object; không log OTP. | H6: =INDEX(BE_Tasks!$P$2:$P$53,MATCH("BE-A15",BE_Tasks!$A$2:$A$53,0)) -> Chưa làm
A7: JOB06 | B7: Phát sự kiện sau commit | C7: A | D7: BE-A14 | E7: Liên tục (đề xuất) | F7: Delivery theo eventId/recipient, retry/backoff/dedupe; chỉ phát dữ liệu tối thiểu. | G7: Giữ nghiệp vụ đúng nếu kênh SSE mất kết nối; client fetch lại. | H7: =INDEX(BE_Tasks!$P$2:$P$53,MATCH("BE-A14",BE_Tasks!$A$2:$A$53,0)) -> Chưa làm
A8: OPS01 | B8: Triển khai schema/migration | C8: A | D8: BE-A17 | E8: Một lần theo phiên bản | F8: Tạo mới HOẶC nâng cấp theo thứ tự README; dừng khi preflight lỗi; không có HTTP endpoint chạy SQL. | G8: Sao lưu + dry run trên DB tạm; không dùng --force. | H8: =INDEX(BE_Tasks!$P$2:$P$53,MATCH("BE-A17",BE_Tasks!$A$2:$A$53,0)) -> Chưa làm
A9: OPS02 | B9: Đối soát dữ liệu cư trú | C9: C | D9: BE-C14 | E9: Khi có cảnh báo (đề xuất) | F9: ACTIVE trên contract đóng vẫn tính tải; báo cáo lỗi thay vì đoán ngày rời/nhận đại diện. | G9: Không tự mở lại hợp đồng, không xóa lịch sử. | H9: =INDEX(BE_Tasks!$P$2:$P$53,MATCH("BE-C14",BE_Tasks!$A$2:$A$53,0)) -> Chưa làm
A10: OPS03 | B10: Hợp đồng hết ngày kết thúc | C10: C | D10: BE-C14 | E10: Cần chốt chính sách | F10: Không tự đóng hợp đồng bỏ lại cư dân ACTIVE. EXPIRED có trong schema; cần quy trình bàn giao/kết thúc/đối soát rõ. | G10: Giữ nghĩa vụ hóa đơn và người ở, không suy đoán đã rời. | H10: =INDEX(BE_Tasks!$P$2:$P$53,MATCH("BE-C14",BE_Tasks!$A$2:$A$53,0)) -> Chưa làm

Sheet QA
A1: ID | B1: Ca kiểm thử | C1: Task chịu trách nhiệm | D1: Owner liên quan | E1: Kịch bản | F1: Kết quả | G1: Bằng chứng / lỗi
A2: QA01 | B2: Giới hạn tin chờ | C2: BE-B06, BE-B19 | D2: B | E2: 4 submit đồng thời cùng room: tối đa 3 PENDING; sửa một tin PENDING không chiếm slot mới. | F2: Chưa chạy
A3: QA02 | B3: Tranh cùng khoảng giờ | C3: BE-B08, BE-B09, BE-B19 | D3: B | E3: 2 accept/propose khác nhau cùng khoảng giờ: chỉ một SCHEDULED; hai lịch liền kề được phép. | F3: Chưa chạy
A4: QA03 | B4: Tranh giữ phòng | C4: BE-B10, BE-C05, BE-C15 | D4: B, C | E4: 2 lịch COMPLETED+AGREED cùng room tạo hợp đồng: chỉ một open contract; rollback mọi side effect bên thua. | F4: Chưa chạy
A5: QA04 | B5: Đóng lịch khi giữ phòng | C5: BE-B10, BE-B19, BE-C05 | D5: B, C | E5: Hủy SCHEDULED tương lai và reject pending còn hạn trên tất cả bài cùng room; giữ lịch đang diễn ra/đã kết thúc. Hủy contract không hồi lịch. | F5: Chưa chạy
A6: QA05 | B6: Giới hạn người ở | C6: BE-B02, BE-C07, BE-C10, BE-C15 | D6: B, C | E6: 2 approve tranh chỗ cuối: chỉ một giữ được. Hold quá 48h không tính capacity/không complete dù job chưa chạy. | F6: Chưa chạy
A7: QA06 | B7: Xác nhận revision cũ | C7: BE-C04, BE-C06, BE-C15 | D7: C | E7: Đại diện mở revision A, chủ gửi B trước confirm: request A phải 409, không xác nhận B ngoài ý muốn (D10). | F7: Chưa chạy
A8: QA07 | B8: Bàn giao đại diện | C8: BE-C11, BE-C15 | D8: C | E8: Người cũ LEFT, người mới cùng hợp đồng ACTIVE, history đúng; request cũ hủy; payer/viewing/giá/ngày hợp đồng cũ giữ. | F8: Chưa chạy
A9: QA08 | B9: Rollback đổi phòng | C9: BE-C12, BE-C15 | D9: C | E9: Đích mất chỗ/quyền trước apply: không đóng nguồn. Thành công chuyển đủ ACTIVE+PLANNED, đích PLANNED chờ move-in. | F9: Chưa chạy
A10: QA09 | B10: Mất quyền nhà | C10: BE-A12, BE-B02, BE-B05, BE-B06, BE-B07, BE-B18, BE-B19, BE-C11, BE-C12, BE-C15 | D10: A, B, C | E10: Hết hạn/thu hồi/đổi định danh/khóa landlord: public ẩn ngay, thuê mới/gia hạn/đích bị chặn, rời/kết thúc cũ vẫn hoạt động. | F10: Chưa chạy
A11: QA10 | B11: Hóa đơn bất biến | C11: BE-A10, BE-A13, BE-A16, BE-B03 | D11: A, B | E11: Đổi giá dịch vụ/đại diện sau phát hành: invoice cũ không đổi. Kỳ trùng bị chặn; override=0 giữ 0; meter cuối<đầu bị chặn. | F11: Chưa chạy
A12: QA11 | B12: Phân quyền chéo tài khoản | C12: BE-A16, BE-C02 | D12: A, C | E12: Thử ID nhà/contract/member/file/chat/invoice của người khác, bao gồm nested route không khớp parent; không lộ PII. | F12: Chưa chạy
A13: QA12 | B13: Idempotency và mất mạng | C13: BE-A04, BE-A14, BE-A16 | D13: A | E13: Retry sau commit/trả response lỗi: cùng key/payload nhận kết quả cũ; khác payload 409; không lặp member/invoice/notification. | F13: Chưa chạy
... A17: QA16 | B17: Tài khoản nhiều vai trò/phiên | C17: BE-A03, BE-A12, BE-A16 | D17: A | E17: Role demo không cấp quyền; users.role không thay bảng role; JWT phiên revoked/LOCKED bị chặn trên mọi endpoint riêng tư. | F17: Chưa chạy

Sheet FE

Sheet AI
